Workbook

Sheet TREINAMENTO DE NR 35
C1: LISTA DE PRESENÇA
C2: NR 35 - NR 35 - TRABALHO EM ALTURA
A3: EMPRESA | D3: OBRA | F3: DATA
A4: Aahbrant Engenharia e Construções LTDA | D4: BEIRA RIO | F4: 46260
A5: INSTRUTOR | D5: LOCAL DO TREINAMENTO | F5: CARGA HORÁRIA
A6: GILTON PEREIRA MIRANDA | D6: SALA DE TREINAMENTO | F6: 8 HORAS
A7: ASSUNTOS ABORDADOS DAS 08:00h às 16:00h
A8: Normas e regulamentos aplicáveis ao trabalho em altura; Análise de Risco e condições impeditivas; Riscos potenciais inerentes ao trabalho em altura e medidas de prevenção e controle; Sistemas, equipamentos e procedimentos de proteção coletiva; Equipamentos de Proteção Individual para trabalho em altura: seleção, inspeção, conservação e limitação de uso; Acidentes típicos em trabalhos em altura; Condutas em situações de emergência, incluindo noções de técnicas de resgate e de primeiros socorros. Atividade pratica e atividade especifica (sistema de ancoragem, linha de vida) Treinamento prático.'PRATICO: CINTO DE SEGURANÇA (SISTEMA DE ANCORAGEM E LINHA DE VIDA)
A29: PRATICO: CINTO DE SEGURANÇA (SISTEMA DE ANCORAGEM E LINHA DE VIDA) ANDAIMES E MONTAGEM DE ANDAIMES.
A32: Nº | B32: Mat: | C32: Nome do colaborador | E32: Função | F32: Assinatura
A33: 1 | B33: 550 | C33: =VLOOKUP(B33,'MATRIZ FUNCIONÁRIOS'!A:H,2,0) -> JOSÉ IGOR GALVÃO SILVA | E33: =VLOOKUP(B33,'MATRIZ FUNCIONÁRIOS'!A:H,3,0) -> AJUDANTE DE OBRAS
A34: 2 | C34: =VLOOKUP(B34,'MATRIZ FUNCIONÁRIOS'!A:H,2,0) -> #N/A | E34: =VLOOKUP(B34,'MATRIZ FUNCIONÁRIOS'!A:H,3,0) -> #N/A
A35: 3 | C35: =VLOOKUP(B35,'MATRIZ FUNCIONÁRIOS'!A:H,2,0) -> #N/A | E35: =VLOOKUP(B35,'MATRIZ FUNCIONÁRIOS'!A:H,3,0) -> #N/A
A36: 4 | C36: =VLOOKUP(B36,'MATRIZ FUNCIONÁRIOS'!A:H,2,0) -> #N/A | E36: =VLOOKUP(B36,'MATRIZ FUNCIONÁRIOS'!A:H,3,0) -> #N/A
A37: 5 | C37: =VLOOKUP(B37,'MATRIZ FUNCIONÁRIOS'!A:H,2,0) -> #N/A | E37: =VLOOKUP(B37,'MATRIZ FUNCIONÁRIOS'!A:H,3,0) -> #N/A
A38: 6 | C38: =VLOOKUP(B38,'MATRIZ FUNCIONÁRIOS'!A:H,2,0) -> #N/A | E38: =VLOOKUP(B38,'MATRIZ FUNCIONÁRIOS'!A:H,3,0) -> #N/A
A39: 7 | C39: =VLOOKUP(B39,'MATRIZ FUNCIONÁRIOS'!A:H,2,0) -> #N/A | E39: =VLOOKUP(B39,'MATRIZ FUNCIONÁRIOS'!A:H,3,0) -> #N/A
A40: 8 | C40: =VLOOKUP(B40,'MATRIZ FUNCIONÁRIOS'!A:H,2,0) -> #N/A | E40: =VLOOKUP(B40,'MATRIZ FUNCIONÁRIOS'!A:H,3,0) -> #N/A
A41: 9 | C41: =VLOOKUP(B41,'MATRIZ FUNCIONÁRIOS'!A:H,2,0) -> #N/A | E41: =VLOOKUP(B41,'MATRIZ FUNCIONÁRIOS'!A:H,3,0) -> #N/A
A42: 10 | C42: =VLOOKUP(B42,'MATRIZ FUNCIONÁRIOS'!A:H,2,0) -> #N/A | E42: =VLOOKUP(B42,'MATRIZ FUNCIONÁRIOS'!A:H,3,0) -> #N/A
A43: 11 | C43: =VLOOKUP(B43,'MATRIZ FUNCIONÁRIOS'!A:H,2,0) -> #N/A | E43: =VLOOKUP(B43,'MATRIZ FUNCIONÁRIOS'!A:H,3,0) -> #N/A
A44: ASSINATURA DO INSTRUTOR DO TREINAMENTO

Sheet CERTIFICADO DE NR 35
C7: CERTIFICADO
C12: Certificamos que o Sr. | G12: ='ORDEM DE SERVIÇO'!B9 -> JOSE ANDRE DE SANTANA CRISPIM | M12: portador do RG: | Q12: ='ORDEM DE SERVIÇO'!B40 -> 3140099
C13: participou do Curso de Formação Básico em Segurança em Trabalho em altura, em conformidade
C14: com a NR 35, no período de | H14: =F22 -> 46260 | K14: na função | M14: ='ORDEM DE SERVIÇO'!D9 -> AJUDANTE DE OBRAS
C15: ='TREINAMENTO DE NR 35'!A29 -> PRATICO: CINTO DE SEGURANÇA (SISTEMA DE ANCORAGEM E LINHA DE VIDA) ANDAIMES E MONTAGEM DE ANDAIMES.
C17: promovido pelo SESMT da Empresa Aahbrant Engenharia e Construções LTDA, CNPJ 23.837.456/0002-97
C18: AV PRESIDENTE EPITACIO PESSOA, 753,ANDAR 11 SALA 1108,ESTADOS, JOAO PESSOA-PB
C19: OBRA BEIRA RIO
C22: ESTADOS, JOAO PESSOA-PB | F22: ='TREINAMENTO DE NR 35'!F4 -> 46260
C26: GILTON PEREIRA MIRANDA | N26: ='ORDEM DE SERVIÇO'!B39 -> JOSE ANDRE DE SANTANA CRISPIM
C27: TEC SEGURANÇA DO TRABALHO | N27: ='ORDEM DE SERVIÇO'!B41 -> AJUDANTE DE OBRAS
C28: Registro MTE-0123056/SP
C29: INSTRUTOR
O30: ESTADOS, JOAO PESSOA-PB
C40: CONTEUDO PROGRAMÁTICO
C46: Normas e regulamentos aplicáveis ao trabalho em altura; Análise de Risco e condições impeditivas; Riscos potenciais inerentes ao trabalho em altura e medidas de prevenção e controle; Sistemas, equipamentos e procedimentos de proteção coletiva; Equipamentos de Proteção Individual para trabalho em altura: seleção, inspeção, conservação e limitação de uso; Acidentes típicos em trabalhos em altura; Condutas em situações de emergência, incluindo noções de técnicas de resgate e de primeiros socorros. Atividade pratica e atividade especifica (sistema de ancoragem, linha de vida) Treinamento prático.
C64: ='TREINAMENTO DE NR 35'!A29 -> PRATICO: CINTO DE SEGURANÇA (SISTEMA DE ANCORAGEM E LINHA DE VIDA) ANDAIMES E MONTAGEM DE ANDAIMES.
C68: GILTON PEREIRA MIRANDA | I68: ='ORDEM DE SERVIÇO'!B39 -> JOSE ANDRE DE SANTANA CRISPIM | N68: AV PRESIDENTE EPITACIO PESSOA, 753,ANDAR 11 SALA 1108
C69: TEC SEGURANÇA DO TRABALHO | I69: ='ORDEM DE SERVIÇO'!B41 -> AJUDANTE DE OBRAS | O69: ESTADOS, JOAO PESSOA-PB
C70: Registro MTE-SP 012305/6
C71: INSTRUTOR

Sheet TREINAMENTO DE NR 11
C1: LISTA DE PRESENÇA
C2: NR-11 TREINAMENTO ESPECIFICO OPERADOR DE MAQUINAS
A3: EMPRESA | F3: DATA
A4: Aahbrant Engenharia e Construções LTDA | D4: OBRA BEIRA RIO | F4: 45757
A5: INSTRUTOR | D5: LOCAL DO TREINAMENTO | F5: CARGA HORÁRIA
A6: GILTON PEREIRA MIRANDA | D6: SALA DE TREINAMENTO AAHBRANT | F6: 8 HORAS
A7: ASSUNTOS ABORDADOS DAS 08:00h às 16:00h
A8: Princípios básicos da operação de máquinas pesadas;
A9: Técnicas de operação de máquinas pesadas como escavação, movimentação de cargas, etc;
A10: Normas regulamentadoras (como as NRs 05, 06, 07, 09 e 11);
A11: Responsabilidades do operador de máquinas;
A12: Principais sistemas e componentes de máquinas e equipamentos;
A13: Inspeção inicial da máquina ou equipamento;
A14: A importância da manutenção corretiva e preventiva;
A15: Lista de verificação (checklist);
A16: Cuidados para a utilização da máquina;
A17: Práticas recomendáveis para o uso de máquinas e equipamentos;
A18: Cuidados com pneus e rodas;
... A24: Treinamento para as máquinas: CAMINHÃO MUNCK, ROLO COMPACTADOR, ROLO CHAPA E PNEU, BOBCAT, ROLO PATA DE CARNEIRO, FRESADORA DE ASFALTICO, ESCAVADEIRA HIDRÁULICA RETROESCAVADEIRA E MOTONIVELADORA (PATROL).
A26: Nº | B26: Mat: | C26: Nome do colaborador | E26: Função | F26: Assinatura
A27: 1 | B27: ='ORDEM DE SERVIÇO'!D7 -> 25 | C27: =VLOOKUP(B27,'MATRIZ FUNCIONÁRIOS'!A:H,2,0) -> JOSE ANDRE DE SANTANA CRISPIM | E27: =VLOOKUP(B27,'MATRIZ FUNCIONÁRIOS'!A:H,3,0) -> AJUDANTE DE OBRAS | F27: X
A28: 2 | C28: =VLOOKUP(B28,'MATRIZ FUNCIONÁRIOS'!A:H,2,0) -> #N/A | E28: =VLOOKUP(B28,'MATRIZ FUNCIONÁRIOS'!A:H,3,0) -> #N/A
A29: 3 | C29: =VLOOKUP(B29,'MATRIZ FUNCIONÁRIOS'!A:H,2,0) -> #N/A | E29: =VLOOKUP(B29,'MATRIZ FUNCIONÁRIOS'!A:H,3,0) -> #N/A
A30: 4 | C30: =VLOOKUP(B30,'MATRIZ FUNCIONÁRIOS'!A:H,2,0) -> #N/A | E30: =VLOOKUP(B30,'MATRIZ FUNCIONÁRIOS'!A:H,3,0) -> #N/A
A31: 5 | C31: =VLOOKUP(B31,'MATRIZ FUNCIONÁRIOS'!A:H,2,0) -> #N/A | E31: =VLOOKUP(B31,'MATRIZ FUNCIONÁRIOS'!A:H,3,0) -> #N/A
A32: 6 | C32: =VLOOKUP(B32,'MATRIZ FUNCIONÁRIOS'!A:H,2,0) -> #N/A | E32: =VLOOKUP(B32,'MATRIZ FUNCIONÁRIOS'!A:H,3,0) -> #N/A
A33: 7 | C33: =VLOOKUP(B33,'MATRIZ FUNCIONÁRIOS'!A:H,2,0) -> #N/A | E33: =VLOOKUP(B33,'MATRIZ FUNCIONÁRIOS'!A:H,3,0) -> #N/A
A34: 8 | C34: =VLOOKUP(B34,'MATRIZ FUNCIONÁRIOS'!A:H,2,0) -> #N/A | E34: =VLOOKUP(B34,'MATRIZ FUNCIONÁRIOS'!A:H,3,0) -> #N/A
A35: 9 | C35: =VLOOKUP(B35,'MATRIZ FUNCIONÁRIOS'!A:H,2,0) -> #N/A | E35: =VLOOKUP(B35,'MATRIZ FUNCIONÁRIOS'!A:H,3,0) -> #N/A
A36: 10 | C36: =VLOOKUP(B36,'MATRIZ FUNCIONÁRIOS'!A:H,2,0) -> #N/A | E36: =VLOOKUP(B36,'MATRIZ FUNCIONÁRIOS'!A:H,3,0) -> #N/A
A37: 11 | C37: =VLOOKUP(B37,'MATRIZ FUNCIONÁRIOS'!A:H,2,0) -> #N/A | E37: =VLOOKUP(B37,'MATRIZ FUNCIONÁRIOS'!A:H,3,0) -> #N/A
A38: ASSINATURA DO INSTRUTOR DO TREINAMENTO

Sheet CERTIFICADO DE NR 11
C7: CERTIFICADO
C12: Certificamos que o Sr. | G12: ='ORDEM DE SERVIÇO'!B9 -> JOSE ANDRE DE SANTANA CRISPIM | M12: portador do RG: | Q12: ='ORDEM DE SERVIÇO'!B40 -> 3140099
C13: participou do Curso de Segurança em Trabalho em Maquinas e Equipamentos, em conformidade
C14: com a NR 12, no período de | H14: =F23 -> 45757 | K14: na função | M14: ='ORDEM DE SERVIÇO'!D9 -> AJUDANTE DE OBRAS
C15: ='TREINAMENTO DE NR 11'!A24 -> Treinamento para as máquinas: CAMINHÃO MUNCK, ROLO COMPACTADOR, ROLO CHAPA E PNEU, BOBCAT, ROLO PATA DE CARNEIRO, FRESADORA DE ASFALTICO, ESCAVADEIRA HIDRÁULICA RETROESCAVADEIRA E MOTONIVELADORA (PATROL).
C18: promovido pelo SESMT da EmpresaAahbrant Engenharia e Construções LTDA, CNPJ 23.837.456/0002-97 ,
C19: sede da empresa AV PRESIDENTE EPITACIO PESSOA, 753,ANDAR 11 SALA 1108,ESTADOS, JOAO PESSOA-PB
C21: com carga horária de 08 h.
C23: Barueri, SP, data: | F23: ='TREINAMENTO DE NR 11'!F4 -> 45757
N26: x
C27: GILTON PEREIRA MIRANDA | I27: GILTON PEREIRA MIRANDA | N27: ='ORDEM DE SERVIÇO'!B39 -> JOSE ANDRE DE SANTANA CRISPIM
C28: TEC SEGURANÇA DO TRABALHO | I28: TÉC SEGURANÇA DO TRABALHO | N28: ='ORDEM DE SERVIÇO'!B41 -> AJUDANTE DE OBRAS
C29: Registro MTE-0123056/SP | I29: MTE-0123056/SP
I30: RESP TÉCNICO | N30: AV PRESIDENTE EPITACIO PESSOA, 753,ANDAR 11 SALA 1108
O31: ESTADOS, JOAO PESSOA-PB
C40: CONTEUDO PROGRAMÁTICO
C46: A capacitação para operação segura de máquinas.
C47: a) descrição e identificação dos riscos associados com cada máquina e equipamento e as proteções específicas contra cada um deles;
C48: b) funcionamento das proteções; como e por que devem ser usadas;
C49: c) como e em que circunstâncias uma proteção pode ser removida, e por quem, sendo na maioria dos casos, somente o pessoal de inspeção ou manutenção;
C50: d) o que fazer, por exemplo, contatar o supervisor, se uma proteção foi danificada ou se perdeu sua função, deixando
C51: de garantir uma segurança adequada;
C52: e) os princípios de segurança na utilização da máquina ou equipamento;
C53: f) segurança para riscos mecânicos, elétricos e outros relevantes;
C54: g) método de trabalho seguro;
C55: h) permissão de trabalho; e
C56: i) sistema de bloqueio de funcionamento da máquina e equipamento durante operações de inspeção, limpeza, lubrificação e manutenção.
... C65: h) noções sobre prestação de primeiros socorros.
C66: ='TREINAMENTO DE NR 11'!A24 -> Treinamento para as máquinas: CAMINHÃO MUNCK, ROLO COMPACTADOR, ROLO CHAPA E PNEU, BOBCAT, ROLO PATA DE CARNEIRO, FRESADORA DE ASFALTICO, ESCAVADEIRA HIDRÁULICA RETROESCAVADEIRA E MOTONIVELADORA (PATROL).
C68: GILTON PEREIRA MIRANDA | I68: ='ORDEM DE SERVIÇO'!B39 -> JOSE ANDRE DE SANTANA CRISPIM
C69: TÉC SEGURANÇA DO TRABALHO | I69: ='ORDEM DE SERVIÇO'!B41 -> AJUDANTE DE OBRAS
C70: MTE-0123056/SP
C71: RESP TÉCNICO

Sheet TREINAMENTO DE NR 12 PORTATEIS
C1: LISTA DE PRESENÇA
C2: NR 12 - SEGURANÇA NO TRABALHO EM MÁQUINAS E EQUIPAMENTOS
A3: EMPRESA | D3: LOCAL DO TREINAMENTO | F3: DATA
A4: Aahbrant Engenharia e Construções LTDA | D4: SALA DE TREINAMENTO-SEDE AAHBRANT | F4: 46252
A5: INSTRUTOR | D5: LOCAL DO TREINAMENTO | F5: CARGA HORÁRIA
A6: GILTON PEREIRA MIRANDA | D6: SALA DE TREINAMENTO | F6: 6 HORAS
A7: ASSUNTOS ABORDADOS DAS 08:00h às 16:00h
A8: Capacitação para operação segura de máquinas. a) descrição e identificação dos riscos associados com cada máquina e equipamento e as proteções específicas contra cada um deles; b) funcionamento das proteções; como e por que devem ser usadas; c) como e em que circunstâncias uma proteção pode ser removida, e por quem, sendo na maioria dos casos, somente o pessoal de inspeção ou manutenção; d) o que fazer, por exemplo, contatar o supervisor,se uma proteção foi danificada ou se perdeu sua função,deixando de garantir uma segurança adequada; e) os princípios de segurança na utilização da máquina ou equipamento; f) segurança para riscos mecânicos, elétricos e outros relevantes; g) método de trabalho seguro; h) permissão de trabalho; e i) sistema de bloqueio de funcionamento da máquina e equipamento durante operações de inspeção, limpeza, lubrificação e manutenção. Etapas teórica e prática a) noções sobre legislação de trânsito e de legislação de segurança e saúde no trabalho; b) noções sobre acidentes e doenças decorrentes da exposição aos riscos existentes na máquina, equipamentos e implementos; c) medidas de controle dos riscos: EPC e EPI; d) operação com segurança da máquina ou equipamento; e) inspeção, regulagem e manutenção com segurança; f) sinalização de segurança; g) procedimentos em situação de emergência; e h) noções sobre prestação de primeiros socorros. Maquinas utilizadas nas aulas praticas:
A30: SERRA CIRCULAR, MAKITA, FERRAMENTAS ELÉTRICAS E DIVERSAS
A34: Nº | B34: Mat: | C34: Nome do colaborador | E34: Função | F34: Assinatura
A35: 1 | B35: 548 | C35: =VLOOKUP(B35,'MATRIZ FUNCIONÁRIOS'!A:H,2,0) -> LUCIANO DA SILVA | E35: =VLOOKUP(B35,'MATRIZ FUNCIONÁRIOS'!A:H,3,0) -> AJUDANTE DE OBRAS
A36: 2 | C36: =VLOOKUP(B36,'MATRIZ FUNCIONÁRIOS'!A:H,2,0) -> #N/A | E36: =VLOOKUP(B36,'MATRIZ FUNCIONÁRIOS'!A:H,3,0) -> #N/A
A37: 3 | C37: =VLOOKUP(B37,'MATRIZ FUNCIONÁRIOS'!A:H,2,0) -> #N/A | E37: =VLOOKUP(B37,'MATRIZ FUNCIONÁRIOS'!A:H,3,0) -> #N/A
A38: 4 | C38: =VLOOKUP(B38,'MATRIZ FUNCIONÁRIOS'!A:H,2,0) -> #N/A | E38: =VLOOKUP(B38,'MATRIZ FUNCIONÁRIOS'!A:H,3,0) -> #N/A
A39: 5 | C39: =VLOOKUP(B39,'MATRIZ FUNCIONÁRIOS'!A:H,2,0) -> #N/A | E39: =VLOOKUP(B39,'MATRIZ FUNCIONÁRIOS'!A:H,3,0) -> #N/A
A40: 6 | C40: =VLOOKUP(B40,'MATRIZ FUNCIONÁRIOS'!A:H,2,0) -> #N/A | E40: =VLOOKUP(B40,'MATRIZ FUNCIONÁRIOS'!A:H,3,0) -> #N/A
A41: 7 | C41: =VLOOKUP(B41,'MATRIZ FUNCIONÁRIOS'!A:H,2,0) -> #N/A | E41: =VLOOKUP(B41,'MATRIZ FUNCIONÁRIOS'!A:H,3,0) -> #N/A
A42: 8 | C42: =VLOOKUP(B42,'MATRIZ FUNCIONÁRIOS'!A:H,2,0) -> #N/A | E42: =VLOOKUP(B42,'MATRIZ FUNCIONÁRIOS'!A:H,3,0) -> #N/A
A43: 9 | C43: =VLOOKUP(B43,'MATRIZ FUNCIONÁRIOS'!A:H,2,0) -> #N/A | E43: =VLOOKUP(B43,'MATRIZ FUNCIONÁRIOS'!A:H,3,0) -> #N/A
A44: 10 | C44: =VLOOKUP(B44,'MATRIZ FUNCIONÁRIOS'!A:H,2,0) -> #N/A | E44: =VLOOKUP(B44,'MATRIZ FUNCIONÁRIOS'!A:H,3,0) -> #N/A
A45: 11 | C45: =VLOOKUP(B45,'MATRIZ FUNCIONÁRIOS'!A:H,2,0) -> #N/A | E45: =VLOOKUP(B45,'MATRIZ FUNCIONÁRIOS'!A:H,3,0) -> #N/A
A46: ASSINATURA DO INSTRUTOR DO TREINAMENTO

Sheet CERTIFICADO DE NR 12 PORTATEIS
C7: CERTIFICADO
C12: Certificamos que o Sr. | G12: ='ORDEM DE SERVIÇO'!B9 -> JOSE ANDRE DE SANTANA CRISPIM | M12: portador do RG: | Q12: ='ORDEM DE SERVIÇO'!B40 -> 3140099
C13: participou do Curso de Segurança em Trabalho em Maquinas e Equipamentos, em conformidade
C14: com a NR 12, no período de | H14: =F21 -> 46252 | K14: na função de | M14: ='ORDEM DE SERVIÇO'!D9 -> AJUDANTE DE OBRAS
C15: para Maquinas | F15: SERRA CIRCULAR, MAKITA, FERRAMENTAS ELÉTRICAS E DIVERSAS
C16: promovido pelo SESMT da Empresa , Aahbrant Engenharia e Construções LTDA, CNPJ 23.837.456/0002-9
C17: sede da empresa na AV PRESIDENTE EPITACIO PESSOA, 753,ANDAR 11 SALA 1108,ESTADOS, JOAO PESSOA-PB.
C18: , com carga horária de 06 horas.
C21: JOÁO PESSOA, PB | F21: 46252
C26: GILTON PEREIRA MIRANDA | N26: ='ORDEM DE SERVIÇO'!B39 -> JOSE ANDRE DE SANTANA CRISPIM
C27: TEC SEGURANÇA DO TRABALHO | N27: ='ORDEM DE SERVIÇO'!B41 -> AJUDANTE DE OBRAS
C28: Registro MTE-0123056/SP | N28: Registro MTE-SP 012305/6
C40: CONTEUDO PROGRAMÁTICO
C46: A capacitação para operação segura de máquinas.
C47: a) descrição e identificação dos riscos associados com cada máquina e equipamento e as proteções específicas contra cada um deles;
C48: b) funcionamento das proteções; como e por que devem ser usadas;
C49: c) como e em que circunstâncias uma proteção pode ser removida, e por quem, sendo na maioria dos casos, somente o pessoal de inspeção ou manutenção;
C50: d) o que fazer, por exemplo, contatar o supervisor, se uma proteção foi danificada ou se perdeu sua função, deixando de garantir uma segurança adequada;
C51: e) os princípios de segurança na utilização da máquina ou equipamento;
C52: f) segurança para riscos mecânicos, elétricos e outros relevantes;
C53: g) método de trabalho seguro;
C54: h) permissão de trabalho; e
C55: i) sistema de bloqueio de funcionamento da máquina e equipamento durante operações de inspeção, limpeza, lubrificação e manutenção.
C57: Etapas teórica e prática
... C65: h) noções sobre prestação de primeiros socorros.
C66: Maquina utilizados nas aulas praticas: | H66: =F15 -> SERRA CIRCULAR, MAKITA, FERRAMENTAS ELÉTRICAS E DIVERSAS

Sheet TREINAMENTO DE NR 12
C1: LISTA DE PRESENÇA
C2: NR 12 - SEGURANÇA NO TRABALHO EM MÁQUINAS E EQUIPAMENTOS
A3: EMPRESA | F3: DATA
A4: Aahbrant Engenharia e Construções LTDA | F4: 45769
A5: INSTRUTOR | D5: LOCAL DO TREINAMENTO | F5: CARGA HORÁRIA
A6: GILTON PEREIRA MIRANDA | D6: SALA DE TREINAMENTO AAHBRANT | F6: 08 HORAS
A7: ASSUNTOS ABORDADOS DAS 08:00h às 16:00h
A8: Capacitação para operação segura de máquinas. a) descrição e identificação dos riscos associados com cada máquina e equipamento e as proteções específicas contra cada um deles; b) funcionamento das proteções; como e por que devem ser usadas; c) como e em que circunstâncias uma proteção pode ser removida, e por quem, sendo na maioria dos casos, somente o pessoal de inspeção ou manutenção; d) o que fazer, por exemplo, contatar o supervisor,se uma proteção foi danificada ou se perdeu sua função,deixando de garantir uma segurança adequada; e) os princípios de segurança na utilização da máquina ou equipamento; f) segurança para riscos mecânicos, elétricos e outros relevantes; g) método de trabalho seguro; h) permissão de trabalho; e i) sistema de bloqueio de funcionamento da máquina e equipamento durante operações de inspeção, limpeza, lubrificação e manutenção. Etapas teórica e prática a) noções sobre legislação de trânsito e de legislação de segurança e saúde no trabalho; b) noções sobre acidentes e doenças decorrentes da exposição aos riscos existentes na máquina, equipamentos e implementos; c) medidas de controle dos riscos: EPC e EPI; d) operação com segurança da máquina ou equipamento; e) inspeção, regulagem e manutenção com segurança; f) sinalização de segurança; g) procedimentos em situação de emergência; e h) noções sobre prestação de primeiros socorros.
A29: Treinamento para as máquinas: ROLO COMPACTADOR, ROLO CHAPA E PNEU, BOBCAT, ROLO PATA DE CARNEIRO, FRESADORA DE ASFALTICO, ESCAVADEIRA HIDRÁULICA RETROESCAVADEIRA E MOTONIVELADORA (PATROL).
A32: Nº | B32: Mat: | C32: Nome do colaborador | E32: Função | F32: Assinatura
A33: 1 | B33: ='ORDEM DE SERVIÇO'!D7 -> 25 | C33: =VLOOKUP(B33,'MATRIZ FUNCIONÁRIOS'!A:H,2,0) -> JOSE ANDRE DE SANTANA CRISPIM | E33: =VLOOKUP(B33,'MATRIZ FUNCIONÁRIOS'!A:H,3,0) -> AJUDANTE DE OBRAS | F33: X
A34: 2 | C34: =VLOOKUP(B34,'MATRIZ FUNCIONÁRIOS'!A:H,2,0) -> #N/A | E34: =VLOOKUP(B34,'MATRIZ FUNCIONÁRIOS'!A:H,3,0) -> #N/A
A35: 3 | C35: =VLOOKUP(B35,'MATRIZ FUNCIONÁRIOS'!A:H,2,0) -> #N/A | E35: =VLOOKUP(B35,'MATRIZ FUNCIONÁRIOS'!A:H,3,0) -> #N/A
A36: 4 | C36: =VLOOKUP(B36,'MATRIZ FUNCIONÁRIOS'!A:H,2,0) -> #N/A | E36: =VLOOKUP(B36,'MATRIZ FUNCIONÁRIOS'!A:H,3,0) -> #N/A
A37: 5 | C37: =VLOOKUP(B37,'MATRIZ FUNCIONÁRIOS'!A:H,2,0) -> #N/A | E37: =VLOOKUP(B37,'MATRIZ FUNCIONÁRIOS'!A:H,3,0) -> #N/A
A38: 6 | C38: =VLOOKUP(B38,'MATRIZ FUNCIONÁRIOS'!A:H,2,0) -> #N/A | E38: =VLOOKUP(B38,'MATRIZ FUNCIONÁRIOS'!A:H,3,0) -> #N/A
A39: 7 | C39: =VLOOKUP(B39,'MATRIZ FUNCIONÁRIOS'!A:H,2,0) -> #N/A | E39: =VLOOKUP(B39,'MATRIZ FUNCIONÁRIOS'!A:H,3,0) -> #N/A
A40: 8 | C40: =VLOOKUP(B40,'MATRIZ FUNCIONÁRIOS'!A:H,2,0) -> #N/A | E40: =VLOOKUP(B40,'MATRIZ FUNCIONÁRIOS'!A:H,3,0) -> #N/A
A41: 9 | C41: =VLOOKUP(B41,'MATRIZ FUNCIONÁRIOS'!A:H,2,0) -> #N/A | E41: =VLOOKUP(B41,'MATRIZ FUNCIONÁRIOS'!A:H,3,0) -> #N/A
A42: 10 | C42: =VLOOKUP(B42,'MATRIZ FUNCIONÁRIOS'!A:H,2,0) -> #N/A | E42: =VLOOKUP(B42,'MATRIZ FUNCIONÁRIOS'!A:H,3,0) -> #N/A
A43: 11 | C43: =VLOOKUP(B43,'MATRIZ FUNCIONÁRIOS'!A:H,2,0) -> #N/A | E43: =VLOOKUP(B43,'MATRIZ FUNCIONÁRIOS'!A:H,3,0) -> #N/A
A44: ASSINATURA INSTRUTOR DO TREINAMENTO

Sheet CERTIFICADO DE NR 12
C7: CERTIFICADO
C12: Certificamos que o Sr. | G12: ='ORDEM DE SERVIÇO'!B9 -> JOSE ANDRE DE SANTANA CRISPIM | M12: portador do RG: | Q12: ='ORDEM DE SERVIÇO'!B40 -> 3140099
C13: participou do Curso de Segurança em Trabalho em Maquinas e Equipamentos, em conformidade
C14: com a NR 12, no período de | H14: =F23 -> 45758 | K14: na função | M14: ='ORDEM DE SERVIÇO'!D9 -> AJUDANTE DE OBRAS
C15: ='TREINAMENTO DE NR 12'!A29 -> Treinamento para as máquinas: ROLO COMPACTADOR, ROLO CHAPA E PNEU, BOBCAT, ROLO PATA DE CARNEIRO, FRESADORA DE ASFALTICO, ESCAVADEIRA HIDRÁULICA RETROESCAVADEIRA E MOTONIVELADORA (PATROL).
C18: promovido pelo SESMT da Empresa Aahbrant Engenharia e Construções LTDA, CNPJ 23.837.456/0002-97
C19: sede da empresa na sede da empresa AV PRESIDENTE EPITACIO PESSOA, 753,ANDAR 11 SALA 1108,ESTADOS, JOAO PESSOA-PB
C21: com carga horária de 08 h.
C23: JOÃO PESOA-PB | F23: 45758
N26: X
C27: GILTON PEREIRA MIRANDA | N27: ='ORDEM DE SERVIÇO'!B39 -> JOSE ANDRE DE SANTANA CRISPIM
C28: TEC SEGURANÇA DO TRABALHO | N28: ='ORDEM DE SERVIÇO'!B41 -> AJUDANTE DE OBRAS
C29: REGISTRO - MTE-0123056/SP
C40: CONTEUDO PROGRAMÁTICO
C46: A capacitação para operação segura de máquinas.
C47: a) descrição e identificação dos riscos associados com cada máquina e equipamento e as proteções específicas contra cada um deles;
C48: b) funcionamento das proteções; como e por que devem ser usadas;
C49: c) como e em que circunstâncias uma proteção pode ser removida, e por quem, sendo na maioria dos casos, somente o pessoal de inspeção ou manutenção;
C50: d) o que fazer, por exemplo, contatar o supervisor, se uma proteção foi danificada ou se perdeu sua função, deixando
C51: de garantir uma segurança adequada;
C52: e) os princípios de segurança na utilização da máquina ou equipamento;
C53: f) segurança para riscos mecânicos, elétricos e outros relevantes;
C54: g) método de trabalho seguro;
C55: h) permissão de trabalho; e
... C65: h) noções sobre prestação de primeiros socorros.
C66: ='TREINAMENTO DE NR 12'!A29 -> Treinamento para as máquinas: ROLO COMPACTADOR, ROLO CHAPA E PNEU, BOBCAT, ROLO PATA DE CARNEIRO, FRESADORA DE ASFALTICO, ESCAVADEIRA HIDRÁULICA RETROESCAVADEIRA E MOTONIVELADORA (PATROL).
C68: GILTON PEREIRA MIRANDA | I68: ='ORDEM DE SERVIÇO'!B39 -> JOSE ANDRE DE SANTANA CRISPIM
C69: TEC SEGURANÇA DO TRABALHO | I69: ='ORDEM DE SERVIÇO'!B41 -> AJUDANTE DE OBRAS
C70: MTE-SP 0123056
D71: RESP TÉCNICO

Sheet TREINAMENTO DE INTEGRAÇÃO
C1: FORMULÁRIO | F1: FO.M. VER. 00 fl. 01/01
C2: TREINAMENTO DE INTEGRAÇÃO
A3: Nome da Empresa: | F3: Data:
A4: Aahbrant Engenharia e Construções LTDA | F4: 46259
A5: Responsável pelo treinamento: | F5: Assinatura do Responsável:
A6: GILTON PEREIRA MIRANDA
A7: Declaro ter participado do Treinamento de Integração NA SEDE DA EMPRESA TALUDE CONSTRUÇÕES S.A , dentro do horário normal de trabalho, com carga horária de quatro (04) horas conforme 18.14 Anexo-l, recebendo orientações e informações necessárias para que eu possa iniciar meu trabalho, conforme descrito abaixo: • Informações sobre as condições e meio ambiente de trabalho; • PGR - Plano de Gerenciamento de Resíduos; • Contenção de Vazamento; • Perigos e Riscos, Aspectos e Impactos Ambientais; • Uso adequado dos Equipamentos de Proteção Individual; • Informações sobre os Equipamentos de Proteção Coletiva (EPC) existentes no canteiro de obras; • APR - Análise Preliminar de Riscos, PTR- Permissão de Trabalho de Riscos; • Trabalho em Altura; Instalações Elétricas; • Investigação e Análise de Incidentes, Comunicação de Incidentes; • Plano de Atendimento a Emergência (PAE); • PGR, PCMAT e PCMSO; • Noções básicas sobre SGQ na obra; • Monitoramento de recebimento, inspeção e armazenamento de materiais; • Política de Segurança do Trabalho Talude (Política do Sistema de Gestão Integrado CCR AutoBan); • Inspeção em Maquinas e equipamentos; • Isolamento e sinalização de segurança vias e marginais; • Proteção contra quedas; • Organização e limpeza do canteiro, preservação de equipamentos e ferramentas e terminalidade dos serviços; • Recomendações e Ações de Prevenção Covid 19 conforme legislação vigente. , AlcoolXDrogas . Manual de Normas e Condutas para Motorista no Trânsito; ECONOMIA DE ENERGIA; COLETA SELETIVA E RECICLAGEM. Declaro ainda que recebi cópias de procedimentos das operações a serem realizadas, conforme a NR-18.28.4. Estou ciente dos riscos inerentes ao trabalho que vou executar e sei que é necessário trabalhar com segurança, cumprindo e obedecendo as regras, regulamentos, procedimentos e padrões da minha empresa. Estou ciente que, se eu não cumpri-los, posso ser penalizado inclusive com a minha demissão.
A34: Nº | B34: Mat: | C34: Nome do colaborador | E34: Função | F34: Assinatura
A35: 1 | B35: ='ORDEM DE SERVIÇO'!D7 -> 25 | C35: =VLOOKUP(B35,'MATRIZ FUNCIONÁRIOS'!A:H,2,0) -> JOSE ANDRE DE SANTANA CRISPIM | E35: =VLOOKUP(B35,'MATRIZ FUNCIONÁRIOS'!A:H,3,0) -> AJUDANTE DE OBRAS | F35: X

Sheet CERTIFICADO DE NR 18
C7: CERTIFICADO
C12: Certificamos que o Sr.(a) | G12: ='ORDEM DE SERVIÇO'!B9 -> JOSE ANDRE DE SANTANA CRISPIM | M12: portador do RG: | Q12: ='ORDEM DE SERVIÇO'!B40 -> 3140099
C13: participou do Treinamento Admissional para novos funcionários, conforme NR-18, item 18.14 Anexo-l
C14: aprovada pela Portaria 3.214/78 do Ministério do Trabalho, realizada no dia | Q14: 46259
C15: promovido pelo SESMT da Empresa, Aahbrant Engenharia e Construções LTDA, CNPJ 23.837.456/0002-97
C16: sede da empresa na Estrada Ibateguara, 170 Jardim Mutinga, Tamboré, Barueri, SP
C17: realizado na – sede da empresa AV PRESIDENTE EPITACIO PESSOA, 753,ANDAR 11 SALA 1108,ESTADOS, JOAO PESSOA-PB
C18: com carga horária de 4 horas
C19: JOÁO PESSOA, PB, data: | F19: =Q14 -> 46259
C25: GILTON PEREIRA MIRANDA | N25: ='ORDEM DE SERVIÇO'!B39 -> JOSE ANDRE DE SANTANA CRISPIM
C26: TEC SEGURANÇA DO TRABALHO | N26: ='ORDEM DE SERVIÇO'!B41 -> AJUDANTE DE OBRAS
C27: Registro MTE-0123056/SP
C40: CERTIFICADO
C46: Informações sobre as condições e meio ambiente de trabalho;PGR - Plano de Gerenciamento de Resíduos; Contenção de Vazamento; Perigos e Riscos, Aspectos e Impactos Ambientais; Uso adequado dos Equipamentos de Proteção Individual;
C51: Informações sobre os Equipamentos de Proteção Coletiva (EPC) existentes no canteiro de obras; APR - Análise Preliminar da riscos, PTR- Permissão de Trabalho de Riscos;
C54: Trabalho em Altura; Instalações Elétricas; Investigação e Análise de Incidentes, Comunicação de Incidentes; Plano de Atendimento a Emergência (PAE);PGR e PCMSO; Noções básicas sobre SGQ na obra; Monitoramento de recebimento, inspeção e armazenamento de materiais; Política de Segurança do Trabalho Talude; Inspeção em Maquinas e equipamentos; Isolamento e sinalização de segurança vias e marginais;
C59: Proteção contra quedas; Organização e limpeza do canteiro, preservação de equipamentos e ferramentas; Recomendações e Ações de Prevenção Covid 19 conforme legislação vigente; Álcool X Drogas; Manual de Normas e Condutas para Motorista no Trânsito.
I64: GILTON PEREIRA MIRANDA | N64: ='ORDEM DE SERVIÇO'!B9 -> JOSE ANDRE DE SANTANA CRISPIM
I65: TEC SEGURANÇA DO TRABALHO | N65: ='ORDEM DE SERVIÇO'!D9 -> AJUDANTE DE OBRAS
I66: Registro MTE-SP 0123056
I67: INSTRUTOR

Sheet ORDEM DE SERVIÇO
A1: AAHBRANT ENGENHARIA E CONSTRUÇÕES LTDA
A2: INSTRUÇÃO DE SEGURANÇA DO TRABALHO
A3: ORDEM DE SERVIÇO SOBRE HIGIENE, SEGURANÇA E MEDICINA DO TRABALHO
A4: Conforme estabelecido no item 1.7, letra “b”, NR-01 da Portaria 3214/MTE, cabe ao empregador elaborar Ordem de Serviço (OS) sobre Segurança e Medicina do Trabalho, dando ciência aos empregados.
A5: ORDEM DE SERVIÇO
A6: EMPRESA: | B6: AAHBRANT ENGENHARIA E CONSTRUÇÕES LTDA | C6: SETOR: | D6: =VLOOKUP(D8,'MATRIZ FUNCIONÁRIOS'!A:H,8) -> OPERACIONAL
A7: ELABORADO POR: | B7: GILTON PEREIRA MIRANDA | C7: MATRIC: | D7: 25
A8: CARGO: | B8: TEC. SEGURANÇA DO TRABALHO | C8: CBO: | D8: =VLOOKUP(D7,'MATRIZ FUNCIONÁRIOS'!A:D,4,FALSE) -> 717020
A9: FUNCIONÁRIO: | B9: =VLOOKUP(D7,'MATRIZ FUNCIONÁRIOS'!A:F,2,0) -> JOSE ANDRE DE SANTANA CRISPIM | C9: FUNÇÃO: | D9: =VLOOKUP(D7,'MATRIZ FUNCIONÁRIOS'!A:H,3,0) -> AJUDANTE DE OBRAS
A10: OBRIGAÇÕES DO EMPREGADO
A11: Considerando o interesse da empresa na redução de Acidentes do Trabalho, bem como cumprir o estabelecido no Artigo 157 – item II da C.L.T., com nova redação dada pela Lei n.º 6.514 de 22/12/77, fica determinado que é obrigação de todo empregado o cumprimento desta ordem de serviço e instrução de segurança do trabalho.
A12: DESCRIÇÃO DAS ATIVIDADES
A13: =VLOOKUP(D8,'MATRIZ FUNÇÃO'!A:E,3,0) -> Ajudam a executar tarefa de demolição de estrutura de alvenaria, Quebra de pisos e bases de concreto, construção e reparos em edificações de alvenaria, executar escavações, escoramento de valas e recomposição de pisos, Ajuda a executar paredes de alvenaria, executar trabalhos de retiradas de entulhos, espalhamento de materiais, carregamento e descarregamentos, desvios de trânsito auxilia na sinalização.
A14: RISCOS OCUPACIONAIS
A15: =VLOOKUP(D8,'MATRIZ FUNÇÃO'!A:E,4,0) -> FISICO: RUIDO, RADIAÇÃO NÃO IONIZANTES. QUÍMICO: POEIRAS MINERAIS (SILICA LIVRE CRISTALIZADA) ERGONOMICO: POSTURA INADEQUADA. ACIDENTE:ATROPELAMENTOS, BATIDAS CONTRA, CORTES E PERFURAÇÕES, PROJEÇÃO DE PARTICULAS, QUEDA DE MESMO NÍVEL.
A16: MEDIDAS PREVENTIVAS PARA REALIZAÇÃO DAS ATIVIDADES
A17: Ao utilizar escadas moveis procure fixa-la corretamente procurando apoiar-se pelo corrimão. Ao descer e subir escadas utilize o corrimão. Ao movimentar cargas e materiais procure mantê-la próximo do peito para proporcionar equilíbrio ao corpo. Ao alavancar cargas e materiais do piso manter a coluna ereta e usar as pernas como alavanca. Proibido realizar atividades para as quais não esteja capacitado, habilitado e autorizado pela empresa. Mesmo nas atividades em circuitos desnergizados utilizar luvas de borracha compatível com a voltagem do loca. Isole as partes vivas expostas dos circuitos provisórios. Atenção e cuidado com as partes moveis de maquinários, não manter contato direto com o equipamento em movimento. Fume somente nos locais permitidos que estejam sinalizados. Preservar o meio ambiente, não jogando lixos em locais inadequados. Use os EPI´s apenas para aas finalidades a que se destinam, guarde e conserve-os. Use protetor auditivo, quando trabalhar em local ruidoso. Use ferramentas manuais adequadas e as mantenha em boas condições para emprego. Somente ligue maquinas e equipamentos, com intermédio de conjunto de plug tomada. Evite emendas paralelas nos cabos/fios, use fita isolante adequada. Comparecer ao departamento medico para exame periódicos sempre que solicitado. Não improvise ferramentas, procure uma que seja adequada para seu serviço. Comunique ao seu encarregado toda e qualquer anormalidade ou defeito que notar na maquina ou ferramenta que for utilizar. Quando não souber ou tiver sobre algum serviço, pergunte ao encarregado, para prevenir-se contra possíveis acedentes. Não transite pela obra sem uniforme, capacete, óculos de segurança, protetor auditivo e botina de segurança. Nos trabalhos em altura superior a 2,00 (dois) metros na periferia do elevado, andaimes, estruturas, equipamentos, etc.. use o cinto De segurança. Não improvise andaimes de madeira, caixa e massa e nem trabalhe em andaimes sem guarda corpo, rodapé e estrado com mínimo De 0,60 cm de largura, chame seu encarregado. Obedecer as instruções do Técnico de Segurança, quando determinadas para você.
A18: TREINAMENTOS OBRIGATÓRIOS
A19: NR 05 CIPA
A20: NR 06 Equipamento de proteção individual;
A21: NR 17 Todos os empregados devem receber treinamentos ou instruções satisfatórias quanto aos métodos de trabalho, visando a garantir a execução de suas atividades com conforto e segurança;
A22: NR 23 Treinamento sobre princípios de incêndio e de como combatê-los;
A23: PROVIDÊNCIAS MÍNIMAS A SEREM TOMADAS EM CASO DE ACIDENTE:
A24: Todo e qualquer acidente de trabalho, deverá ser comunicado para o encarregado, na falta deste para o membro da CIPA e/ou ao Departamento Pessoal, para que possa ser providenciada a emissão da CAT – Comunicação de Acidente do Trabalho, cujo prazo é de 24 horas.
A25: OBS: O ACIDENTE NÃO COMUNICADO, NÃO SERÁ CONSIDERADO PARA EFEITOS LEGAIS.
A26: PROIBIÇÕES
A27: O descumprimento do aqui estabelecido importará em ato faltoso do integrante, com aplicação de penalidades cabíveis, baseadas no artigo 158 da C.L.T. e bem com o estabelecido nas cláusulas contratuais.
... A33: ATIVIDADES HABITUAIS
A34: =VLOOKUP(D8,'MATRIZ FUNÇÃO'!A:F,5,0) -> DESCRIÇÃO SINTÉTICA: Atuar em atividades auxiliares relativas à execução de obras em geral DESCRIÇÃO DETALHADA: Executar trabalhos auxiliares, sob supervisão, de serviços de alvenaria, concreto e outros materiais, auxiliando em processos pertinentes para construir, reformar ou reparar prédios e obras similares; Preparar concretos e argamassas segundo as características da obra e orientação superior. Assentar diferentes materiais, sob orientação; Revestir diferentes superfícies, sob supervisão; Realizar reforma e manutenção de prédios, calçadas e outras estruturas, sob Supervisão superior; Auxiliar na instalação de molduras de portas, janelas, quadro de luz e outros; Auxiliar na armação e desmonte andaimes de madeira ou metálicos para execução de obras desejadas; Auxiliar na montagem tubulações para instalações elétricas; Realizar treinamento na área de atuação, quando solicitado; Atuar, na qualidade de instrutor de treinamentos e outros eventos de igual natureza, mediante participação prévia em processo de qualificação e autorização superior; Manter organizados, limpos e conservados os materiais, máquinas, equipamentos e local de trabalho; Auxiliar na limpeza de frente de trabalho; Auxiliar na recomposição de materiais com carrinho de mão; Executar serviços manuais, utilizando ferramentas como: pá, enxada, picareta, vassoura, carrinho de mão entre outros; Montagem e desmontagem de barracas, utilizadas na área de vivencia Limpeza, retirada de lixo das áreas de vivencia; Orientar operadores e motoristas em manobras; Executar carregamento de peso manual; Auxiliar na medição camadas fresadas, utilizando linhas, trenas e outros; Pulverizar com óleo vegetal os pneus dos rolos durante a operação; Auxiliar no assopramento da areia de aplicação do material; Escavar valas, fixar piquetes; Executar tarefas manuais rotineiras que exigem esforços físicos; Remover e Manusear volumes, maquinas, moveis e equipamentos sempre que solicitado; Auxiliar na faxina em geral;
A36: TERMO DE RECEBIMENTO E COMPROMISSO
A37: Recebi da Empresa Talude Construções SA, a Ordem de Serviço (OS) que agora assino referente às minhas funções, que foi elaborada atendendo a legislação trabalhista em vigor, na qual cumprirei.
A38: DADOS DO FUNCIONÁRIO E ASSINATURA
A39: NOME LEGIVEL: | B39: =B9 -> JOSE ANDRE DE SANTANA CRISPIM
A40: IDENTIDADE: | B40: =VLOOKUP(D7,'MATRIZ FUNCIONÁRIOS'!A:F,6,0) -> 3140099 | C40: CPF: | D40: =VLOOKUP(D7,'MATRIZ FUNCIONÁRIOS'!A:F,5,0) -> 068.473.064-24
A41: FUNÇÃO: | B41: =D9 -> AJUDANTE DE OBRAS | C41: DATA: | D41: =VLOOKUP(D7,'MATRIZ FUNCIONÁRIOS'!A:H,7,0) -> 0
A42: ASSINATURA: | B42: x
A46: GILTON PEREIRA MIRANDA
A47: TÉCNICO DE SEGURANÇA DO TRABALHO
A48: Registro MTE-SP 0123056
A49: INSTRUTOR

Sheet FICHA DE EPI
A1: AAHBRANT ENGENHARIA E CONSTRUÇÕES LTDA
A4: TERMO DE RESPONSABILIDADE E CONTROLE DE ENTREGA DE EQUIPAMENTO DE PROTEÇÃO INDIVIDUAL - EPI
A6: COLABORADOR: | C6: =VLOOKUP(G7,'MATRIZ FUNCIONÁRIOS'!A:F,2,0) -> JOSÉ IGOR GALVÃO SILVA
A7: FUNÇÃO: | C7: =VLOOKUP(G7,'MATRIZ FUNCIONÁRIOS'!A:F,3,0) -> AJUDANTE DE OBRAS | F7: MATRIC: | G7: 550
A8: DATA ADMISSÃO: | C8: =VLOOKUP(G7,'MATRIZ FUNCIONÁRIOS'!A:G,7,0) -> 46259 | F8: SETOR: | G8: =VLOOKUP(G7,'MATRIZ FUNCIONÁRIOS'!A:H,8,0) -> OPERACIONAL
A9: DECLARAÇÃO DE RECEBIMENTO DE EPI
A10: Declaro em conformidade ao artigo 166 da Lei 6514/77 e NR-6 portaria 3214/78 do MTe, ter recebido gratuitamente os “Equipamentos de Proteção Individual – EPI” abaixo descritos, os quais me obrigo a usá-los, sistematicamente, em minhas atividades na empresa. Declaro também, que recebi orientação adequada quanto ao uso, finalidade, higienização, guarda conservação e ocasiões de substituições dos equipamentos de segurança abaixo descritos. Declaro ainda, ter ciência de que: a. Os EPIs deverão ser utilizados unicamente para o fim a que se destinam; b. Qualquer alteração que os tornem danificados deverá ser por mim comunicados à minha empregadora; c. A falta do uso por mim dos EPIs, fornecidos pela minha empregadora, constitui ato faltoso sujeito as sanções disciplinares previstas na legislação, no Regulamento Interno e nas Normas de Segurança da Empresa, aplicáveis ao assunto, inclusive e, especialmente, a demissão por justa causa. d. Responsabilizar-me-ei, integralmente, pela guarda e conservação dos EPIs, que me forem entregues; e. A minha empregadora fica expressamente autorizada a descontar dos meus salários bem como de indenizações, os valores dos EPIs, que porventura eu danificar culposa ou dolosamente, extrair e/ou não devolver para substituição ou por ocasião de meu desligamento da empresa. Finalmente, declaro que estou de acordo com todos os termos presentes, razão pela qual assino nesta data.
A11: Informe o Código correspondente ao motivo da aquisição
A12: (A) 1ª aquisição / (B) Gasto Normal / (C) Danos / (D) extraviados/ (E) Acidente
A14: QUANT | B14: DESCRIÇÃO DO EQUIPAMENTO | D14: NºCA | E14: DATA ENTREGA | F14: CÓD | G14: ASSINATURA | H14: DATA DEVOL.
A15: 2 | B15: CONJUNTO UNIFORMES | D15: UNI | E15: 46251 | F15: B | G15: X
A16: 1 | B16: BOTINA DE SEGURANÇA | D16: 38362 | E16: 46251 | F16: =F15 -> B | G16: x
A17: 1 | B17: PROTETOR AURICULAR TIPO PLUG | D17: 10043 | E17: 46251 | F17: =F16 -> B | G17: x
A18: 2 | B18: RESPIRADOR PFF2VS | D18: 45364 | E18: 46251 | F18: B | G18: x
A19: 1 | B19: =VLOOKUP(D19,'[1]MATRIZ EPI'!A:B,2,0) -> PROTETOR SOLAR LUVEX UV F60 | D19: SOL | E19: 46251 | F19: =F18 -> B | G19: x
A20: 1 | B20: ='MATRIZ EPI'!B9 -> ÓCULOS DE SEGURANÇA | D20: 11268 | E20: 46251 | F20: =F19 -> B | G20: x
A21: 1 | B21: CAPACETE DE SEG. | D21: 31469 | E21: 46251 | F21: =F20 -> B | G21: x
A22: 1 | B22: PAR DE LUVAS PIGMENTA | D22: 37930 | E22: 46251 | F22: =F21 -> B | G22: X
A23: 1 | B23: OCULOS DE SEG. INCOLOR | D23: 11268 | E23: 46251 | F23: =F22 -> B | G23: x
A24: (A) 1ª aquisição / (B) Gasto Normal / (C) Danos / (D) extraviados/ (E) Acidente
A25: DADOS DO FUNCIONÁRIO E ASSINATURA
A26: NOME LEGÍVEL: | C26: =C6 -> JOSÉ IGOR GALVÃO SILVA
A27: IDENTIDADE: | C27: =VLOOKUP(G7,'MATRIZ FUNCIONÁRIOS'!A:H,6,0) -> 71147506418 | E27: CPF: | F27: =VLOOKUP(G7,'MATRIZ FUNCIONÁRIOS'!A:H,5,0) -> 711.475.064-18
A28: FUNÇÃO: | C28: =C7 -> AJUDANTE DE OBRAS | E28: DATA ADM: | F28: =C8 -> 46259
A29: ASSINATURA: | C29: X
A31: AAHBRANT ENGENHARIA E CONSTRUÇÕES LTDA
A34: TERMO DE RESPONSABILIDADE E CONTROLE DE ENTREGA DE EQUIPAMENTO DE PROTEÇÃO INDIVIDUAL - EPI
A36: COLABORADOR: | C36: =C6 -> JOSÉ IGOR GALVÃO SILVA
A37: FUNÇÃO: | C37: =C7 -> AJUDANTE DE OBRAS | F37: MATRIC: | G37: =G7 -> 550
A38: DATA ADMISSÃO: | C38: =C8 -> 46259 | F38: SETOR: | G38: =G8 -> OPERACIONAL
A39: QUANT | B39: DESCRIÇÃO DO EQUIPAMENTO | D39: NºCA | E39: DATA ENTREGA | F39: CÓD | G39: ASSINATURA | H39: DATA DEVOL.
G40: X
G41: X
G42: X
G43: X
G44: X
G45: X
G46: X
G47: X
G48: X
G49: X
G50: X
G51: X
... G71: X
A72: DADOS DO FUNCIONÁRIO E ASSINATURA
A73: NOME LEGÍVEL: | C73: =C26 -> JOSÉ IGOR GALVÃO SILVA
A74: IDENTIDADE: | C74: =C27 -> 71147506418 | E74: CPF: | F74: =F27 -> 711.475.064-18
A75: FUNÇÃO: | C75: =C28 -> AJUDANTE DE OBRAS | E75: DATA ADM: | F75: =F28 -> 46259
A76: ASSINATURA: | C76: X

Sheet MATRIZ FUNÇÃO
A1: CBO | B1: FUNÇÃO | C1: DESCRIÇÃO SUMÁRIA | D1: RISCOS | E1: ATIVIDADES | F1: CARGOS | G1: SETOR
A2: 717020 | B2: AJUDANTE DE OBRAS | C2: Ajudam a executar tarefa de demolição de estrutura de alvenaria, Quebra de pisos e bases de concreto, construção e reparos em edificações de alvenaria, executar escavações, escoramento de valas e recomposição de pisos, Ajuda a executar paredes de alvenaria, executar trabalhos de retiradas de entulhos, espalhamento de materiais, carregamento e descarregamentos, desvios de trânsito auxilia na sinalização. | D2: FISICO: RUIDO, RADIAÇÃO NÃO IONIZANTES. QUÍMICO: POEIRAS MINERAIS (SILICA LIVRE CRISTALIZADA) ERGONOMICO: POSTURA INADEQUADA. ACIDENTE:ATROPELAMENTOS, BATIDAS CONTRA, CORTES E PERFURAÇÕES, PROJEÇÃO DE PARTICULAS, QUEDA DE MESMO NÍVEL. | E2: DESCRIÇÃO SINTÉTICA: Atuar em atividades auxiliares relativas à execução de obras em geral DESCRIÇÃO DETALHADA: Executar trabalhos auxiliares, sob supervisão, de serviços de alvenaria, concreto e outros materiais, auxiliando em processos pertinentes para construir, reformar ou reparar prédios e obras similares; Preparar concretos e argamassas segundo as características da obra e orientação superior. Assentar diferentes materiais, sob orientação; Revestir diferentes superfícies, sob supervisão; Realizar reforma e manutenção de prédios, calçadas e outras estruturas, sob Supervisão superior; Auxiliar na instalação de molduras de portas, janelas, quadro de luz e outros; Auxiliar na armação e desmonte andaimes de madeira ou metálicos para execução de obras desejadas; Auxiliar na montagem tubulações para instalações elétricas; Realizar treinamento na área de atuação, quando solicitado; Atuar, na qualidade de instrutor de treinamentos e outros eventos de igual natureza, mediante participação prévia em processo de qualificação e autorização superior; Manter organizados, limpos e conservados os materiais, máquinas, equipamentos e local de trabalho; Auxiliar na limpeza de frente de trabalho; Auxiliar na recomposição de materiais com carrinho de mão; Executar serviços manuais, utilizando ferramentas como: pá, enxada, picareta, vassoura, carrinho de mão entre outros; Montagem e desmontagem de barracas, utilizadas na área de vivencia Limpeza, retirada de lixo das áreas de vivencia; Orientar operadores e motoristas em manobras; Executar carregamento de peso manual; Auxiliar na medição camadas fresadas, utilizando linhas, trenas e outros; Pulverizar com óleo vegetal os pneus dos rolos durante a operação; Auxiliar no assopramento da areia de aplicação do material; Escavar valas, fixar piquetes; Executar tarefas manuais rotineiras que exigem esforços físicos; Remover e Manusear volumes, maquinas, moveis e equipamentos sempre que solicitado; Auxiliar na faxina em geral; | F2: CARGO: AJUDANTE DE OBRAS FUNÇÃO: SERVIÇOS OPERACIONAIS NA EXECUÇÃO DE OBRAS CBO: 7170-20 | G2: PRODUÇÃO
A3: 717020-A | B3: AJUDANTE DE OBRAS (TRABALHO EM ALTURA) | C3: Ajudam a executar tarefa de demolição de estrutura de alvenaria, Quebra de pisos e bases de concreto, construção e reparos em edificações de alvenaria, executar escavações, escoramento de valas e recomposição de pisos, Ajuda a executar paredes de alvenaria, executar trabalhos de retiradas de entulhos, espalhamento de materiais, carregamento e descarregamentos, desvios de trânsito auxilia na sinalização. | D3: FISICO: RUIDO, RADIAÇÃO NÃO IONIZANTES. QUÍMICO: POEIRASMINERAIS (SILICA LIVRE CRISTALIZADA) ERGONOMICO: POSTURA INADEQUADA. ACIDENTE:ATROPELAMENTOS, BATIDAS CONTRA, PROJEÇÃO DE PARTICULAS, QUEDA DE MESMO NÍVEL E TRABALHO EM ALTURA. | E3: DESCRIÇÃO SINTÉTICA: Atuar em atividades auxiliares relativas à execução de obras em geral DESCRIÇÃO DETALHADA: Executar trabalhos auxiliares, sob supervisão, de serviços de alvenaria, concreto e outros materiais, auxiliando em processos pertinentes para construir, reformar ou reparar prédios e obras similares; Preparar concretos e argamassas segundo as características da obra e orientação superior. Assentar diferentes materiais, sob orientação; Revestir diferentes superfícies, sob supervisão; Realizar reforma e manutenção de prédios, calçadas e outras estruturas, sob Supervisão superior; Auxiliar na instalação de molduras de portas, janelas, quadro de luz e outros; Auxiliar na armação e desmonte andaimes de madeira ou metálicos para execução de obras desejadas; Auxiliar na montagem tubulações para instalações elétricas; Realizar treinamento na área de atuação, quando solicitado; Atuar, na qualidade de instrutor de treinamentos e outros eventos de igual natureza, mediante participação prévia em processo de qualificação e autorização superior; Manter organizados, limpos e conservados os materiais, máquinas, equipamentos e local de trabalho; Auxiliar na limpeza de frente de trabalho; Auxiliar na recomposição de materiais com carrinho de mão; Executar serviços manuais, utilizando ferramentas como: pá, enxada, picareta, vassoura, carrinho de mão entre outros; Montagem e desmontagem de barracas, utilizadas na área de vivencia Limpeza, retirada de lixo das áreas de vivencia; Orientar operadores e motoristas em manobras; Executar carregamento de peso manual; Auxiliar na medição camadas fresadas, utilizando linhas, trenas e outros; Pulverizar com óleo vegetal os pneus dos rolos durante a operação; Auxiliar no assopramento da areia de aplicação do material; Escavar valas, fixar piquetes; Executar tarefas manuais rotineiras que exigem esforços físicos; Remover e Manusear volumes, maquinas, moveis e equipamentos sempre que solicitado; Auxiliar na faxina em geral; | F3: CARGO: AJUDANTE DE OBRAS FUNÇÃO: SERVIÇOS OPERACIONAIS NA EXECUÇÃO DE OBRAS CBO: 7170-20 | G3: PRODUÇÃO
A4: 715315 | B4: ARMADOR | C4: Preparar formas de madeira, colocando ferragens no interior das mesmas, baseando-se nas especificações ouinstruções recebidas, cortando, curvando e unindo vergalhões com a ajuda de ferramentas manuais, máquinas e outros utensílios, sob orientação do seu superior. | D4: FISICO: RUIDO, RADIAÇÃO NÃO IONIZANTE. QUÍMICO: POEIRAS MINERAIS (SILICA LIVRE CRISTALIZADA) , POEIRAS METÁLICAS. ERGONOMICO: POSTURA INADEQUADA. ACIDENTE: ATROPELAMENTO, BATIDAS CONTRA, CORTES E PERFURAÇÕES, PROJEÇÃO DE PARTÍCULAS E QUEDA DE MESMO NÍVEL. | E4:  DESCRIÇÃO SINTÉTICA:  Atuar em atividades relativas à área de confecção de armações e estruturas de concreto e madeira.Preparar a confecção de armações de estruturas de concreto e de corpos de provas;  Montar armações de ferragens em geral;  Cortar e dobrar ferragens;  Aplicação de armações e formações de lajes e vigas;  Realizar treinamento na área de atuação, quando solicitado;  Execultar cortes e dobras de ferragens;  Amarra as ferragens utilizando turquesas e arrames;  Montar ferragens de acordo com o projeto orientado pelo encarregado;  Efetuar carregamento manual de ferragens;  Manter organizados, limpos e conservados os materiais, máquinas, equipamentos e local de trabalho, que estão sob sua responsabilidade;  Ler,Interpretar e seguir projetos;  Zelar e manter sob sua reponsabilidade os ferramentais de uso. | F4: CARGO: ARMADOR;:FUNÇÃO: SERVIÇOS DE CONFECÇÃO DE ARMAÇÕES FERRAGEM - CBO: 7153-15 | G4: PRODUÇÃO
A5: 715315 (A) | B5: ARMADOR | C5: Preparar formas de madeira, colocando ferragens no interior das mesmas, baseando-se nas especificações ouinstruções recebidas, cortando, curvando e unindo vergalhões com a ajuda de ferramentas manuais, máquinas e outros utensílios, sob orientação do seu superior. | D5: FISICO: RUIDO, RADIAÇÃO NÃO IONIZANTE. QUÍMICO: POEIRAS POEIRAS MINERAIS (SILICA LIVRE CRISTALIZADA), POEIRAS METÁLICAS. ERGONOMICO: POSTURA INADEQUADA. ACIDENTE: ATROPELAMENTO, BATIDAS CONTRA, CORTES E PERFURAÇÕES, PROJEÇÃO DE PARTÍCULAS, QUEDA DE MESMO NÍVEL E TRABALHO EM ALTURA. | E5:  DESCRIÇÃO SINTÉTICA:  Atuar em atividades relativas à área de confecção de armações e estruturas de concreto e madeira.Preparar a confecção de armações de estruturas de concreto e de corpos de provas;  Montar armações de ferragens em geral;  Cortar e dobrar ferragens;  Aplicação de armações e formações de lajes e vigas;  Realizar treinamento na área de atuação, quando solicitado;  Execultar cortes e dobras de ferragens;  Amarra as ferragens utilizando turquesas e arrames;  Montar ferragens de acordo com o projeto orientado pelo encarregado;  Efetuar carregamento manual de ferragens;  Manter organizados, limpos e conservados os materiais, máquinas, equipamentos e local de trabalho, que estão sob sua responsabilidade;  Ler,Interpretar e seguir projetos;  Zelar e manter sob sua reponsabilidade os ferramentais de uso. | F5: CARGO: ARMADOR;:FUNÇÃO: SERVIÇOS DE CONFECÇÃO DE ARMAÇÕES FERRAGEM - CBO: 7153-15 | G5: PRODUÇÃO
A6: 312105-M | B6: ASSIST. TEC. DE MEDIÇÃO | C6: Realiza medições de obras, de acordo com dados levantados na topografia, para determinar quantidades e custos de materiais, mão de obra, equipamento e serviços necessários. | D6: FISICO: RUIDO, RADIAÇÃO NÃO IONIZANTE. QUÍMICO: POEIRAS MINERAIS (SILICA LIVRE CRISTALIZADA), ERGONOMICO: POSTURA INADEQUADA ACIDENTE: ACIDENTES DE TRANSITO (COLISÕES E ATROPELAMENTOS) BATIDAS CONTRA, QUEDA DE MESMO NÍVEL.. | E6: DESCRIÇÃO SINTÉTICA:  Auxiliar na elaborar, executar e dirigir projetos de engenharia civil. DESCRIÇÃO DETALHADA:  Auxilia na elaborar projetos de engenharia relativos a estrutura de edificações, tráfegos, vias urbanas e obras de pavimentação, sistemas de água e esgoto, aproveitamento de  Recursos naturais, serviços de equipamentos urbanos, rurais e regionais, entre outros;  Estudar características, especificações e preparar plantas, orçamentos de custos,técnicas de execução e outros dados, para possibilitar e orientar a construção,manutenção e reparo das obras, dentro dos padrões técnicos exigidos;  Efetuar vistorias, perícias, avaliação de imóveis, arbitramento, emitindo laudos e pareceres técnicos;  Participar de planos gerais e específicos, que visem o posicionamento institucional frente à comunidade, no que tange a sua especialidade e formação;  Realizar treinamento na área de atuação, quando solicitado;  Atuar, na qualidade de instrutor de treinamentos e outros eventos de igual natureza,mediante participação prévia em processo de qualificação e autorização superior;  Operar equipamentos e sistemas de informática e outros, quando autorizado e  Necessário ao exercício das demais atividades;  Dirigir veículos leves, mediante autorização prévia, quando necessário ao exercício das demais atividades; | F6: CARGO: ASSISTENTE DE ENGENHARIA FUNÇÃO: ASSISTENTE DE ENGENHARIA CBO:312105 | G6: ADMINISTRATIVO
A7: 715505 | B7: CARPINTEIRO | C7: Auxilia na construção, montagem e transporte, das formas e caixaria de madeira para a estrutura (vigas, colunas, sapatas, pilares) dos edifícios e obras similares, utilizando processos e ferramentas manuais e mecânicas, para compor tesouras, armações de telhado, andaimes e outros materiais afins, Executa trabalhos de carpintaria, com, desbaste e armação de portas, janelas, caixilhos e outros em esquadrias de madeira, Executa trabalhos em madeira, com base em desenhos, croquis ou ordens de serviços, montagens, reparos ou modificações em estrutura de alvenaria, portas, divisórias, engradados, etc, Efetua levantamento dos materiais necessários, selecionando e preparando os mesmos de acordo com os trabalhos a serem realizados. Operam máquinas, ferramentas e/ou instrumentos, a fim de lixar, cortar, plainar, montar. | D7: FISICO: RUIDO, RADIAÇÕES NÃO IONIZANTES; QUÍMICO: POEIRAS DE MADEIRA, DESMOLDANTE MINERAIS (SILICA LIVRE CRISTALIZADA); ERGONOMICO: POSTURA INADEQUADA. ACIDENTE: ATROPELAMENTO, BATIDA CONTRA, CORTE E PERFURAÇÕES, PROJEÇÕES DE PARTÍCULAS E QUEDA DE MESMO NÍVEL, | E7: DESCRIÇÃO SINTÉTICA:  Atuar em atividades relativas à área de carpintaria. DESCRIÇÃO DETALHADA:  Montagem e desmontagem de formas /Ecoramentos/Cimbramentos;  Auxiliar reajuste de formas no momento da concretagem;  Auxiliar em atividades relacionadas a reformas e construções, segundo orientação;  Montar andaimes, caixarias e tapumes de madeira;  Executar serviços diversos de carpintaria em geral, segundo orientações;  Realizar treinamento na área de atuação, quando solicitado;  Reparar elementos de madeira, substituindo total ou parcialmente peças desgastadas ou deterioradas ou fixando partes soltas para recompor sua estrutura;  Afiar ferramentas de corte, utilizando rebolo, lima, assentador ou pedra de afiar, para manter o gume;  Manter organizados, limpos e conservados os materiais, máquinas, equipamentos e local de trabalho, que estão sob sua responsabilidade;  Montar e desmontar andaimes;  Nivelar e alinhar formas,escorametos e cimbramentos;  Ler,Interpretar e seguir projetos;  Zelar e manter sob sua reponsabilidade os ferramentais de uso | F7: CARGO: CARPINTEIRO FUNÇÃO: SERVIÇOS DE CARPINTARIA CBO: 7155-05 | G7: PRODUÇÃO
A8: 715615 | B8: AUXILIAR DE ELETRICISTA | C8: Realiza instalações provisórias nas frentes de serviço, Realiza revisões dos cabos e ligações elétricas em máquinas e equipamentos, Executa verificação de painéis elétricos nos canteiros, Executa pequenas manutenções em ferramentas elétricas, Revisa os sistemas de iluminação e distribuição de energia nos canteiros, Realiza serviços de aterramento em diversos serviços, Testa e identifica redes e quadros. | D8: FISICO: RUIDO, RADIAÇÃO NÃO IONIZANTE. QUÍMICO: POEIRAS MINERAIS (SILICA LIVRE CRISTALIZADA) ERGONOMICO: POSTURA INADEQUADA ACIDENTE: ATROPELAMENTOS, CHOQUE ELÉTRICO, QUEDA DE MESMO NÍVEL.. | E8: PLANEJAR SERVIÇOS ELÉTRICOS REALIZAR INSTALAÇÃO DE DISTRIBUIÇÃO DE ALTA E BAIXA TENSÃO REALIZAR INSTALAÇÕES ELÉTRICAS PREDIAIS FAZER INSTALAÇÃO INDUSTRIAL EFETUAR SERVIÇOS COMERCIAIS DE ALTA E BAIXA TENSÃO Planejam serviços elétricos, realizam instalação de distribuição de alta e baixa tensão. Montam e reparam instalações elétricas e equipamentos auxiliares em residências, estabelecimentos industriais, comerciais e de serviços. Instalam e reparam equipamentos de iluminação de cenários ou palcos. EXECUTAR SERVIÇOS DE MANUTENÇÃO PREVENTIVA | F8: CARGO: ELETRICISTA FUNÇÃO: ELETRICISTA CBO: 7156-05 | G8: PRODUÇÃO
A9: 715605 | B9: ELETRICISTA | C9: Realiza instalações provisórias nas frentes de serviço, Realiza revisões dos cabos e ligações elétricas emmáquinas e equipamentos, Executa verificação de painéis elétricos nos canteiros, Executa pequenas manutenções em ferramentas elétricas, Revisa os sistemas de iluminação e distribuição de energia nos canteiros, Realiza serviços de aterramento em diversos serviços, Testa e identifica redes e quadros. | D9: FISICO: RUIDO, RADIAÇÃO NÃO IONIZANTE. QUÍMICO: POEIRAS MINERAIS (SILICA LIVRE CRISTALIZADA). ERGONOMICO: POSTURA INADEQUADA ACIDENTE: ATROPELAMENTOS, CHOQUE ELÉTRICO, QUEDA DE MESMO NÍVEL.. | E9: PLANEJAR SERVIÇOS ELÉTRICOS REALIZAR INSTALAÇÃO DE DISTRIBUIÇÃO DE ALTA E BAIXA TENSÃO REALIZAR INSTALAÇÕES ELÉTRICAS PREDIAIS FAZER INSTALAÇÃO INDUSTRIAL EFETUAR SERVIÇOS COMERCIAIS DE ALTA E BAIXA TENSÃO Planejam serviços elétricos, realizam instalação de distribuição de alta e baixa tensão. Montam e reparam instalações elétricas e equipamentos auxiliares em residências, estabelecimentos industriais, comerciais e de serviços. Instalam e reparam equipamentos de iluminação de cenários ou palcos. EXECUTAR SERVIÇOS DE MANUTENÇÃO PREVENTIVA | F9: CARGO: ELETRICISTA FUNÇÃO: ELETRICISTA CBO: 7156-05 | G9: PRODUÇÃO
A10: 514320 | B10: FAXINEIRO | C10: Realiza faxina nos escritórios e canteiro da obra, recolhe os lixos armazena em locais adequado. | D10: FISICO: RUIDO. QUÍMICO: POEIRAS MINERAIS (SILICA LIVRE CRISTALIZADA) ; PRODUTOS QUIMICOS DE USO DOMESTICO. BIOLÓGICO: FUNGOS, VIRUS E BACTÉRIAS (LIMPEZA); ERGONOMICO: POSTURA EM PÉ POR LONGOS PERIODOS ACIDENTE: QUEDA DE MESMO NÍVEL. | E10: LIMPAR RECINTOS E ACESSÓRIOS Limpar vidros Remover resíduos dos vidros Limpar móveis e equipamentos Limpeza de sanitários Limpar superfícies (paredes, pisos, etc..) Aspirar pó Lavar pisos Encerar pisos Remover sujeira Varrer pisos Secar pisos Passar pano Limpar cortinas e persianas Recolher lixo | F10: CARGO: FAXINEIRA FUNÇÃO: FAXINEIRA CBO: 5143-20 | G10: LIMPEZA
A11: 312320-G | B11: GREIDISTA | C11: Realiza cálculo de material a ser usado em terraplanagem, orienta e acompanha trabalho de corte e aterro, nivelamento e compactação de pistas e verifica estacas e marcações. | D11: FISICO: RUIDO, RADIAÇÃO NÃO IONIZANTE. QUÍMICO: POEIRAS MINERAIS (SILICA LIVRE CRISTALIZADAS) ERGONOMICO: POSTURA INADEQUADA ACIDENTE:ATROPELAMENTOS, BATIDAS CONTRA, QUEDA DE MESMO NÍVEL. | E11: Executam levantamentos geodésicos e topohidrográficos, por meio de levantamentos altimétricos e planimétricos; implantam, no campo, pontos de projeto, locando obras de sistemas de transporte, obras civis, industriais, rurais e delimitando glebas; planejam trabalhos em geomática; analisam documentos e informações cartográficas, interpretando fotos terrestres, fotos aéreas, imagens orbitais, cartas, mapas, plantas, identificando acidentes geométricos e pontos de apoio para georeferenciamento e amarração, coletando dados geométricos. Efetuam cálculos e desenhos e elaboram documentos cartográficos, definindo escalas e cálculos cartográficos, efetuando aerotriangulação, restituindo fotografias aéreas. | F11: CARGO: GREIDISTA FUNÇÃO: GREIDISTA CBO: 3123-20 | G11: PRODUÇÃO
A12: 7825.10-C | B12: MOTORISTA DE CAMINHAO | C12: Transportam, coletam e entregam cargas em geral, guincham, destombam e removem veículos avariados e prestam socorro mecânico. Movimentam cargas volumosas e pesadas, podem, também, operar equipamentos, realizar inspeções e reparos em veículos, vistoriar cargas, além de verificar documentação de veículos e de cargas. Definem rotas e asseguram a regularidade do transporte. As atividades são desenvolvidas em conformidade com normas e procedimentos técnicos e de segurança. | D12: RISCO FISICO: RUIDO, RADIAÇÃO NÃO IONIZANTE, VIBRAÇÕES DE CORPO INTEIRO. RISCO QUÍMICO: POEIRAS MINERAIS (SILICA LIVRE CRISTALIZADA) ; RISCO ERGONÔMICO: POSTURA INADEQUADA RISCO DE ACIDENTE: COLISÃO E TOMBAMENTO, BATIDAS CONTRA, QUEDA DO MESMO NÍVEL | E12: DESCRIÇÃO SINTÉTICA:  Condução de veículos de médio e grande porte. DESCRIÇÃO DETALHADA:  Dirigir veículos de médio e grande porte;  Transportar materiais, equipamentos e documentos;  Verificar, diariamente, as condições de funcionamento do veículo, antes de sua Utilização;  Comunicar a chefia imediata por escrito assinando a comunicação da necessidade de reparos no veículo;  Zelar pela segurança de passageiros no caso de ajudante;  Orientar e auxiliar na carga e descarga de materiais;  Amarrar a carga e conferir;  Atentar – se ao peso da carga e zelar pelo equipamento;  Registrar dados preestabelecidos, sobre a utilização diária do veículo;  Verificar, trocar ou completar, se necessário cotidianamente o óleo, a água e o Combustível;  Efetuar limpeza dos materiais que ficam encostados na caçamba;  Limpar placas, faróis e sinaleiros dos veículos utilizados;  Estar sempre atualizado com as leis e normas de trânsito e respeita- las;  Realizar treinamento na área de atuação, quando solicitado;  Utilizar a carga horária que lhe é pertinente com zelo, dedicação, responsabilidade e a serviço da Empresa;  Manter organizados, limpos e conservados os materiais, máquinas, equipamentos e local de trabalho, que estão sob sua responsabilidade;  Operar de acordo com a capacidade e especificações do fabricante. | F12: CARGO: SERVIÇO DE CONDUÇÃO DE VEÍCULOS DE MÉDIO E GRANDE PORTE. FUNÇÃO: MOTORISTA CBO: 7823-05 | G12: PRODUÇÃO
A13: 715110 | B13: OP. DE MÁQUINAS | C13: Operam máquinas e equipamentos, Operador de máquina de terraplenagem, Operador de máquina rodoviária, Operador de tratores diversos, retro escavadeiras, escavadeiras hidráulicas, moto niveladora (Patrol), rolo compactador chapa e pneu, Bob cat, Vibro acabadora e fresadora de asfalto , ajustando comandos, acionando movimentos das máquinas, Avaliam condições de funcionamento das máquinas e equipamentos, interpretando painel de instrumentos de medição, verificando fonte de alimentação, testando comandos de acionamento, Preparam área para operação dos equipamentos e transportam materiais em máquinas e equipamentos, Trabalham seguindo normas de segurança, higiene, qualidade e proteção ao meio ambiente. | D13: FISICO: RUIDO, RADIAÇÃO NÃO IONIZANTES E VIBRAÇÕES DE CORPO INTEIRO. QUÍMICO: POEIRAS MINERAIS(SILICA LIVRE CRISTALIZADA) ERGONOMICO: POSTURA INADEQUADA. ACIDENTE: COLISÃO E TOMBAMENTO, QUEDA DO MESMO NÍVEL, BATIDAS CONTRA. | E13: DESCRIÇÃO SINTÉTICA: Atuar em atividades auxiliares relativas à execução de obras em ger Atuar em atividades relativas à área de operação de máquinas e equipamentos,Operam máquinas e equipamentos, Operador de máquina de terraplenagem, Operador de máquina rodoviária, Operador de tratores diversos, retro escavadeiras, escavadeiras hidráulicas, moto niveladora (Patrol) , ajustando comandos, acionando movimentos das máquinas, Avaliam condições de funcionamento das máquinas e equipamentos, interpretando painel de instrumentos de medição, verificando fonte de alimentação, testando comandos de acionamento, Preparam área para operação dos equipamentos e transportam materiais em máquinas e equipamentos, Trabalham seguindo normas de segurança, higiene, qualidade e proteção ao meio ambiente DESCRIÇÃO DETALHADA: Operar as seguintes máquinas: britador, betoneira, escavadeira hidráulica, pá carregadeira, retro escavadeira, trator, espagidor de asfalto, moto niveladora, rolo compactador, fresadora de asfálto, vibro acabadora entre outras; operar máquinas munidas de uma lâmina ou escarifador, movida por autopropulsão ou por reboque, manipulando os comandos de marcha e direção, para nivelar terrenos na construção de edifícios, estradas, pistas e de outras obras; verificar, trocar ou completar, se necessário cotidianamente o óleo, a água e o combustível;limpar, lubrificar e ajustar as máquinas e seus implementos, de acordo com as instruções de manutenção do fabricante; acompanhar os serviços de manutenção preventiva e corretiva das máquinas e seus implementos e, após executados, efetuar os testes necessários; realizar treinamento na área de atuação, quando solicitado; observar as medidas de segurança ao operar e estacionar as máquinas; anotar, segundo normas estabelecidas, dados e informações sobre trabalhos realizados, consumo de combustível, consertos e outras ocorrências; limpar placas, faróis e sinaleiros das máquinas e equipamentos utilizado; Obedecer a legislação de transito; Vistoriar mangueira,óleo,combustível e agua; Compactar o solo; manter organizados, limpos e conservados os materiais, máquinas, equipamentos e local de trabalho, que estão sob sua responsabilidade; Espalhar material (Asfalto,BGS,BGTC,CBUQ e etc...); Escavar solo; Fresamento da camada asfáltica; Nivelar o solo; Carregar material e cortar buracos; Laminar o solo; Varrer o solo com vassoura mecânica; operar equipamentos e sistemas de informática e outros, quando autorizado e necessário ao exercício das demais atividades; Dirigir veículos leves, mediante autorização prévia, quando necessário ao exercício das demais atividades; Manter organizados, limpos e conservados os materiais, máquinas, equipamentos e local de trabalho, que estão sob sua responsabilidade, incluindo a limpeza da incrustações em laminas, conchas e demais partes do equipamento onde há possibilidade de incrustações de produtos;utilizar a carga horária de lhe é pertinente com dedicação, zelo, responsabilidade e tão somente a serviço da empresa; Responsalidade pelo manuseio do equipamento; Controlar capacidade do equipamento dentro das especificações do fabricante. | F13: CARGO: ESCAVADEIRAS HIDRÁULICAS, FRESADORA DE ASFÁLTO MOTO NIVELADORA, TRATOR DE ESTEIRA, TRATOR D6 E D8, OPERADOR DE FRESADEIRA, RETRO ESCAVAEIRAS E ROLO COMPACTADOR FUNÇÃO: SERVIÇOS OPERACIONAIS DE MÁQUINAS E EQUIPAMENTOS DE OBRAS. CBO: 7151-10 | G13: PRODUÇÃO
A14: 715210-(A) | B14: PEDREIRO | C14: Executa tarefa de demolição de estrutura de alvenaria, quebra de pisos e bases de concreto, construção e reparos em edificações de alvenaria, executa escavações, escoramento de valas e recomposição de pisos, Executa paredes em alvenarias, Construções de caixas e meios fios e etc. | D14: FISICO: RUIDO, RADIAÇÃO NÃO IONIZANTE. QUÍMICO: POEIRAS MINERAIS (SILICA LIVRE CRISTALIZADA), PRODUTOS QUÍMICOS. ERGONOMICO: POSTURA INADEQUADA. ACIDENTE: ATROPELAMENTOS, BATIDAS CONTRA, CORTES E PERFURAÇÕES, PROJEÇÃO DE PARTÍCULAS, QUEDAS DE MESMO NIVEL E TRABALHO EM ALTURA | E14: DESCRIÇÃO SINTÉTICA: Executar trabalhos de alvenaria, concreto e outros materiais, utilizando processos pertinentes para construir, reformar ou reparar prédios e obras similares. DESCRIÇÃO DETALHADA: Verifica as características da obra, examinando a planta e especificações para orientar-se na escolha do material apropriado e na melhor forma de execução do trabalho; Preparar concreto e argamassa segundo as características da obra; Assentar diferentes materiais; Revestir diferentes superfícies; Realizar reforma e manutenção de prédios, calçadas e outras estruturas; Instalar moldura de portas, janelas, quadro de luz e outros; Armar e desmontar andaimes de madeira ou metálicos para execução de obras desejadas; Montar tubulações para instalações elétricas; Construir caixas de drenagem,montar canaletas,chumbar tubulação de drenos Montar Canaletas,auxliar nos serviços de concretagem e finalizar acabamento no concreto; Atuar, na qualidade de instrutor de treinamentos e outros eventos de igual natureza, Mediante participação prévia em processo de qualificação e autorização superior. Dirigir veículos leves, mediante autorização prévia, quando necessário ao exercício das demais atividades. Manter organizados, limpos e conservados os materiais, máquinas, equipamentos,zelar e manter sob sua reponsabilidade os ferramentais de uso; | F14: CARGO: PEDREIRO FUNÇÃO: SERVIÇOS DE ALVENARIA,CONCRETOS E OUTROS MATERIAIS CBO: 7152-10 | G14: PRODUÇÃO
A15: 715210 | B15: PEDREIRO | C15: Executa tarefa de demolição de estrutura de alvenaria, quebra de pisos e bases de concreto, construção e reparos em edificações de alvenaria, executa escavações, escoramento de valas e recomposição de pisos, Executa paredes em alvenarias, Construções de caixas e meios fios e etc. | D15: FISICO: RUIDO, RADIAÇÃO NÃO IONIZANTE. QUÍMICO: POEIRAS MINERAIS (SILICA LIVRE CRISTALIZADA), ARGAMASSA, CIMENTO. ERGONOMICO: POSTURA INADEQUADA. ACIDENTE: ATROPELAMENTOS, BATIDAS CONTRA, CORTES E PERFURAÇÕES, PROJEÇÃO DE PARTÍCULAS, QUEDAS DE MESMO NIVEL | E15: DESCRIÇÃO SINTÉTICA: Executar trabalhos de alvenaria, concreto e outros materiais, utilizando processos pertinentes para construir, reformar ou reparar prédios e obras similares. DESCRIÇÃO DETALHADA: Verifica as características da obra, examinando a planta e especificações para orientar-se na escolha do material apropriado e na melhor forma de execução do trabalho; Preparar concreto e argamassa segundo as características da obra; Assentar diferentes materiais; Revestir diferentes superfícies; Realizar reforma e manutenção de prédios, calçadas e outras estruturas; Instalar moldura de portas, janelas, quadro de luz e outros; Armar e desmontar andaimes de madeira ou metálicos para execução de obras desejadas; Montar tubulações para instalações elétricas; Construir caixas de drenagem,montar canaletas,chumbar tubulação de drenos Montar Canaletas,auxliar nos serviços de concretagem e finalizar acabamento no concreto; Atuar, na qualidade de instrutor de treinamentos e outros eventos de igual natureza, Mediante participação prévia em processo de qualificação e autorização superior. Dirigir veículos leves, mediante autorização prévia, quando necessário ao exercício das demais atividades. Manter organizados, limpos e conservados os materiais, máquinas, equipamentos,zelar e manter sob sua reponsabilidade os ferramentais de uso; | F15: CARGO: PEDREIRO FUNÇÃO: SERVIÇOS DE ALVENARIA,CONCRETOS E OUTROS MATERIAIS CBO: 7152-10 | G15: PRODUÇÃO
A16: 351605 | B16: TÉC SEG DO TRABALHO | C16: Elaboram, participam da elaboração e implementam política de saúde e segurança no trabalho (SST), Realizam auditoria, acompanhamento e avaliação na área, Identificam variáveis de controle de doenças, acidentes, qualidade de vida e meio ambiente, Desenvolvem ações educativas na área de saúde e segurança no trabalho, Participam de perícias e fiscalizações e integram processos de negociação, Participam da adoção de tecnologias e processos de trabalho, Gerenciam documentação de SST, Investigam, analisam acidentes e recomendam medidas de prevenção e controle.treinamento e conscientização em assuntos pertinentes a SMS para as equipes do empreendimento conforme requerido. Elaborar e aplicar treinamentos voltados para segurança do trabalho, com vistas a garantir a integridade física e mental dos colaboradores. Acompanhar ar obras, prestando devido suporte com a finalidade de atender as exigências da fiscalização da contratante. Realizar medição e inspeção comportamental e de equipamentos. | D16: FISICO: RUIDO, RADIAÇÃO NÃO IONIZANTE. QUÍMICO: POEIRAS POEIRAS MINERAIS (SILICA LIVRE CRISTALIZADA); ERGONOMICO: POSTURA INADEQUADA ACIDENTE:ATROPELAMENTOS, QUEDA DE MESMO NÍVEL. | E16: DESCRIÇÃO SINTÉTICA:  Aplicar os conhecimentos de segurança e medicina do trabalho, de modo a reduzir e eliminar os riscos à saúde do trabalhador. DESCRIÇÃO DETALHADA:  Orientar e coordenar o sistema de segurança do trabalho, investigando riscos E causas de acidentes e analisando esquemas de prevenção, para garantir a Integridade dos colaboradores;  Inspecionar locais, instalações e equipamentos coletivos e individuais, observando as condições de trabalho, para determinar fatores e riscos de acidentes;  Estabelecer normas e dispositivos de segurança, sugerindo eventuais modificações nos equipamentos e instalações e verificando sua observância, para prevenir acidentes;  Inspecionar os postos de combate a incêndios, examinando as mangueiras, Hidrantes, extintores e equipamentos de proteção contra incêndios, para certificar-se de suas perfeitas condições de funcionamento;  Comunicar os resultados de suas inspeções, elaborando relatórios, para propor a reparação ou renovação do equipamento de extinção de incêndios e outras medidas de segurança;  Registrar acidentes ocorridos, examinando as condições da ocorrência, para  Identificar suas causas e propor as providências cabíveis;  Manter contato com os serviços médico e social da empresa ou de outra instituição,utilizando os meios de comunicação oficiais, para facilitar o atendimento necessário aos acidentados;  Registrar irregularidades ocorridas, anotando-as em formulários próprios e elaborando estatísticas de acidentes, para obter subsídios destinados à melhoria das medidas de segurança;  Buscar seu próprio desenvolvimento profissional;  Instruir os funcionários da empresa sobre normas de segurança, combate a incêndios e demais medidas de prevenção de acidentes, ministrando palestras e treinamento,para que possam agir acertadamente em casos de emergência | F16: CARGO: TÉCNICO SEGURANÇA DO TRABALHO FUNÇÃO: GESTÃO SMS E OUTROS. CBO: 351605 | G16: SUPERVISÃO
A17: 717010 | B17: RASTELEIRO | C17: Responsável em espalhar, rejuntar e fazer a emendas durante a aplicação da massa asfáltica. | D17: FISICO: RUIDO, RADIAÇÃO NÃO IONIZANTES. QUÍMICO: POEIRAS MINERAIS (SILICA LIVRE CRISTALIZADA), FUMOS E VAPORES ASFÁLTICOS ERGONOMICO: POSTURA INADEQUADA ACIDENTE: COLISÃO E TOMBAMENTO, BATIDAS CONTRA, COLISÃO E TOMBAMENTO, QUEDA DE MESMO NÍVEL. | E17: DESCRIÇÃO SINTÉTICA:  Atuar em atividades auxiliares relativas à execução de acabamentos de emendas. DESCRIÇÃO DETALHADA:  Executar trabalhos auxiliares, sob supervisão;  Nivelar manualmente o inicio da camada de materiais (BGS – BGTC – CBUQ e etc..);  Auxiliar na limpeza da área de serviço  Execultar serviços de espalhamento e acabamentode massa asfáltica;  Inspecionar seus equipamentos de trabalho (Rastelo – Pá – Vassoura – Carrinho de Mão e etc...);  Auxiliar na limpeza em geral e dos equipamentos de pavimentação. | F17: CARGO: RASTELEIRO FUNÇÃO: SERVIÇOS OPERACIONAIS NA EXECUÇÃO DE OBRAS. CBO: 7170-10 | G17: PRODUÇÃO
A18: 782510 | B18: MOTORISTA CARRETEIRO | C18: Transportam, coletam e entregam cargas em geral; guincham, destombam e removem veículos avariados e prestam socorro mecânico. Movimentam cargas volumosas e pesadas, podem, também, operar equipamentos, realizar inspeções e reparos em veículos, vistoriar cargas, além de verificar documentação de veículos e de cargas. Definem rotas e asseguram a regularidade do transporte. As atividades são desenvolvidas em conformidade com normas e procedimentos técnicos e de segurança. | D18: RISCO FISICO: RUIDO, RADIAÇÃO NÃO IONIZANTE, VIBRAÇÃO DE CORPO INTEIRO RISCO QUÍMICO: POEIRAS MINERAIS (SILICA LIVRE CRISTALIZADA); RISCO ERGONÔMICO: POSTURA INADEQUADA RISCO DE ACIDENTE: COLISÃO E TOMBAMENTO, BATIDAS CONTRA, QUEDA DE MESMO NIVEL | E18: DESCRIÇÃO SINTÉTICA:  Condução de veículos de médio e grande porte. DESCRIÇÃO DETALHADA:  Dirigir veículos de médio e grande porte;  Transportar materiais, equipamentos e documentos;  Verificar, diariamente, as condições de funcionamento do veículo, antes de sua Utilização;  Comunicar a chefia imediata por escrito assinando a comunicação da necessidade de reparos no veículo;  Zelar pela segurança de passageiros no caso de ajudante;  Orientar e auxiliar na carga e descarga de materiais;  Amarrar a carga e conferir;  Atentar – se ao peso da carga e zelar pelo equipamento;  Registrar dados preestabelecidos, sobre a utilização diária do veículo;  Verificar, trocar ou completar, se necessário cotidianamente o óleo, a água e o Combustível;  Efetuar limpeza dos materiais que ficam encostados na caçamba;  Limpar placas, faróis e sinaleiros dos veículos utilizados;  Estar sempre atualizado com as leis e normas de trânsito e respeita- las;  Realizar treinamento na área de atuação, quando solicitado;  Utilizar a carga horária que lhe é pertinente com zelo, dedicação, responsabilidade e a serviço da Empresa;  Manter organizados, limpos e conservados os materiais, máquinas, equipamentos e local de trabalho, que estão sob sua responsabilidade;  Operar de acordo com a capacidade e especificações do fabricante. | F18: CARGO: MOTORISTA DE CAMINHÃO,CARRETA E PLATAFORMA FUNÇÃO: SERVIÇO DE CONDUÇÃO DE VEÍCULOS DE MÉDIO E GRANDE PORTE. CBO: 7825-10 | G18: PRODUÇÃO
A19: 710205 | B19: ENCARREGADO DE OBRAS | C19: Supervisão das equipes dentro dos canteiros de obras, aplicando práticas ambientais pertinentes, Supervisionam equipes de trabalhadores da pavimentação asfálticas, Controle dos recursos produtivos da obra (arranjos físicos, equipamentos, materiais, insumos).e equipes de trabalho), conciliando com práticas ambientais, Inspeção da qualidade dos materiais e insumos e orientação sobre especificação, utilização e manejo ambientalmente correto, Coordenação do fluxo de movimentação dos materiais e equipamentos, Controle das normas de segurança, higiene e proteção ao meio ambiente, Administração do cronograma da obra, Aplicação de práticas ambientais visando o consumo racional de recursos, Condenar os trabalhos de pavimentação asfáltica. | D19: FISICO: RUIDO, RADIAÇÃO NÃO IONIZANTES. QUÍMICO: POEIRAS MINERAIS (SILICA LIVRE CRISTALIZADA), ERGONOMICO: POSTURA INADEQUADA. ACIDENTE:ATROPELAMENTO, BATIDAS CONTRA, PROJEÇÃO DE PARTICULAS, QUEDA DE MESMO NÍVEL. | E19: DESCRIÇÃO SINTÉTICA: Atuar em atividades relativas à área de organização, coordenação e supervisão de construção civil e pavimentação. DESCRIÇÃO DETALHADA: Organizar, coordenar e supervisionar grupos de trabalhadores que desenvolvem suas atribuições na área da construção civil, infraestrutura e pavimentação; Garantir o desenvolvimento do processo de execução das obras dentro dos Prazos e normas estabelecidas; Providenciar que as pessoas sob o seu comando utilizem equipamentos de Proteção individual (EPI), de acordo com as normas de segurança em vigor; Empenhar-se em buscar seu próprio desenvolvimento profissional; Buscar o desenvolvimento pessoal e profissional das pessoas que atuam sob seu comando; Acompanhar a evolução profissional das pessoas sob seu comando; Manter ou desenvolver visando o desempenho apropriado de suas funções, Atuar na qualidade de instrutor de treinamentos e outros eventos de igual Natureza, mediante participação prévia em processo de qualificação e Autorização superior; Dirigir veículos leves, mediante autorização prévia, quando necessário ao Exercício das demais atividades; Manter organizados, limpos e conservados os materiais, máquinas, Equipamentos e local de trabalho, que estão sob sua responsabilidade | F19: CARGO: ENCARREGADO DE OBRAS FUNÇÃO:ENCARREGADO DE OBRAS CBO: 7102-05 | G19: PRODUÇÃO
A20: 715140-M | B20: MESISTA | C20: Responsável pelo nivelamento da vibra acabadora, verificar a vibração da mesa e compactação, nivelamento da espessura da camada do material a ser aplicada, controla o andamento da operação regulando o consumo do material, monitorar e avisar aos supervisores, de eventuais anomalias de funcionamentos do equipamento orientar as auxiliares nos acabamentos da massa asfálticas aplicadas. | D20: FISICO: RUIDO, RADIAÇÃO NÃO IONIZANTES. QUÍMICO: POEIRAS MINERAIS (SILICA LIVRE CRISTALIZADA), FUMOS E VAPORES ASFÁLTICOS ERGONOMICO: POSTURA INADEQUADA ACIDENTE: COLISÃO E TOMBAMENTO, BATIDAS CONTRA, COLISÃO E TOMBAMENTO, QUEDA DE MESMO NÍVEL. | E20: DESCRIÇÃO SINTÉTICA:  Atuar em atividades a mesa da vibro acabadora. DESCRIÇÃO DETALHADA:  Executar trabalhos auxiliares, sob supervisão, de obras similares;  dirigir veículos leves, mediante autorização prévia, quando necessário ao exercício das demais atividades;  Responsavel pelo nivelamento da maquina;  Verificar a vibração da maquina de compactação;  Nivelamento da espessura da camada material;  Controlar o andamento da operação regulando o consumo do material;  Avisar das condições do funcionamento da maquina;  manter organizados, limpos e conservados os materiais, máquinas, equipamentos e local de trabalho, que estão sob sua responsabilidade. | F20: CARGO: MESISTA FUNÇÃO: MESISTA CBO: 7151-40 | G20: PRODUÇÃO
A21: 715125 | B21: OP DE VIBROACABADORA | C21: Operam máquinas e equipamentos, como vibro acabadora, ajustando comandos, acionando movimentos das máquinas, Avaliam condições de funcionamento das máquinas e equipamentos, interpretando painel de instrumentos de medição, verificando fonte de alimentação, testando comandos de acionamento, Preparam área para operação dos equipamentos e transportam materiais em máquinas e equipamentos, Trabalham seguindo normas de segurança, higiene, qualidade e proteção ao meio ambiente, Executam serviços de apoio ao operador de acabadora, regulam espessura no nível de massa e material utilizado na pavimentação apoio para georeferenciamento e amarração. | D21: FISICO: RUIDO, RADIAÇÃO NÃO IONIZANTES E VIBRAÇÕES DE CORPO INTEIRO. QUÍMICO: POEIRAS MINERAIS (SILICA LIVRE CRISTALIZADA) ERGONOMICO: POSTURA INADEQUADA. ACIDENTE: COLISÃO E TOMBAMENTO, BATIDAS CONTRA E QUEDA DE MESMO NÍVEL. | E21: DESCRIÇÃO SINTÉTICA:  Atuar em atividades auxiliares relativas à execução de obras em geral Atuar em atividades relativas à área de operação de máquinas e equipamentos, DESCRIÇÃO DETALHADA:  Operar as seguintes máquinas: vibro acabadora  operar máquinas munidas de uma lâmina ou escarifador, movida por autopropulsão ou por reboque, manipulando os comandos de marcha e direção, para nivelar terrenos na construção de edifícios, estradas, pistas e de outras obras;  verificar, trocar ou completar, se necessário cotidianamente o óleo, a água e o combustível;limpar, lubrificar e ajustar as máquinas e seus implementos, de acordo com as instruções de manutenção do fabricante;  acompanhar os serviços de manutenção preventiva e corretiva das máquinas e seus implementos e, após executados, efetuar os testes necessários;  realizar treinamento na área de atuação, quando solicitado;  observar as medidas de segurança ao operar e estacionar as máquinas;  anotar, segundo normas estabelecidas, dados e informações sobre trabalhos realizados, consumo de combustível, consertos e outras ocorrências;  limpar placas, faróis e sinaleiros das máquinas e equipamentos utilizado;  Obedecer a legislação de transito;  Vistoriar mangueira,óleo,combustível e agua;  manter organizados, limpos e conservados os materiais, máquinas, equipamentos e local de trabalho, que estão sob sua responsabilidade;  Espalhar material (Asfalto,BGS,BGTC,CBUQ e etc...);  Fresamento da camada asfáltica;  Nivelar o solo;  Laminar o solo;  manter organizados, limpos e conservados os materiais, máquinas, equipamentos e local de trabalho, que estão sob sua responsabilidade, incluindo a limpeza da incrustações em laminas, conchas e demais partes do equipamento onde há possibilidade de incrustações de produtos;  Responsalidade pelo manuseio do equipamento;  Controlar capacidade do equipamento dentro das especificações do fabricante | F21: CARGO: OPERADOR DE VIBROACABADORA FUNÇÃO: OPERADOR DE VIBROACABADORA CBO: 715125 CBO: 715140 | G21: PRODUÇÃO
A22: 770110 | B22: ENCARREGADO DE CARPINTARIA | C22: Assessoram aquisição de equipamentos, materiais e serviços, coordenam diretamente equipes de trabalhadores e organizam ambiente de trabalho em indústrias da madeira, mobiliário e de carpintaria. Preparam madeiras e supervisionam produção. Controlam estoque e expedição de materiais e produtos e manutenção de máquinas, equipamentos e ferramentas. Proporcionam segurança no trabalho. | D22: FISICO: RUIDO, RADIAÇÕES NÃO IONIZANTES; QUÍMICO: POEIRAS DE MADEIRA, MINERAIS (SILICA LIVRE CRISTALIZADA) E PRODUTOS QUIMICOS; ERGONOMICO: POSTURA INADEQUADA. ACIDENTE: ATROPELAMENTO, BATIDA CONTRA, CORTE E PERFURAÇÕES, PROJEÇÕES DE PARTÍCULAS E QUEDA DE MESMO NÍVEL, | E22: DESCRIÇÃO SINTÉTICA: Atuar em atividades relativas à área de organização, coordenação e supervisão de construção civil, serviços de carpintaria e pavimentação. DESCRIÇÃO DETALHADA: Organizar, coordenar e supervisionar grupos de trabalhadores que desenvolvem suas atribuições na área da construção civil, infraestrutura e pavimentação; Garantir o desenvolvimento do processo de execução das obras dentro dos Prazos e normas estabelecidas; Providenciar que as pessoas sob o seu comando utilizem equipamentos de Proteção individual (EPI), de acordo com as normas de segurança em vigor; Empenhar-se em buscar seu próprio desenvolvimento profissional; Buscar o desenvolvimento pessoal e profissional das pessoas que atuam sob seu comando; Acompanhar a evolução profissional das pessoas sob seu comando; Manter ou desenvolver visando o desempenho apropriado de suas funções, Atuar na qualidade de instrutor de treinamentos e outros eventos de igual Natureza, mediante participação prévia em processo de qualificação e Autorização superior; Dirigir veículos leves, mediante autorização prévia, quando necessário ao Exercício das demais atividades; Manter organizados, limpos e conservados os materiais, máquinas, Equipamentos e local de trabalho, que estão sob sua responsabilidade | F22: CARGO: ENCARREGADO DE CARPINTARIA FUNÇÃO: ENCARREGADO DE CARPINATRIA CBO: 770110 | G22: PRODUÇÃO
A23: 721410 | B23: OP. DE FRESA | C23: Operam máquinas e equipamentos, como opera fresadora de asfalto ajustando comandos, acionando movimentos das máquinas, Avaliam condições de funcionamento das máquinas e equipamentos, interpretando painel de instrumentos de medição, verificando fonte de alimentação, testando comandos de acionamento, Preparam área para operação dos equipamentos e transportam materiais em máquinas e equipamentos, Trabalham seguindo normas de segurança, higiene, qualidade e proteção ao meio ambiente | D23: FISICO: RUIDO, RADIAÇÃO NÃO IONIZANTES E VIBRAÇÕES. QUÍMICO: POEIRAS DE OBRA ERGONOMICO: POSTURA INADEQUADA. ACIDENTE: ATROPELAMENTOS, BATIDAS CONTRA. | E23: DESCRIÇÃO SINTÉTICA: Atuar em atividades auxiliares relativas à execução de obras em ger Atuar em atividades relativas à área de operação de máquinas e equipamentos, DESCRIÇÃO DETALHADA: Operar as seguintes máquinas: britador, betoneira, escavadeira hidráulica, pá carregadeira, retro escavadeira, trator, espagidor de asfalto, moto niveladora, rolo compactador, fresadora de asfálto, vibro acabadora entre outras; operar máquinas munidas de uma lâmina ou escarifador, movida por autopropulsão ou por reboque, manipulando os comandos de marcha e direção, para nivelar terrenos na construção de edifícios, estradas, pistas e de outras obras; verificar, trocar ou completar, se necessário cotidianamente o óleo, a água e o combustível;limpar, lubrificar e ajustar as máquinas e seus implementos, de acordo com as instruções de manutenção do fabricante; acompanhar os serviços de manutenção preventiva e corretiva das máquinas e seus implementos e, após executados, efetuar os testes necessários; realizar treinamento na área de atuação, quando solicitado; observar as medidas de segurança ao operar e estacionar as máquinas; anotar, segundo normas estabelecidas, dados e informações sobre trabalhos realizados, consumo de combustível, consertos e outras ocorrências; limpar placas, faróis e sinaleiros das máquinas e equipamentos utilizado; Obedecer a legislação de transito; Vistoriar mangueira,óleo,combustível e agua; Compactar o solo; manter organizados, limpos e conservados os materiais, máquinas, equipamentos e local de trabalho, que estão sob sua responsabilidade; Espalhar material (Asfalto,BGS,BGTC,CBUQ e etc...); Escavar solo; Fresamento da camada asfáltica; Nivelar o solo; Carregar material e cortar buracos; Laminar o solo; Varrer o solo com vassoura mecânica; operar equipamentos e sistemas de informática e outros, quando autorizado e necessário ao exercício das demais atividades; Dirigir veículos leves, mediante autorização prévia, quando necessário ao exercício das demais atividades; Manter organizados, limpos e conservados os materiais, máquinas, equipamentos e local de trabalho, que estão sob sua responsabilidade, incluindo a limpeza da incrustações em laminas, conchas e demais partes do equipamento onde há possibilidade de incrustações de produtos;utilizar a carga horária de lhe é pertinente com dedicação, zelo, responsabilidade e tão somente a serviço da empresa; Responsalidade pelo manuseio do equipamento; Controlar capacidade do equipamento dentro das especificações do fabricante. | F23: CARGO: ESCAVADEIRAS HIDRÁULICAS, MOTO NIVELADORA, TRATOR DE ESTEIRA, TRATOR D6 E D8, OPERADOR DE FRESADEIRA, RETRO ESCAVADEIRAS E ROLO COMPACTADOR E FRESADORA DE ASFÁLTO. FUNÇÃO: SERVIÇOS OPERACIONAIS DE MÁQUINAS E EQUIPAMENTOS DE OBRAS. CBO: 7214-10 | G23: PRODUÇÃO
A24: 142415 | B24: ENCARREGADO DE PRODUÇÃO | C24: Supervisionam equipes de trabalhadores da construção civil que atuam em usinas de concreto, canteiros de obras civis e ferrovias. Elaboram documentação técnica e controlam recursos produtivos da obra (arranjos físicos, equipamentos, materiais, insumos e equipes de trabalho). Controlam padrões produtivos da obra tais como inspeção da qualidade dos materiais e insumos utilizados, orientação sobre especificação, fluxo e movimentação dos materiais e sobre medidas de segurança dos locais e equipamentos da obra. Administram o cronograma da obra. Planejam o trabalho, realizam manutenção básica de máquinas pesadas e as operam. Removem solo e material orgânico "bota-fora", drenam solos e executam construção de aterros. | D24: FISICO: RUIDO, RADIAÇÃO NÃO IONIZANTE. QUÍMICO: POEIRAS MINERAIS (SILICA LIVRE CRISTALIZADA) ERGONOMICO: POSTURA INADEQUADA ACIDENTE:ATROPELAMENTOS BATIDAS CONTRA, QUEDA DE MESMO NÍVEL. | E24: DESCRIÇÃO SINTÉTICA: Atuar em atividades relativas à área de organização, coordenação e supervisão de construção civil e pavimentação. DESCRIÇÃO DETALHADA: Organizar, coordenar e supervisionar grupos de trabalhadores que desenvolvem suas atribuições na área da construção civil, infraestrutura e pavimentação; Garantir o desenvolvimento do processo de execução das obras dentro dos Prazos e normas estabelecidas; Providenciar que as pessoas sob o seu comando utilizem equipamentos de Proteção individual (EPI), de acordo com as normas de segurança em vigor; Empenhar-se em buscar seu próprio desenvolvimento profissional; Buscar o desenvolvimento pessoal e profissional das pessoas que atuam sob seu comando; Acompanhar a evolução profissional das pessoas sob seu comando; Manter ou desenvolver visando o desempenho apropriado de suas funções, Atuar na qualidade de instrutor de treinamentos e outros eventos de igual Natureza, mediante participação prévia em processo de qualificação e Autorização superior; Dirigir veículos leves, mediante autorização prévia, quando necessário ao Exercício das demais atividades; Manter organizados, limpos e conservados os materiais, máquinas, Equipamentos e local de trabalho, que estão sob sua responsabilidade | F24: CARGO OU FUNÇÃO: ENCARREGADO DE PRODUÇÃO CBO: 1424-15 | G24: PRODUÇÃO
A25: 214205 | B25: ENGENHEIRO CIVIL | C25: Elaboram projetos de engenharia civil, gerenciam obras, controlam a qualidade deempreendimentos. coordenam a operação e manutenção do empreendimento. podem prestar consultoria, assistência e assessoria e elaborar pesquisas tecnológicas,. | D25: FISICO: RUIDO, RADIAÇÃO NÃO IONIZANTE. QUÍMICO: POEIRAS MINERAIS (SILICA LIVRE CRISTALIZADA) ERGONOMICO: POSTURA INADEQUADA ACIDENTE: QUEDA DE MESMO NÍVEL. | E25: DESCRIÇÃO SINTÉTICA:  Elaborar, executar e dirigir projetos de engenharia civil. DESCRIÇÃO DETALHADA:  Elaborar projetos de engenharia relativos a estrutura de edificações, tráfegos, vias urbanas e obras de pavimentação, sistemas de água e esgoto, aproveitamento de  Recursos naturais, serviços de equipamentos urbanos, rurais e regionais, entre outros;  Estudar características, especificações e preparar plantas, orçamentos de custos,técnicas de execução e outros dados, para possibilitar e orientar a construção,manutenção e reparo das obras, dentro dos padrões técnicos exigidos;  Efetuar vistorias, perícias, avaliação de imóveis, arbitramento, emitindo laudos e pareceres técnicos;  Participar de planos gerais e específicos, que visem o posicionamento institucional frente à comunidade, no que tange a sua especialidade e formação;  Realizar treinamento na área de atuação, quando solicitado;  Atuar, na qualidade de instrutor de treinamentos e outros eventos de igual natureza,mediante participação prévia em processo de qualificação e autorização superior;  Operar equipamentos e sistemas de informática e outros, quando autorizado e  Necessário ao exercício das demais atividades;  Dirigir veículos leves, mediante autorização prévia, quando necessário ao exercício das demais atividades; | F25: CARGO: ENGENHEIRO CIVIL FUNÇÃO: ENGENHEIRO CIVIL CBO:3214205 | G25: ADMINISTRATIVO
A26: 410105 | B26: ENC. ADMINISTRATIVO DE OBRAS | C26: Supervisionam rotinas administrativas em instituições públicas e privadas, chefiando di retamente equipe de escriturários, auxiliares administrativos, secretários de expediente,operadores de máquina de escritório e contínuos. coordenam serviços gerais de ma lotes, mensageiros, transporte, cartório, limpeza, terceirizados, manutenção de equipa mento, mobiliário, instalações etc; administram recursos humanos, bens patrimoniaise materiais de consumo; organizam documentos e correspondências; gerenciam equi pe. podem manter rotinas financeiras, controlando fundo fixo (pequeno caixa), verbas,contas a pagar, fluxo de caixa e conta bancária, emitindo e conferindo notas fiscais erecibos, prestando contas e recolhendo impostos. | D26: FISICO: RUIDO. ERGONOMICO: POSTURA EM PÉ POR LONGOS PERIODOS | E26: DESCRIÇÃO SINTÉTICA: Atuar em atividades relativas à área de organização, coordenação e supervisão de área administrativa. DESCRIÇÃO DETALHADA: Tarefas de departamento pessoal para a gestão dos funcionários • Compra de materiais • Controles financeiros • Crédito e cobrança • Conciliação bancária • Lançamentos contábeis • Elaboração de relatórios gerenciais • Realização de reuniões • Tomada de decisões baseadas em dados e análises • Elaboração de planilhas de controle • Análise de indicadores • Acompanhamento das atividades realizadas pela equipe • Elaboração de O.S. (Ordem de Serviço). • Organização de documentos | F26: CARGO: ENCARREGADO ADMINISTRATIVO-CBO-410105 | G26: ADMINISTRATIVO
A27: 301110 | B27: LABORATÓRISTA | C27: Planejam o trabalho de apoio do laboratório e preparam vidrarias e materiais similares. Preparam soluções e equipamentos de medição e ensaios e analisam amostras de insumos e matérias-primas.Executam ensaios físicos, químicos, metalográficos e biológicos. garantem a calibraçãodos equipamentos e realizam amostragem de materiais. trabalham segundo normasde segurança, saúde e meio ambiente. controlam a qualidade. participam do sistemada qualidade da empresa e no desenvolvimento de novos produtos e fornecedores.colaboram no desenvolvimento de metodologias de análises. | D27: FISICO: RUIDO, RADIAÇÃO NÃO IONIZANTE, CALOR. QUÍMICO: POEIRAS MINERAIS (SILICA LIVRE CRISTALIZADA) ERGONOMICO: POSTURA INADEQUADA ACIDENTE: ARRANJO FÍSICO INADEQUADO, ILUMINAÇÃO INADEQUADA. | E27: O trabalho é exercido em indústrias de extração de petróleo e gás natural, de fabri cação de produtos químicos, de metal, têxteis e na construção. os profissionais sãoassalariados com carteira assinada. trabalham de forma individual, sob supervisãopermanente, exceto o técnico químico em petróleo que é ocasional. os profissionaistrabalham em ambiente fechado e a céu aberto. o técnico de laboratório de análisesfísico-químicas (materiais de construção) e o técnico químico em petróleo podem tra balhar em veículos. o horário de trabalho pode ser de turno fixo diurno ou noturnoou, ainda, no regime de rodízio. em suas atividades, os trabalhadores ficam expostos amateriais tóxicos e inflamáveis; o técnico de laboratório indústrial também fica expostoa altas temperaturas. trabalho subterrâneo e ruído intenso fazem parte das atividadesdo técnico de laboratório de análises físico-químicas (materiais de construção), assimcomo trabalhar em grandes alturas faz parte das atividades do técnico. | F27: CARGO: LABORATORISTA-CBO-301110 | G27: ADMINISTRATIVO
A28: 715140-E | B28: ENCARREGADO DE PAVIMENTAÇÃO | C28: Supervisão das equipes dentro dos canteiros de obras, aplicando práticas ambientais pertinentes, Supervisionam equipes de trabalhadores da pavimentação asfálticas, Controle dos recursos produtivos da obra (arranjos físicos, equipamentos, materiais, insumos).e equipes de trabalho), conciliando com práticas ambientais, Inspeção da qualidade dos materiais e insumos e orientação sobre especificação, utilização e manejo ambientalmente correto, Coordenação do fluxo de movimentação dos materiais e equipamentos, Controle das normas de segurança, higiene e proteção ao meio ambiente, Administração do cronograma da obra, Aplicação de práticas ambientais visando o consumo racional de recursos, Condenar os trabalhos de pavimentação asfáltica. | D28: FISICO: RUIDO, RADIAÇÃO NÃO IONIZANTE. QUÍMICO: POEIRAS MINERAIS (SILICA LIVRE CRISTALIZADA) ERGONOMICO: POSTURA INADEQUADA ACIDENTE:ATROPELAMENTOS, QUEDA DE MESMO NÍVEL. | E28: DESCRIÇÃO SINTÉTICA: Atuar em atividades relativas à área de organização, coordenação e supervisão de construção civil e pavimentação. DESCRIÇÃO DETALHADA: Organizar, coordenar e supervisionar grupos de trabalhadores que desenvolvem suas atribuições na área da construção civil e pavimentação, infraestrutura e pavimentação; Garantir o desenvolvimento do processo de execução das obras dentro dos Prazos e normas estabelecidas; Providenciar que as pessoas sob o seu comando utilizem equipamentos de Proteção individual (EPI), de acordo com as normas de segurança em vigor; Empenhar-se em buscar seu próprio desenvolvimento profissional; Buscar o desenvolvimento pessoal e profissional das pessoas que atuam sob seu comando; Acompanhar a evolução profissional das pessoas sob seu comando; Manter ou desenvolver visando o desempenho apropriado de suas funções, Atuar na qualidade de instrutor de treinamentos e outros eventos de igual Natureza, mediante participação prévia em processo de qualificação e Autorização superior; Dirigir veículos leves, mediante autorização prévia, quando necessário ao Exercício das demais atividades; Manter organizados, limpos e conservados os materiais, máquinas, Equipamentos e local de trabalho, que estão sob sua responsabilidade | F28: CARGO: ENCARREGADO DE PAVIMENTAÇÃO FUNÇÃO: ENCARREGADO DE PAVIMENTAÇÃO CBO: 715140 | G28: PRODUÇÃO
A29: 411010 | B29: AUXILIAR ADMINISTRATIVO DE OBRAS | C29: Executam serviços de apoio nas áreas de recursos humanos, administração, finançase logística; atendem fornecedores e clientes, fornecendo e recebendo informaçõessobre produtos e serviços; tratam de documentos variados, cumprindo todo o pro cedimento necessário referente aos mesmos. atuam na concessão de microcréditoa microempresários, atendendo clientes em campo e nas agências, prospectandoclientes nas comunidades. | D29: FISICO: RUIDO QUÍMICO: POEIRAS MINERAIS (SILICA LIVRE CRISTALIZADA) ERGONOMICO: POSTURA INADEQUADA ACIDENTE: ARRANJO FÍSICO INADEQUADO. | E29: DESCRIÇÃO SINTÉTICA: Auxilia em atividades relativas à área de organização, auxiliar ne área administrativa. DESCRIÇÃO DETALHADA: Tarefas de departamento pessoal para a gestão dos funcionários • Compra de materiais • Controles financeiros • Crédito e cobrança • Conciliação bancária • Lançamentos contábeis • Elaboração de relatórios gerenciais • Realização de reuniões • Tomada de decisões baseadas em dados e análises • Elaboração de planilhas de controle • Análise de indicadores • Acompanhamento das atividades realizadas pela equipe • Elaboração de O.S. (Ordem de Serviço). • Organização de documentos | F29: CARGO: AUXILIA ADMINISTRATIVO DE OBRAS-CBO-411010 | G29: ADMINISTRATIVO
A30: 312320 | B30: NIVELADOR | C30: Auxilia execução de levantamentos geodésicos e topo hidrográficos, por meio de levantamentos altimétricos e planimétricos, implantam, no campo, pontos de projeto, locando obras de sistemas de transporte, obras civis, industriais, rurais e delimitando glebas, planejam trabalhos em geomática, analisam documentos e informações cartográficas, interpretando fotos terrestres, fotos aéreas, imagens orbitais, cartas, mapas, plantas, identificando acidentes geométricos e pontos de apoio para georeferenciamento e amarração, coletando dados geométricos. Efetuam cálculos e desenhos e elaboram documentos cartográficos, definindo escalas e cálculos cartográficos, efetuando aerotriangulação, restituindo fotografias aéreas | D30: FISICO: RUIDO, RADIAÇÃO NÃO IONIZANTE. QUÍMICO: POEIRAS MINERAIS (SILICA LIVRE CRISTALIZADAS) ERGONOMICO: POSTURA INADEQUADA ACIDENTE:ATROPELAMENTOS, BATIDAS CONTRA, QUEDA DE MESMO NÍVEL. | E30: ESCRIÇÃO SINTÉTICA: Atuar em atividades relativas à área, auxiliando nos serviços topograficos. DESCRIÇÃO DETALHADA: . Analisar documentos e informações cartográficas, interpretando fotos terrestres, fotos aéreas, imagens orbitais, cartas, mapas, plantas, identificando acidentes geométricos e pontos de apoio para georeferenciamento e amarração, coletando dados geométricos; . Efetuar cálculos e desenhos; Elaborar documentos cartográficos, definindo escalas e cálculos cartográficos, efetuando aerotriangulação, restituindo fotografias aéreas. • Executam levantamentos geodésicos e topohidrográficos, por meio de levantamentos altimétricos e planimétricos; implantam, no campo, pontos de projeto, locando obras de sistemas de transporte, obras civis, industriais, rurais e delimitando glebas; planejam trabalhos em geomática; analisam documentos e informações cartográficas, interpretando fotos terrestres, fotos aéreas, imagens orbitais, cartas, mapas, plantas, identificando acidentes geométricos e pontos de apoio para georreferenciamento e amarração, coletando dados geométricos. efetuam cálculos e desenhos e elaboram documentos cartográfico • Exercer tarefas de topografia, procedendo ao levantamento, anotação e cálculo de dados da área a ser demarcada bom como efetuar o desenho da área. Zelar pela limpeza e conservação da aparelhagem topográfica. Auxiliar nas atividades de ensino, pesquisa e extensão. | F30: CARGO: AUXILIAR TOPOGRAFO FUNÇÃO: SERVIÇOS DE TOPOGRAFIA | G30: PRODUÇÃO
A31: 312320-T | B31: TOPOGRAFO | C31: Executam levantamentos geodésicos e topo hidrográficos, por meio de levantamentos altimétricos e planimétricos, implantam, no campo, pontos de projeto, locando obras de sistemas de transporte, obras civis, industriais, rurais e delimitando glebas, planejam trabalhos em geomática, analisam documentos e informações cartográficas, interpretando fotos terrestres, fotos aéreas, imagens orbitais, cartas, mapas, plantas, identificando acidentes geométricos e pontos de apoio para georreferenciamento e amarração, coletando dados geométricos. Efetuam cálculos e desenhos e elaboram documentos cartográficos, definindo escalas e cálculos cartográficos, efetuando aerotriangulação, restituindo fotografias aéreas. | D31: FISICO: RUIDO, RADIAÇÃO NÃO IONIZANTE. QUÍMICO: POEIRAS MINERAIS (SILICA LIVRE CRISTALIZADAS) ERGONOMICO: POSTURA INADEQUADA ACIDENTE:ATROPELAMENTOS, BATIDAS CONTRA, QUEDA DE MESMO NÍVEL. | E31: ESCRIÇÃO SINTÉTICA: Atuar em atividades relativas à área, auxiliando nos serviços topograficos. DESCRIÇÃO DETALHADA: . Analisar documentos e informações cartográficas, interpretando fotos terrestres, fotos aéreas, imagens orbitais, cartas, mapas, plantas, identificando acidentes geométricos e pontos de apoio para georeferenciamento e amarração, coletando dados geométricos; . Efetuar cálculos e desenhos; Elaborar documentos cartográficos, definindo escalas e cálculos cartográficos, efetuando aerotriangulação, restituindo fotografias aéreas. • Executam levantamentos geodésicos e topohidrográficos, por meio de levantamentos altimétricos e planimétricos; implantam, no campo, pontos de projeto, locando obras de sistemas de transporte, obras civis, industriais, rurais e delimitando glebas; planejam trabalhos em geomática; analisam documentos e informações cartográficas, interpretando fotos terrestres, fotos aéreas, imagens orbitais, cartas, mapas, plantas, identificando acidentes geométricos e pontos de apoio para georreferenciamento e amarração, coletando dados geométricos. efetuam cálculos e desenhos e elaboram documentos cartográfico • Exercer tarefas de topografia, procedendo ao levantamento, anotação e cálculo de dados da área a ser demarcada bom como efetuar o desenho da área. Zelar pela limpeza e conservação da aparelhagem topográfica. Auxiliar nas atividades de ensino, pesquisa e extensão. | F31: CARGO: TOPOGRAFO FUNÇÃO: SERVIÇOS DE TOPOGRAFIA | G31: PRODUÇÃO
A32: 254110 | B32: AUXILIAR TÉC SEG DO TRABALHO | C32: Elabora e participam da elaboração e implementam política de saúde e segurança do trabalho; realizam diagnóstico da situação de SST da instituição; identificam variáveis de controle de doenças, acidentes, qualidade de vida e meio ambiente. Desenvolvem ações educativas na área de saúde e segurança do trabalho; integram processos de negociação. Participam da adoção de tecnologias e processos de trabalho; investigam, analisam acidentes de trabalho e recomendam medidas de prevenção e controle. | D32: FISICO: RUIDO, RADIAÇÃO NÃO IONIZANTE. QUÍMICO: POEIRAS MINERAIS (SILICA LIVRE CRISTALIZADA) ERGONOMICO: POSTURA INADEQUADA ACIDENTE:ATROPELAMENTOS BATIDAS CONTRA, QUEDA DE MESMO NÍVEL. | E32: DESCRIÇÃO SINTÉTICA:  Aplicar os conhecimentos de segurança e medicina do trabalho, de modo a reduzir e eliminar os riscos à saúde do trabalhador. DESCRIÇÃO DETALHADA:  Orientar e coordenar o sistema de segurança do trabalho, investigando riscos E causas de acidentes e analisando esquemas de prevenção, para garantir a Integridade dos colaboradores;  Inspecionar locais, instalações e equipamentos coletivos e individuais, observando as condições de trabalho, para determinar fatores e riscos de acidentes;  Estabelecer normas e dispositivos de segurança, sugerindo eventuais modificações nos equipamentos e instalações e verificando sua observância, para prevenir acidentes;  Inspecionar os postos de combate a incêndios, examinando as mangueiras, Hidrantes, extintores e equipamentos de proteção contra incêndios, para certificar-se de suas perfeitas condições de funcionamento;  Comunicar os resultados de suas inspeções, elaborando relatórios, para propor a reparação ou renovação do equipamento de extinção de incêndios e outras medidas de segurança;  Registrar acidentes ocorridos, examinando as condições da ocorrência, para  Identificar suas causas e propor as providências cabíveis;  Manter contato com os serviços médico e social da empresa ou de outra instituição,utilizando os meios de comunicação oficiais, para facilitar o atendimento necessário aos acidentados;  Registrar irregularidades ocorridas, anotando-as em formulários próprios e elaborando estatísticas de acidentes, para obter subsídios destinados à melhoria das medidas de segurança;  Buscar seu próprio desenvolvimento profissional;  Instruir os funcionários da empresa sobre normas de segurança, combate a incêndios e demais medidas de prevenção de acidentes, ministrando palestras e treinamento,para que possam agir acertadamente em casos de emergência | F32: CARGO: AULIAR TÉCNICO SEGURANÇA DO TRABALHO FUNÇÃO: GESTÃO SMS E OUTROS. CBO: 351605 | G32: PRODUÇÃO
A33: 913115 | B33: Eletricista de veículos de máquinas | C33: Planejam serviços de instalação e manutenção eletroeletrônicos em veículos, estabe lecendo cronogramas e estimando prazos. instalam sistemas e componentes eletroe letrônicos em aeronaves, embarcações e veículos, elaborando leiautes e esquemas, in terpretando e corrigindo esquemas, conectando cabos aos equipamentos e acessóriose testando o funcionamento de máquinas, equipamentos e sistemas para operação.realizam manutenções preventiva, preditiva e corretiva, | D33: FISICO: RUIDO, CALOR, FRIO QUIMICO: POEIRA DE OBRA ERGONOMICO: POSTURA INADEQUADA ACIDENTE: QUEDA DE MESMO NIVEL, CHOQUE ELÉTRICO. | E33: Planeja serviços de elétricas de automoveis. Executa manuteção preventivas componetes eletricos, :inspecionando visualmentemáquinas e equipamentos, diagnosticando defeitos eletroeletrônicos, desmontando,reparando, lubrificando, substituindo e montando componentes, ajustando componen tes e peças e simulando o funcionamento de componentes e equipamentos. elaboramdocumentação técnica, cumprem normas de segurança, meio ambiente e saúde e rea lizam com qualidade as instalações eletroeletrônicas.DESCRIÇÃO DE ATIVIDADES TÍPICAS DO CARGO • reparação de aparelhos elétricos. • Montagem de instalações elétricas de residências, fábricas e outros estabelecimentos, e de embarcações, aviões, automóveis e outros veículos automotores. • Instalação e manutenção de redes elétricas. • Transportar equipamentos e ferramentas necessários à execução dos trabalhos. • Executar outras tarefas de mesma natureza e nível de complexidade associadas ao ambiente organizacional. | F33: CARGO: ELETRICISTA DE AUTOMOVEIS FUNÇÃO: ELETRICISTA AUTOMOVEIS CBO: 913115 | G33: PRODUÇÃO
A34: 913120 | B34: MECÂNICO | C34: Consertam máquinas e equipamentos, requisitando peças para reposição, montando máquinas equipamentos e acessórios, conforme especificações do fabricante. Organizam o local de trabalho para manutenção e avaliam as condições de máquinas e equipamentos. Elaboram propostas de serviços e orçamentos, relacionando causas de defeitos e listando peças para substituição. Trabalham seguindo normas de segurança e qualidade. | D34: FISICO: RUIDO, RADIAÇÃO NÃO IONIZANTE. QUIMICO: ÓLEOS LUBRIFICANTES E GRAXAS. ERGONOMICO: POSTURA INADEQUADA ACIDENTE: CORTE PERFURAÇÕES E QUEDA DE MESMO NIVEL. | E34: DESCRIÇÃO SINTÉTICA:  Atuar em atividades relativas à área de montagem, desmontagem, reparo e manutenção de máquinas pesadas. DESCRIÇÃO DETALHADA:  Examinar a máquina ou equipamentos inspecionando-os para determinar os defeitos e anormalidades do funcionamento;  Orientar e executar serviços de manutenção mecânica corretiva e preventiva em veículos pesados, máquinas, motores e equipamentos;  Reparar defeitos, substituindo peças, fazendo ajustes, regulagens e lubrificação,segundo orientações;  Fazer o desmonte, limpeza e a montagem do motor, órgãos de transmissão, diferencial e outras partes;  Providenciar o recondicionamento do equipamento elétrico, o alinhamento da direção e regulagem dos faróis do veículo;  Retirar forros, cintos, revestimentos e carpete e providenciar seu reparo ou manutenção;  Efetuar ajustes, reparos, reformas e manutenções em geral em equipamentos  Diversos, interpretando manuais e normas técnicas;  Realizar diagnósticos técnicos e realizar serviços corretivos e de manutenção, peças,ferramentas e mão-de-obra necessária;  Identificar e prescrever necessidades de serviços de terceiros, mediante relatório escrito e assinado, encaminhado a chefia imediata;  Utilizar a carga horária de lhe é pertinente com dedicação, zelo, responsabilidade e tão somente a serviço da empresa;  Realizar treinamento na área de atuação, quando solicitado;  Zelar pela limpeza, conservação e manutenção dos aparelhos, ferramentas e ambiente de trabalho;Lubrificar máquinas e componentes; Ajustar, trocar, reparar e consertar componentes e partes da máquina; Montar e desmontar máquinas e equipamentos; Realizar inspeções e medições periódicas (manutenção preventiva);Executa processos de manutenção mecânica de máquinas industriais, desmontando, montando, recuperando ou substituindo peças e máquinas, respeitando procedimentos e normas técnicas de qualidade, segurança, meio ambiente e saúde.especializado em agricultura, mineração ou material rodante pesado: escavadeiras, retroescavadeiras, rolo compactador, moto niveladora e tratores, etc. uma das funções do mecânico de máquinas pesadas é planejar, supervisionar e participar dos trabalhos de manutenção corretiva e preventiva. | F34: CARGO: MECÂNICO FUNÇÃO: MECÂNICO CBO: 913120 | G34: OFICINA
A35: 914405 | B35: AUXILIAR DE MECÂNICO | C35: Realizam manutenção em máquinas pesadas e implementos agrícolas. Preparam peças para montagem de equipamento, realizam manutenções, inspecionam e testam o funcionamento de máquinas e equipamentos. Planejam as atividades de manutenção e registram informações técnicas. As atividades são desenvolvidas em conformidade com normas e procedimentos técnicos, de segurança, qualidade e de preservação do meio ambiente. | D35: FISICO: RUIDO, RADIAÇÃO NÃO IONIZANTE. QUIMICO: ÓLEOS LUBRIFICANTES E GRAXAS. ERGONOMICO: POSTURA INADEQUADA ACIDENTE: CORTE PERFURAÇÕES, QUEDA DE MESMO NIVEL, . PARTICULAS E BATIDAS CONTRA. | E35: DESCRIÇÃO SINTÉTICA:  Atuar em atividades de auxílio relativas à área de montagem, desmontagem, reparo e manutenção de veículos. DESCRIÇÃO DETALHADA:  Auxiliar no concerto, montagem e desmontagem, observando catálogos e manuais de peças e manutenção, interpretando descrições técnicas dos referidos catálogos e manuais dos equipamentos, máquinas e veículos;  Auxiliar na execução de serviços de manutenção mecânica corretiva e preventiva em veículos leves, pesados, máquinas, motores e equipamentos;  Auxiliar no reparo de defeitos, substituindo peças, fazendo ajustes, regulagens e lubrificação, segundo orientações;  Auxiliar no desmonte, limpeza e a montagem do motor, órgãos de transmissão, diferencial e outras partes;  Auxiliar no recondicionamento do equipamento elétrico, o alinhamento da direção e regulagem dos faróis do veículo;  Auxiliar o mecânico a retirar forros, cintos, revestimentos e carpete e providenciar seu reparo ou manutenção.  Auxiliar o mecânico com peças, ferramentas e mão-de-obra necessária.  Utilizar a carga horária de lhe é pertinente com dedicação, zelo e responsabilidade;  Utilizar a carga horária atribuída ao seu emprego, tão somente a serviço da empresa;  Zelar pela limpeza, conservação e manutenção dos aparelhos, ferramentas e ambiente de trabalho.  Dirigir veículos leves, mediante autorização prévia, quando necessário ao exercício das demais atividades.  Manter organizados, limpos e conservados os materiais;  local de trabalho, que estão sob sua responsabilidade.Auxilia na lubrificar máquinas e componentes; Ajustar, trocar, reparar e consertar componentes e partes da máquina; Montar e desmontar máquinas e equipamentos; Realizar inspeções e medições periódicas (manutenção preventiva);Executa processos de manutenção mecânica de máquinas industriais, desmontando, montando, recuperando ou substituindo peças e máquinas, respeitando procedimentos e normas técnicas de qualidade, segurança, meio ambiente e saúde.especializado em agricultura, mineração ou material rodante pesado: escavadeiras, retroescavadeiras, rolo compactador, moto niveladora e tratores, etc. uma das funções do mecânico de máquinas pesadas é planejar, supervisionar e participar dos trabalhos de manutenção corretiva e preventiva. | F35: CARGO: AUXILIAR DE MECÂNICO FUNÇÃO: AUXILIAR DE MECÂNICO CBO: 913120 | G35: OFICINA
A36: 919110 | B36: MOTORISTA LUBRIFICADOR | C36: Lubrificam máquinas e equipamentos, sinalizando pontos de lubrificação, interpretan do desenhos de máquinas, avaliando a situação de máquinas e equipamentos, sele cionando material de limpeza e ferramentas para lubrificação, retirando excessos delubrificantes, liberando máquinas e equipamentos lubrificados e preenchendo relató rios e registros de ocorrências. monitoram o desempenho de máquinas e equipamentos,realizando inspeções preventivas, identificando anomalias, solicitando manutenções,verificando a ocorrência de impurezas em lubrificantes e retirando amostras para análi ses. colaboram na elaboração de planos de lubrificação. conservam ferramentas e ma teriais para lubrificação. trabalham seguindo normas de segurança, higiene, qualidadee proteção ao meio ambiente. | D36: FISICO: RUIDO, RADIAÇÃO NÃO IONIZANTE. QUIMICO: ÓLEOS E GRAXAS, POEIRA DE OBRA E SOLVENTES. ERGONOMICO: POSTURA INADEQUADA ACIDENTE: QUEDA DE MESMO NIVEL, ATROPELAMENTO, BATIDAS CONTRA E QUEDA DE MATERIAL. | E36: DESCRIÇÃO SINTÉTICA:  Lubrifica e abastece máquinas e equipamentos, selecionando o material de limpeza e ferramentas necessários. Realiza inspeções preventivas, preenche relatórios e registros de ocorrências. DESCRIÇÃO DETALHADA:  Abastece maquinas e veiculos com diesel.  Lubrificar maquinas, veiculos e equipamentos.  Usar de equipamentos de lubrificação adequado para cada tipo de lubrificante. Manter sistema de identificação que permita usar o equipamento adequado x lubrificante x plano de lubrificação. Manter as FISPQs e Fichas de Emergência sempre próximas a cada lubrificante estocado caso necessite em situações de emergências. | F36: CARGO: MOTORISTA LUBRIFICADOR FUNÇÃO: MOTORISTA LUBRIFICADOR CBO: 919110 | G36: OFICINA
A37: 414105 | B37: ALMOXARIFE | C37: Responsável pelo controle do estoque, conferência de mercadorias e expedição. Trabalha em armazéns, silos e depósitos, fazendo os registros de entrada e saída dos itens de estoque. Colaboram na organização da movimentação dos itens armazenados. | D37: FISICO: RUÌDO. ERGONOMICO: POSTURA INADEQUADA ACIDENTE: BATIDA CONTRA, QUEDA DE MESMO NIVEL, . | E37: DESCRIÇÃO SINTÉTICA: Organizar e manter o almoxarifado, executar recebimento, estocagem, distribuição, registro e inventário de matérias-primas e mercadorias adquiridas e confeccionadas. DESCRIÇÃO DETALHADA:Realiza o recebimento, movimentação e estocagem de matérias-primas e produtos. Recebe e confere as notas fiscais de entrada dos materiais adquiridos, verifica quantidade, descrição e as condições gerais dos materiais e embalagens | F37: CARGO: ALMOXARIFE-CBO-410105 | G37: OFICINA ALMOXARIFADO
A38: 312105-E | B38: ASSIST. TEC. DE ENGENHARIA | C38: Planejam a execução do trabalho e supervisionam equipes de trabalhadores de construção de obras de infra-estrutura. Auxiliam engenheiros no desenvolvimento de projetos, no levantamento e tabulação de dados e na vistoria técnica. Estruturam o serviço de coleta de resíduos sólidos das obras, controlando os procedimentos de preservação do meio ambiente. Realizam trabalhos de laboratório, vendas e compras de materiais e equipamentos. Padronizam procedimentos técnicos. | D38: FISICO: RUIDO, RADIAÇÃO NÃO IONIZANTES. QUÍMICO: POEIRAS DE OBRA ERGONOMICO: POSTURA INADEQUADA. ACIDENTE: ACIDENTES DE TRANSITO (COLISÕES E ATROPELAMENTOS), BATIDAS CONTRA, PROJEÇÃO DE PARTICULAS, QUEDA DE MESMO NÍVEL. | E38: DESCRIÇÃO SINTÉTICA:  Auxiliar na elaborar, executar e dirigir projetos de engenharia civil. DESCRIÇÃO DETALHADA:  Auxilia na elaborar projetos de engenharia relativos a estrutura de edificações, tráfegos, vias urbanas e obras de pavimentação, sistemas de água e esgoto, aproveitamento de  Recursos naturais, serviços de equipamentos urbanos, rurais e regionais, entre outros;  Estudar características, especificações e preparar plantas, orçamentos de custos,técnicas de execução e outros dados, para possibilitar e orientar a construção,manutenção e reparo das obras, dentro dos padrões técnicos exigidos;  Efetuar vistorias, perícias, avaliação de imóveis, arbitramento, emitindo laudos e pareceres técnicos;  Participar de planos gerais e específicos, que visem o posicionamento institucional frente à comunidade, no que tange a sua especialidade e formação;  Realizar treinamento na área de atuação, quando solicitado;  Atuar, na qualidade de instrutor de treinamentos e outros eventos de igual natureza,mediante participação prévia em processo de qualificação e autorização superior;  Operar equipamentos e sistemas de informática e outros, quando autorizado e  Necessário ao exercício das demais atividades;  Dirigir veículos leves, mediante autorização prévia, quando necessário ao exercício das demais atividades; | F38: CARGO: ASS. TECNICO DE ENGENHARIA FUNÇÃO: ASSISTENTE TÉCNICO DE ENGENHARIA CBO: 312105 | G38: PRODUÇÃO
A39: 414205 | B39: APONTADOR DE OBRA | C39: Apontam a produção e controlam a frequência de mão-de-obra. acompanham atividades de produção, conferem cargas e verificam documentação. preenchem relatórios, guias, boletins, plano de carga e recibos. controlam movimentação de carga e descarga nos portos, terminais portuários e embarcações. podem liderar equipes de trabalho | D39: FISICO: RUÌDO. RADIAÇÃO RADIAÇÃO NÃO IONIOZANTE ERGONOMICO: POSTURA INADEQUADA,QUIMICO: POEIRA MINERAIS ( SILICA LIVRE CRISTALIZADA ) ACIDENTE:ATROPELAMENTO, BATIDA CONTRA, QUEDA DE E MESMO NIVEL, . | E39: DESCRIÇÃO SINTÉTICA: APONATDOR DE OBRA. DESCRIÇÃO DETALHADA: Apontam a produção e controlam a frequência de mão-de-obra. acompanham atividades de produção, conferem cargas e verificam documentação. preenchem relatórios, guias, boletins, plano de carga e recibos. controlam movimentação de carga e descarga nos portos, terminais portuários e embarcações. podem liderar equipes de trabalhoTarefas de departamento pessoal para a gestão dos funcionários O anotador de mão de obra da construção civil trabalha para processar o tipo de mão de obra e outras tarefas executadas pelos operários em um canteiro de obras. Ele pode coletar dados de várias fontes, como planos de projeto, filmagens e fotografias. Além disso, ele também anota informações relacionadas a alimentação dos funcionários, transporte e vestuário ideal para trabalhar no canteiro de obras. Vale ressaltar que ele trabalha fazendo uma espécie de ponte entre o canteiro e a parte administrativa da empresa. | F39: CARGO: AUXILIA ADMINISTRATIVO DE OBRAS-CBO-411010 | G39: PRODUÇÃO
A40: 919110 | B40: LIDER DE LUBRIFICAÇÃO | C40: Lidera equipe que lubrifica as partes móveis de motores fixos, máquinas operatrizes e equipamentos auxiliares de produção, seguindo programa estabelecido e processos manuais e mecânicos, para evitar desgastes excessivos e garantir o melhor rendimento dos equipamentos e maquinas | D40: FISICO: RUIDO, RADIAÇÃO NÃO IONIZANTE,CALOR. QUIMICO: ÓLEOS E GRAXAS, POEIRA DE OBRA E SOLVENTES. ERGONOMICO: POSTURA INADEQUADA ACIDENTE: QUEDA DE MESMO NIVEL, ACINDENTES DE TRANSITO, PPROJEÇÃO DE PARTICULAS E BATIDAS CONTRA. | E40: DESCRIÇÃO SINTÉTICA:  Lubrifica e abastece máquinas e equipamentos, selecionando o material de limpeza e ferramentas necessários. Realiza inspeções preventivas, preenche relatórios e registros de ocorrências. DESCRIÇÃO DETALHADA:  Abastece maquinas e veiculos com diesel.  Lubrificar maquinas, veiculos e equipamentos.  Usar de equipamentos de lubrificação adequado para cada tipo de lubrificante. Manter sistema de identificação que permita usar o equipamento adequado x lubrificante x plano de lubrificação. Manter as FISPQs e Fichas de Emergência sempre próximas a cada lubrificante estocado caso necessite em situações de emergências.verifica o nível do óleo ou graxa, examinando depósitos e consultando manuais de lubrificação e outras instruções, para providenciar o atendimento às necessidades operacionais; prepara almotolias e bombas de lubrificação, enchendo-as com produto apropriado, para efetuar a operação programada; desmonta peças essenciais do equipamento, seguindo diagramas e manuais técnicos e utilizando ferramentas manuais e outros dispositivos, para verificar suas condições e efetuar a manutenção preventiva; aplica o lubrificante nos pontos indicados, seguindo as especificações ou seus conhecimentos técnicos, para conservar a máquina e melhorar seu desempenho; verifica o funcionamento das partes da máquina lubrificada, pondo-a a trabalhar experimentalmente, para certificar-se da eficácia da lubrificação efetuada; mantém em bom estado os filtros, tubulações e outras partes, reparando-as ou substituindo-as, se necessário, para assegurar seu funcionamento normal. Pode comunicar defeitos mecânicos encontrados, anormalidades observadas durante a lubrificação, fornecendo registros ou por outros meios, para facilitar a manutenção corretiva da máquina. Pode efetuar regulagens e pequenos reparos no equipamento de lubrificação | F40: CARGO: LIDER DE LUBRIFICADOR FUNÇÃO: LIDER DE LUBRIFICADOR CBO: 919110 L | G40: OFICINA
A41: 715705 | B41: MANGUERISTA | C41: Responsável fazer a aplicação de ligante betuminoso sobre a superfície da base da pavimentação através de uma mangueira com bico de aço através de caminhão espagidor. | D41: FISICO: RUIDO, RADIAÇÃO NÃO IONIZANTES. QUÍMICO: POEIRAS MINERAIS (SILICA LIVRE CRISTALIZADA), FUMOS E VAPORES ASFÁLTICOS ERGONOMICO: POSTURA INADEQUADA ACIDENTE: ATROPELAMENTO, COLISÃO E TOMBAMENTO, BATIDAS CONTRA, QUEDA DE MESMO NÍVEL. | E41: DESCRIÇÃO DETALHADA:  Executar trabalhos auxiliares, sob supervisão;  Resposavel em aplicação de ligante betuminoso sobre a superfície da base da pavimentação,através de uma mangueira com bico de aço;  Responsavel pelo aquecimento do material;  Acompanhamento do consumo do material;  Responsavel por verificar o motor da bomba do equipamento;  Avisar ao seu superior quando detectar irregularidades;  Vistoriar mangueira,óleo,combustível e agua;  Manter organizados, limpos e conservados os materiais, máquinas, equipamentos e local de trabalho, que estão sob sua responsabilidade;  Responsável pela manutenção e limpeza do equipamento;  Responsavel pela integridade do equipamento e acessórios:mangueiras,bicos espagidores etc... | F41: CARGO: MANGUERISTA FUNÇÃO: MANGUERISTA . CBO: 7157-05 | G41: PRODUÇÃO
A42: 391145 | B42: Analista de planejamento de manutenção. | C42: (Controlar produção e/ou manutenção): Coletar dados da produção e/ou da manutenção; controlar custos de manutenção; definir ações corretivas; estabelecer parâmetros de controle; identificar desvios no processo de produção e/ou de manutenção; monitorar fluxo de produção e/ou de manutenção; propor melhorias no processo de produção e/ou de manutenção; . | D42: FISICO: RUIDO, RADIAÇÃO NÃO IONIZANTES. QUÍMICO: POEIRAS DE OBRA ERGONOMICO: POSTURA INADEQUADA. ACIDENTE: ACIDENTES DE TRANSITO (COLISÕES E ATROPELAMENTOS), BATIDAS CONTRA, PROJEÇÃO DE PARTICULAS, QUEDA DE MESMO NÍVEL. | E42: DESCRIÇÃO SINTÉTICA:  Analista de planejamento de manutenção. DESCRIÇÃO DETALHADA: (planejar manutenção de máquinas e equipamentos): analisar capacidade de manutenção; elaborar cronograma de manutenção; emitir ordem de serviço; participar de grupos multidisciplinares para tomadas de decisões; planejar custos de manutenção; programar manutenção preventiva, preditiva e corretiva; quantificar demanda de manutenção por período; tratar informações): atualizar as informações; disponibilizar informações; elaborar gráficos e relatórios de controles; interagir com clientes e/ou fornecedores; registrar não conformidades; (trabalhar com segurança): cumprir normas e procedimentos da empresa; cumprir os procedimentos dos manuais dos fabricantes; cumprir requisitos dos orgãos reguladores; usar epi. | F42: CARGO: Analista de planejamento de manutenção FUNÇÃO: Analista de planejamento de manutenção CBO:391145 | G42: ADMINISTRATIVO
A43: 992115 | B43: BORRACHEIRO | C43: Realizam manutenção de equipamentos, montagem e desmontagem de pneu e alinha mento. controlam vida útil e utilização do pneu. trocam e ressulcam pneus. consertampneus a frio e a quente, reparam câmara de ar e balanceiam conjunto de roda e pneu.prestam socorro a veículos e lavam chassi e peças. trabalham seguindo normas desegurança, higiene, qualidade e proteção ao meio ambiente. | D43: FISICO: RUIDO, RADIAÇÃO NÃO IONIZANTE,CALOR. QUIMICO: ÓLEOS E GRAXAS, POEIRA DE OBRA E SOLVENTES. ERGONOMICO: POSTURA INADEQUADA ACIDENTE: QUEDA DE MESMO NIVEL, ACINDENTES DE TRANSITO, PPROJEÇÃO DE PARTICULAS E BATIDAS CONTRA. | E43: DESCRIÇÃO SINTÉTICA:  Atuar em atividades relativas à área de trocas e colagem de pneus, desmontagem, reparo e manutenção nos pneus de máquinas pesadas. DESCRIÇÃO DETALHADA:  Fiscalização da vida útil dos pneus com sugestões de recapagens, calibragem e outros assemelhados; prestar socorro a frota municipal; transportar o equipamento necessário para a atividade; zelar pela limpeza e pela manutenção, incluindo a necessária lubrificação, dos veículos e equipamentos da pesados.Além dos serviços de conserto e troca de pneus avariados, uma borracharia também pode oferecer serviços de alinhamento de direção, balanceamento de rodas, venda de pneus novos e/ou recauchutados e de câmaras de ar. | F43: CARGO: BORRACHEIRO FUNÇÃO: BORRACHEIRO CBO: 992115 | G43: OFICINA
A44: 715705-S | B44: OP.SELAGEM DE ASFÁTICAS I, II,III | C44: Operam máquinas e equipamentos, como seladora, ajustando comandos, acionando movimento das máquinas. Avaliam condições de funcionamento das máquinas e equipamentos, interpretando painel de instrumentos de medição, verificando fonte de alimentação, testando comandos de acionamento. Preparam a área para operação dos equipamentos e transportam materiais em máquinas e equipamentos. Trabalham seguindo normas de segurança, higiene, qualidade e proteção ao meio ambiente. Identificam serviços, instalações de material isolantes, selecionam materiais a serem aplicados, solicitam liberação da área de trabalho. | D44: FISICO: RUIDO, RADIAÇÃO NÃO IONIZANTES, VIBRAÇÃO DE CORPO INTEIRO. QUÍMICO: FUMOS ASFÁLTICOS E POEIRAS MINERAIS (SÍLICA LIVRE CRISTALIZADA) ERGONOMICO: POSTURA INADEQUADA. ACIDENTE:COLISÃO E TOMBAMENTO, BATIDAS CONTRA, QUEDA DE MESMO NÍVEL . | E44: DESCRIÇÃO SINTÉTICA: Atuar em atividades auxiliares relativas à execução de obras em geral DESCRIÇÃO DETALHADA: Selagem da trincas com Sika rodoselante. Identificam serviços de instalação de materiais isolantes, selecionam materiais a seremaplicados, solicitam liberação da área de trabalho, preparam o local e executam a insta lação de acordo com projetos, normas técnicas, normas de segurança e recomendaçõesdos fabricantes. providenciam descarte de resíduos.Revestir diferentes superfícies, sob supervisão, sob Supervisão superior; Auxiliar na instalação de molduras de portas, janelas, quadro de luz e outros; Aquecimentos da sika rodoselante; Auxiliar na limpeza em geral; Selagem da trincas com Sika rodoselante em rodovias e pistas pouso em aeroportos | F44: CARGO: OP.SELAGEM DE ASFÁTICAS I, II,III FUNÇÃO: SERVIÇOS OPERACIONAIS NA EXECUÇÃO DE OBRAS CBO: 715705 | G44: PRODUÇÃO
A45: 710205-G | B45: ENCARREGADO DE OBRAS GERAL | C45: Coordena e discutir com os encarregados instruções técnicas do projeto a ser desenvolvido. Interpretarplantas, gráficos e escalas. Orientar e acompanhar a equipe quanto a execução dos trabalhos cumprindo o cronograma. Coordenar a instalação e utilização de equipamentos e estruturas construtivas em canteiros de obra. Participar da instalação do canteiro de obras, demarcando a obra, conforme projeto. | D45: FISICO: RUIDO, RADIAÇÃO NÃO IONIZANTES. ERGONOMICO: POSTURA INADEQUADA. ACIDENTE: ATROPELAMENTO, BATIDAS CONTRA, PROJEÇÃO DE PARTICULAS, QUEDA DE MESMO NÍVEL. | E45: DESCRIÇÃO SINTÉTICA: Atuar em atividades relativas à área de organização, coordenação e supervisão de construção civil e pavimentação. DESCRIÇÃO DETALHADA: Organizar, coordenar e supervisionar grupos de trabalhadores que desenvolvem suas atribuições na área da construção civil, infraestrutura e pavimentação; Garantir o desenvolvimento do processo de execução das obras dentro dos Prazos e normas estabelecidas; Providenciar que as pessoas sob o seu comando utilizem equipamentos de Proteção individual (EPI), de acordo com as normas de segurança em vigor; Empenhar-se em buscar seu próprio desenvolvimento profissional; Buscar o desenvolvimento pessoal e profissional das pessoas que atuam sob seu comando; Acompanhar a evolução profissional das pessoas sob seu comando; Manter ou desenvolver visando o desempenho apropriado de suas funções, Atuar na qualidade de instrutor de treinamentos e outros eventos de igual Natureza, mediante participação prévia em processo de qualificação e Autorização superior; Dirigir veículos leves, mediante autorização prévia, quando necessário ao Exercício das demais atividades; Manter organizados, limpos e conservados os materiais, máquinas, Equipamentos e local de trabalho, que estão sob sua responsabilidade | F45: CARGO: ENCARREGADO GERAL FUNÇÃO: ENCARREGADO GERAL CBO: 123105 | G45: PRODUÇÃO
A46: 342115 | B46: CONTROLE DE SERV.DE MAQUINAS E VEICULOS | C46: Controlam, programam e coordenam operações de transportes em geral; acompanhamas operações de embarque, transbordo e desembarque de carga. verificam as condi ções de segurança dos meios de transportes e equipamentos utilizados, como também,da própria carga. supervisionam armazenamento e transporte de carga e eficiência operacional de equipamentos e veículos. controlam recursos financeiros e insumos,elaboram documentação necessária ao desembargo de cargas e atendem clientes. pesquisam preços de serviços de transporte, identificam e programam rotas e informamsobre condições do transporte e da carga. | D46: FISICO: RUIDO, RADIAÇÃO NÃO IONIZANTE. ERGONOMICO: POSTURA INADEQUADA ACIDENTE: QUEDA DE MESMO NIVEL, ACINDENTES DE TRANSITO, PPROJEÇÃO DE PARTICULAS E BATIDAS CONTRA. | E46: DESCRIÇÃO SINTÉTICA: Trabalham em empresas de PAVIMENTAÇÃO ASFALTICAS e serviços correlatos; de fabricação deprodutos têxteis, metalurgia básica, fabricação de máquinas e equipamentos, fabrica ção e montagem de veículos automotores, reboques e carrocerias, entre outras. são as salariados, com carteira assinada. atuam em equipe multidisciplinar, sob supervisão ocasional; em ambientes fechados; de forma presencial; em turnosde trabalho, com disponibilidade para atuar em horários irregulares, para atendimentoa situações imprevistas e de emergência. no desenvolvimento de algumas atividades,podem permanecer em posições desconfortáveis durante períodos e, ainda, podemestar expostos a ruído intenso e trabalhar sob pressão, podendo ocasionar estresse.Trabalham em empresas de transportes intermodais, predominantemente em empresasde transporte aéreo, aquaviário e terrestre. os profissionais do transporte multimodalpodem trabalhar de forma presencial e a distância, por rodízio de turnos. geralmente,trabalham em equipe multidisciplinar, sob supervisão ocasional. para essas ocupaçõespredomina o trabalho assalariado, com carteira assinada. eventualmente, desempe nham atividades que podem levar ao estresse constante. | F46: CARGO: Controle de serviços de maquinas e veículos FUNÇÃO: Controle de serviços de maquinas e veículos CBO: 342115 | G46: OFICINA
A47: 910105 | B47: ENCARREGADO MECÂNICA | C47: Supervisionam manutenção preventiva e preditiva, corretiva e emergencial de má quinas e equipamentos industriais, comerciais e residenciais; estabelecem indica dores de qualidade da manutenção; coordenam a construção de equipamentospara linha de produção de máquinas e equipamentos; elaboram documentaçãotécnica; administram recursos humanos e financeiros, e trabalham de acordo comnormas de segurança. | D47: FISICO: RUIDO, RADIAÇÃO NÃO IONIZANTE,CALOR. QUIMICO: ÓLEOS E GRAXAS, POEIRA DE OBRA E SOLVENTES. ERGONOMICO: POSTURA INADEQUADA ACIDENTE: QUEDA DE MESMO NIVEL, ACINDENTES DE TRANSITO, PPROJEÇÃO DE PARTICULAS E BATIDAS CONTRA. | E47: DSCRIÇÃO SINTÉTICA:  Supervisonam as atividades de auxílio relativas à área de montagem, desmontagem, reparo e manutenção de veículos. DESCRIÇÃO DETALHADA:SUPERVISONAM  Auxiliar no concerto, montagem e desmontagem, observando catálogos e manuais de peças e manutenção, interpretando descrições técnicas dos referidos catálogos e manuais dos equipamentos, máquinas e veículos;  Auxiliar na execução de serviços de manutenção mecânica corretiva e preventiva em veículos leves, pesados, máquinas, motores e equipamentos;  Auxiliar no reparo de defeitos, substituindo peças, fazendo ajustes, regulagens e lubrificação, segundo orientações;  Auxiliar no desmonte, limpeza e a montagem do motor, órgãos de transmissão, diferencial e outras partes;  Auxiliar no recondicionamento do equipamento elétrico, o alinhamento da direção e regulagem dos faróis do veículo;  Auxiliar o mecânico a retirar forros, cintos, revestimentos e carpete e providenciar seu reparo ou manutenção.  Auxiliar o mecânico com peças, ferramentas e mão-de-obra necessária.  Utilizar a carga horária de lhe é pertinente com dedicação, zelo e responsabilidade;  Utilizar a carga horária atribuída ao seu emprego, tão somente a serviço da empresa;  Zelar pela limpeza, conservação e manutenção dos aparelhos, ferramentas e ambiente de trabalho.  Dirigir veículos leves, mediante autorização prévia, quando necessário ao exercício das demais atividades.  Manter organizados, limpos e conservados os materiais;  local de trabalho, que estão sob sua responsabilidade.Auxilia na lubrificar máquinas e componentes; Ajustar, trocar, reparar e consertar componentes e partes da máquina; Montar e desmontar máquinas e equipamentos; Realizar inspeções e medições periódicas (manutenção preventiva);Executa processos de manutenção mecânica de máquinas industriais, desmontando, montando, recuperando ou substituindo peças e máquinas, respeitando procedimentos e normas técnicas de qualidade, segurança, meio ambiente e saúde.especializado em agricultura, mineração ou material rodante pesado: escavadeiras, retroescavadeiras, rolo compactador, moto niveladora e tratores, etc. uma das funções do mecânico de máquinas pesadas é planejar, supervisionar e participar dos trabalhos de manutenção corretiva e preventiva. | F47: CARGO: ENCARREGADO MECÂNICA FUNÇÃO: ENCARREGADO MECÂNICA CBO: 910105 | G47: OFICINA
A48: 214405 | B48: ENGENHEIRO MECÂNICA | C48: Projetam sistemas e conjuntos mecânicos, componentes, ferramentas e materiais, es pecificando limites de referência para cálculo, calculando e desenhando. implementamatividades de manutenção, testam sistemas, conjuntos mecânicos, componentes e fer ramentas, desenvolvem atividades de fabricação de produtos e elaboram documenta ção técnica. podem coordenar e assessorar atividades técnicas. | D48: FISICO: RUIDO, RADIAÇÃO NÃO IONIZANTE. ERGONOMICO: POSTURA INADEQUADA ACIDENTE: QUEDA DE MESMO NIVEL, ACINDENTES DE TRANSITO. | E48: DSCRIÇÃO SINTÉTICA:  Engenheiros mecânicos são responsáveis por realizar atividades voltadas a sistemas mecânicos, englobando as aplicações contidas nas macroáreas da profissão: materiais, processos de fabricação, fluido/térmicas, projetos mecânicos e gestão DESCRIÇÃO DETALHADA: O engenheiro mecânico é o profissional responsável por executar tarefas relacionadas aos sistemas mecânicos. Isso abrange áreas como materiais, processos de fabricação, termofluidos, projetos mecatrônicos e gestão. Ele desempenha um papel fundamental na condução de atividades relacionadas a sistemas mecânicos, abrangendo diversas áreas-chave da profissão. Isso inclui o domínio de materiais, processos de fabricação, sistemas fluido/térmicos, elaboração de projetos mecânicos e gestão. | F48: CARGO: ENGENHEIRO MECÂNICO FUNÇÃO: ENGENHEIRO MECÂNICA CBO: 214405 | G48: OFICINA
A49: 2142-05 | B49: ENGENHEIRO ORÇAMENTISTA PLENO | C49: Desenvolvem projetos de engenharia civil, executam obras, planejam, orçam e contratam empreendimentos, coordenam a operação e a manutenção dos mesmos. Controlam a qualidade dos suprimentos e serviços comprados e executados. Elaboram normas e documentação técnica. Podem prestar consultorias. | D49: , ERGONOMICO: POSTURA EM PÉ POR LONGOS PERIODOS. . | E49: DESCRIÇÃO SINTÉTICA:  Elaborar, executar e dirigir projetos de engenharia civil Orçamnetos de obras. DESCRIÇÃO DETALHADA:  Elaborar projetos de engenharia relativos a estrutura de edificações, tráfegos, vias urbanas e obras de pavimentação, sistemas de água e esgoto, aproveitamento de  Recursos naturais, serviços de equipamentos urbanos, rurais e regionais, entre outros;  Estudar características, especificações e preparar plantas, orçamentos de custos,técnicas de execução e outros dados, para possibilitar e orientar a construção,manutenção e reparo das obras, dentro dos padrões técnicos exigidos;  Efetuar vistorias, perícias, avaliação de imóveis, arbitramento, emitindo laudos e pareceres técnicos;  Participar de planos gerais e específicos, que visem o posicionamento institucional frente à comunidade, no que tange a sua especialidade e formação;  Realizar treinamento na área de atuação, quando solicitado;  Atuar, na qualidade de instrutor de treinamentos e outros eventos de igual natureza,mediante participação prévia em processo de qualificação e autorização superior;  Operar equipamentos e sistemas de informática e outros, quando autorizado e  Necessário ao exercício das demais atividades;  Dirigir veículos leves, mediante autorização prévia, quando necessário ao exercício das demais atividades; | F49: CARGO: ENGENHEIRO ORÇAMENTISTA PLENO FUNÇÃO: ENGENHEIRO ORÇAMENTISTAS PLENO CBO:3214205 | G49: ADMINISTRATIVO
A50: 411010-RH | B50: AUXILIAR ADMINISTRATIVO DE RH | C50: Os agentes, assistentes e auxiliares administrativos realizam serviços de apoio nas áreas de recursos humanos, administração, finanças e logística, atendendo fornecedores e clientes, prestando e recebendo informações sobre produtos e serviços, tratando de documentos diversos, cumprindo todos os procedimentos necessários em relação a eles. | D50: FISICO: RUIDO ERGONOMICO: POSTURA EM PÉ POR LONGOS PERÍODOS | E50: DESCRIÇÃO DETALHADA:  Recebimento de documentos e correspondências, assim como sua organização.  Digitação de documentos.  Elaboração e preenchimento de planilhas de controle interno.  Auxílio ao departamento financeiro com lançamento.  Auxiliar operações diárias das funções e obrigações de RH  Compilar e atualizar registros do funcionário (cópias impressas e digitais)  Processar a documentação e preparar relatórios relacionados com as atividades do pessoal (agenciamento, recrutamento, treinamento, reclamações, avaliações de desempenho etc.)  Solicitações de funcionário relacionadas com problemas, regras e regulamentos de recursos humanos  Auxiliar na preparação da folha de pagamento fornecendo dados relevantes (ausências, bônus, licenças etc.)  Elaborar Relatórios e documentação mensais ao cliente  Conduzir a orientação inicial para funcionários recentemente contratados  Auxiliar os nossos recrutadores na seleção de candidatos e atualizar o nosso banco de dados.  Apoiar os processos de admissão, integração e desligamento;  Elaboração e preenchimento de planilhas de controles. Exemplo: controle de férias dos colaboradores;  Fazer a gestão de ponto;  Responder dúvidas e solicitações dos colaboradores acerca dos processos do RH  Auxiliar o no lançamento benefícios e adicionais que incidem na folha de pagamento  Suporte as rotinas do departamento Pessoal;  Atendimento interno à colaboradores. | F50: CARGO: AUXILIA ADMINISTRATIVO DE RH-CBO-411010 | G50: ADMINISTRATIVO
A51: 4110-10 F | B51: ASSISTENTE FINANCEIRO | C51: O assistente financeiro é responsável por monitorar receitas e despesas, gerenciar contas a pagar e receber, elaborar relatórios financeiros, preparar orçamentos e planejamentos financeiros, além de ajudar na tomada de decisões estratégicas relacionadas às finanças. | D51: FISICO: RUIDO ERGONOMICO: POSTURA EM PÉ POR LONGOS PERÍODOS | E51: DESCRIÇÃO DETALHADA:  Contas a pagar  Receber e fazer triagem de notas, boletos e faturas.  Inserir pagamento no banco  Fazer conciliação dos pagamentos realizados  Arquivamento de movimentos financeiros/pagamentos  Analise de custos dos lançamentos  Contas a receber  Fazer lançamento das notas no sistema  Conferência de boletos e notas fiscais  Fazer a conciliação dos recebimentos efetivados na conta bancária  Acompanhar recebimentos de clientes e fornecedores  Tesouraria/ Fundo Fixo  Conciliação Bancária  Aplicação/Resgate de financeira  Administrar fundo fixo de reembolso  Lançar notas e cupons no sistema  Baixar títulos pagos e recebidos em suas respectivas contas bancárias.  Lançar tarifas debitadas na conta corrente.  Apurar/lançar receitas financeiras, mensalmente. | F51: CARGO: ASS. FINACEIRO FUNÇÃO: ASSISTENTE FINACEIRO CBO: 4110-10 F | G51: ADMINISTRATIVO
A52: 2525-45 | B52: ANALISTA FINANCEIRO | C52: O Analista Financeiro planeja, gere e analisa os recursos financeiros de uma empresa. É seu papel garantir a rentabilidade nas contas e investimentos, bem como ficar de olho nos gastos e ver os recursos disponíveis. | D52: FISICO: RUIDO ERGONOMICO: POSTURA EM PÉ POR LONGOS PERÍODOS | E52: DESCRIÇÃO DETALHADA:  Contas a pagar  Receber e fazer triagem de notas, boletos e faturas.  Inserir pagamento no banco  Fazer conciliação dos pagamentos realizados  Arquivamento de movimentos financeiros/pagamentos  Analise de custos dos lançamentos  Contas a receber  Emitir notas fiscais conforme solicitações recebidas  Fazer lançamento contábil das notas no sistema  Conferência de boletos e notas fiscais  Fazer a conciliação dos recebimentos efetivados na conta bancária  Acompanhar recebimentos de clientes e fornecedores  Tesouraria/ Fundo Fixo  Conciliação Bancária  Aplicação/Resgate de financeira  Administrar fundo fixo de reembolso  Lançar notas e cupons no sistema  Baixar títulos pagos e recebidos em suas respectivas contas bancárias.  Lançar tarifas debitadas na conta corrente.  Apurar/lançar receitas financeiras, mensalmente.; Fluxo de caixa; Analise de documentos; Analise de apuração dos resultados financeiros; Controle de diretos e indiretos de custos; Apoio ao Departamento Contábil, à gestão de documentos e à análise de Balanço/DRE.; Conferência das bases de cálculos de impostos.; Análise de faturamento e tributária.; Desenvolvimento de Análise ; Desenvolvimento e controle ; Relatórios Gerenciais | F52: CARGO: ANALISTA. FINACEIRO FUNÇÃO: ANALISTA FINACEIRO CBO: 2525-45 | G52: ADMINISTRATIVO
A53: 4221-05 | B53: RECEPCIONISTA | C53: Recepcionam e prestam serviços de apoio a clientes, visitantes, colaboradores; prestam atendimento telefônico e fornecem informações em escritórios, outros estabelecimentos; marcam entrevistas ou e recebem clientes ou visitantes; averiguam suas necessida des e dirigem ao lugar ou a pessoa procurados; agendam serviços, observam normas internas de segurança, conferindo documentos e idoneidade dos clientes enotificando seguranças sobre presenças estranhas; fecham contas e estadas de clientes.organizam informações e planejam o trabalho do cotidiano. | D53: FISICO: RUIDO ERGONOMICO: POSTURA EM PÉ POR LONGOS PERÍODOS | E53: DESCRIÇÃO DETALHADA:  Executam serviços de apoio nas áreas de recursos humanos, administração, finanças e logística, atendem fornecedores e clientes, fornecendo e recebendo informações sobre produtos e serviços, tratam de documentos variados, cumprindo todo o procedimento necessário referente aos mesmos Comunicação., Multitarefa., Habilidades sociais., Organização., Habilidades técnicas., Resistência ao estresse., Resolução de problemas., Empatia. Como já contado, o(a) recepcionista faz o contato direto com o público e cliente, por isso, saber se comunicar bem é a primeira habilidade imprescindível para quem quer atuar como tal. Além disso, o mercado de trabalho busca profissionais que contam com certas características | F53: CARGO: RECEPCIONISTA FUNÇÃO: RECPICIONISTA CBO: 4221-05 | G53: ADMINISTRATIVO
A54: 514310 | B54: AUXILIAR DE MANUTENÇÃO GERAL | C54: Executam serviços de manutenção elétrica, mecânica, hidráulica, carpintaria e alvenaria, substituindo, trocando, limpando, reparando e instalando peças, componentes e equipamentos. Conservam vidros e fachadas, limpam recintos e acessórios e tratam de piscinas. Trabalham seguindo normas de segurança, higiene, qualidade e proteção ao meio ambiente. | D54: FISICO: RUIDO, RADIAÇÃO NÃO IONIZANTE,CALOR. QUIMICO:DETERGENTE DESENGRAXANTE; DIESEL; GRAXA E OLEO LUBRIFICANTE . ERGONOMICO: POSTURA EM PÉ LONGOS PERIODO. ACIDENTE: TRABALHO EM ALTURA | E54: DESCRIÇÃO SINTÉTICA:  Auxiliar de manutenção é um profissional que planeja e executa serviços com o intuito de arrumar ou prevenir que algum acidente aconteça com as máquinas e equipamentos que são utilizados, seja no serviços de facilities ou segurança. Eles também cuidam dos espaços DESCRIÇÃO DETALHADA:  Zelar pela guarda, conservação, manutenção, higiene e limpeza dos equipamentos, instrumentos e demais materiais utilizados, bem como do local de trabalho. Separar materiais recicláveis para descarte. Executar o tratamento e descarte dos resíduos de materiais provenientes do seu local de trabalho.;  Auxiliar no reparo de defeitos, substituindo peças, fazendo ajustes, regulagens e lubrificação, segundo orientações;  Auxiliar no desmonte, limpeza e a montagem do motor, órgãos de transmissão, diferencial e outras partes; Auxiliar o mecânico com peças, ferramentas e mão-de-obra necessária.  Utilizar a carga horária de lhe é pertinente com dedicação, zelo e responsabilidade;  Utilizar a carga horária atribuída ao seu emprego, tão somente a serviço da empresa;  Zelar pela limpeza, conservação e manutenção dos aparelhos, ferramentas e ambiente de trabalho.  Dirigir veículos leves, mediante autorização prévia, quando necessário ao exercício das demais atividades.  Manter organizados, limpos e conservados os materiais;  local de trabalho, que estão sob sua responsabilidade. | F54: CARGO: AUXILIAR DE MANUTENÇÃO GERAL FUNÇÃO: AUXILIAR DE MANUTENÇÃO GERAL CBO: 514310 | G54: SEDE OFICINA
A55: 715405 | B55: OPERADOR DE BETONEIRA ELETRICA. | C55: Operam a betoneira misturar materiais nela que se coloca água, areia, cimento e agregados para a formação do concreto, preparar o concreto por meio da adequada mistura dos materiais previamente dosados, utilizado no preparo do concreto e argamassa.. | D55: FISICO: RUIDO, RADIAÇÃO NÃO IONIZANTE. QUÍMICO: POEIRAS MINERAIS (SILICA LIVRE CRISTALIZADA), ARGAMASSA, CIMENTO. ERGONOMICO: POSTURA INADEQUADA. ACIDENTE: ATROPELAMENTOS, BATIDAS CONTRA, CORTES E PERFURAÇÕES, PROJEÇÃO DE PARTÍCULAS, QUEDAS DE MESMO NIVEL | E55: DESCRIÇÃO SINTÉTICA: Atuar em atividades auxiliares relativas à execução de obras em geral DESCRIÇÃO DETALHADA: Para evitar risco de ferimento,morte, incêndio,choque elétrico,quando usar a máquina, observe as informações relacionadasabaixo: » A máquina foi desenvolvida exclusivamente para o uso de mistura de matérias na temperatura ambiente e capacidade de carga defi nida (ler todo manual para conhecer); » Instalação e funcionamento somente podem ser executadas por pessoas qualifi cadas, capacitadas e supervisionadas por profi ssional legalmente habilitado; » Operação somente por pessoas capacitadas; » Não instale ou guarde a máquina em local sujeito a chuvas ou ao mau tempo; » Não repare ou troque qualquer parte da máquina e nem faça nenhum reparo que não seja explicitamente recomendado neste manual. Para manutenção, entre em contato com a Rede Autorizada ou Fabricante; » Observe atentamente as instruções de instalação, principalmente, quanto à voltagem de alimentação e ao aterramento; » Nunca conecte ou desconecte o plugue com as mãos molhadas, para evitar uma descarga elétrica; » Sempre trabalhar de botina/sapato de segurança e outros EPI’S que se fi zerem necessário segundo especifi cação do responsável pela segurança do trabalhador do local de trabalho 3.1. cuIdAdOs gERAIs » Antes de operar o equipamento faça uma inspeção de pré-operação (Item 3.4) para maior segurança; » Somente pessoas qualifi cadas, capacitadas e autorizadas devem testar, operar, fazer manutenção ou reparar o equipamento; » Somente um operador de cada vez pode operar a máquina; » Não deixe o equipamento sozinho quando estiver em funcionamento; » Sempre que operar o equipamento usar E.P.I.’s – Equipamento de Proteção Individual – como: capacete, protetor auricular, luvas de borracha, calçados apropriados e roupas de proteção (Os EPI’s corretos devem ser informados no PPRA da empresa e/ou PCMAT da obra (Conforme NR 09). » Mantenha as mãos, cabelos, roupas soltas e ferramentas longe das partes móveis do equipamento; » É proibido trabalhar no equipamento com roupas soltas e cabelos longos por existir o risco de agarramento destes pelas partes móveis do equipamento gerando acidentes graves podendo até acontecer morte; » Não opere o equipamento quando estiver sob infl uência de remédios, bebidas alcoólicas e outros que prejudique a atenção no trabalho com betoneira; MANUAL DE OPERAÇÃO E MANuTENÇÃO 4 Sempre limpe o equipamento após o uso e antes de armazená-lo (Ver procedimento de limpeza – item 7). » Quando estiver em funcionamento, animais e pessoas não autorizadas devem ser mantidos a uma distância segura | F55: CARGO: OPERADOR DE BETONEIRA ELETRICA. FUNÇÃO: SERVIÇOS OOPERADOR DE BETONEIRA ELETRICA NA OBRAS CBO: 715405 | G55: PRODUÇÃO
A56: 782305 | B56: MOTORISTA | C56: Dirigir e manobrar veículos e transportar pessoas, valores e outros compatíveis com a categoria da CNH,Providenciar para que sejam executadas as manutenções programadas do veículo. | D56: RISCO FISICO: RUIDO, RADIAÇÃO NÃO IONIZANTE, VIBRAÇÕES DE CORPO INTEIRO. RISCO QUÍMICO: POEIRAS MINERAIS (SILICA LIVRE CRISTALIZADA) ; RISCO ERGONÔMICO: POSTURA INADEQUADA RISCO DE ACIDENTE: COLISÃO E TOMBAMENTO, BATIDAS CONTRA, QUEDA DO MESMO NÍVEL | E56: DESCRIÇÃO SINTÉTICA:  Condução de veículos de médio e grande porte. DESCRIÇÃO DETALHADA:  Dirigir veículos de médio e grande porte;  Transportar materiais, equipamentos e documentos;  Verificar, diariamente, as condições de funcionamento do veículo, antes de sua Utilização;  Comunicar a chefia imediata por escrito assinando a comunicação da necessidade de reparos no veículo;  Zelar pela segurança de passageiros no caso de ajudante;  Orientar e auxiliar na carga e descarga de materiais;  Amarrar a carga e conferir;  Atentar – se ao peso da carga e zelar pelo equipamento;  Registrar dados preestabelecidos, sobre a utilização diária do veículo;  Verificar, trocar ou completar, se necessário cotidianamente o óleo, a água e o Combustível;  Efetuar limpeza dos materiais que ficam encostados na caçamba;  Limpar placas, faróis e sinaleiros dos veículos utilizados;  Estar sempre atualizado com as leis e normas de trânsito e respeita- las;  Realizar treinamento na área de atuação, quando solicitado;  Utilizar a carga horária que lhe é pertinente com zelo, dedicação, responsabilidade e a serviço da Empresa;  Manter organizados, limpos e conservados os materiais, máquinas, equipamentos e local de trabalho, que estão sob sua responsabilidade;  Operar de acordo com a capacidade e especificações do fabricante. | F56: CARGO: SERVIÇO DE CONDUÇÃO DE VEÍCULOS DE MÉDIO E GRANDE PORTE. FUNÇÃO: MOTORISTA CBO: 7823-05 | G56: PRODUÇÃO
A57: 2147-05 | B57: ESTAGIÁRIO(A). DE ENGENHARIA | C57: Auxiliam engenheiros civis em atividades como acompanhamento de obras, desenvolvimento de projetos, elaboração de relatórios técnicos, entre outras tarefas relacionadas à engenharia civil. | D57: FISICO: RUIDO, RADIAÇÃO NÃO IONIZANTES. QUÍMICO: POEIRAS DE OBRA ERGONOMICO: POSTURA INADEQUADA. ACIDENTE: ACIDENTES DE TRANSITO (COLISÕES E ATROPELAMENTOS), BATIDAS CONTRA, PROJEÇÃO DE PARTICULAS, QUEDA DE MESMO NÍVEL. | E57: DESCRIÇÃO SINTÉTICA:  Auxiliar na elaborar, executar e dirigir projetos de engenharia civil. DESCRIÇÃO DETALHADA:  Auxilia na elaborar projetos de engenharia relativos a estrutura de edificações, tráfegos, vias urbanas e obras de pavimentação, sistemas de água e esgoto, aproveitamento de  Recursos naturais, serviços de equipamentos urbanos, rurais e regionais, entre outros;  Estudar características, especificações e preparar plantas, orçamentos de custos,técnicas de execução e outros dados, para possibilitar e orientar a construção,manutenção e reparo das obras, dentro dos padrões técnicos exigidos;  Efetuar vistorias, perícias, avaliação de imóveis, arbitramento, emitindo laudos e pareceres técnicos;  Participar de planos gerais e específicos, que visem o posicionamento institucional frente à comunidade, no que tange a sua especialidade e formação;  Realizar treinamento na área de atuação, quando solicitado;  Atuar, na qualidade de instrutor de treinamentos e outros eventos de igual natureza,mediante participação prévia em processo de qualificação e autorização superior;  Operar equipamentos e sistemas de informática e outros, quando autorizado e  Necessário ao exercício das demais atividades;  Dirigir veículos leves, mediante autorização prévia, quando necessário ao exercício das demais atividades; | F57: CARGO: ESTAGIÁRIO ENGENHARIA FUNÇÃO: ESTAGIÁRIO DE ENGENHARIA CBO: 2147-05 | G57: PRODUÇÃO
A58: 2147-05 E | B58: ESTAGIÁRIO(A) | C58: Executam serviços de apoio nas áreas de recursos humanos, administração, finanças e logística, atendem fornecedores e clientes, fornecendo e recebendo informações sobre produtos e serviços, tratam de documentos variados, cumprindo todo o procedimento necessário referente aos mesmos, preparam relatórios e planilhas, executam serviços gerais de escritórios. | D58: FISICO: RUIDO, ERGONOMICO: POSTURA EM PÉ POR LONGOS PERÍODOS. | E58: DESCRIÇÃO SINTÉTICA:  Auxiliar na elaborar, executar e dirigir projetos de administrativos. DESCRIÇÃO DETALHADA:  Solicitação de material Solicitar via sistema Mega materiais; Diário de obra Preenchimento das atividades diárias; Controle Almoxarifado Apoio no controle do estoque ; Controle de Produção; Apoio no monitoramento dos índices; Pedido de Compra; Solicitação via sistema Mega; Medições Medições de terceiros Auxilia na elaborar projetos de administrativo a estrutura de edificações, tráfegos, vias urbanas e obras de pavimentação, sistemas de água e esgoto, aproveitamento de  Recursos naturais, serviços de equipamentos urbanos, rurais e regionais, entre outros;  Estudar características, especificações e preparar plantas, orçamentos de custos,técnicas de execução e outros dados, para possibilitar e orientar a construção,manutenção e reparo das obras, dentro dos padrões técnicos exigidos;  Participar de planos gerais e específicos, que visem o posicionamento institucional frente à comunidade, no que tange a sua especialidade e formação;  Realizar treinamento na área de atuação, quando solicitado;  Atuar, na qualidade de instrutor de treinamentos e outros eventos de igual natureza,mediante participação prévia em processo de qualificação e autorização superior;  Operar equipamentos e sistemas de informática e outros, quando autorizado e  Necessário ao exercício das demais atividades;  Dirigir veículos leves, mediante autorização prévia, quando necessário ao exercício das demais atividades; | F58: CARGO: ESTAGIÁRIO(A) FUNÇÃO: ESTAGIÁRIO (A) CBO: 2147-05 | G58: PRODUÇÃO
A59: 715140-P | B59: ENCARREGADO DE PAVIMENTAÇÃO PLENO | C59: Supervisão das equipes dentro dos canteiros de obras, aplicando práticas ambientais pertinentes, Supervisionam equipes de trabalhadores da pavimentação asfálticas, Controle dos recursos produtivos da obra (arranjos físicos, equipamentos, materiais, insumos).e equipes de trabalho), conciliando com práticas ambientais, Inspeção da qualidade dos materiais e insumos e orientação sobre especificação, utilização e manejo ambientalmente correto, Coordenação do fluxo de movimentação dos materiais e equipamentos, Controle das normas de segurança, higiene e proteção ao meio ambiente, Administração do cronograma da obra, Aplicação de práticas ambientais visando o consumo racional de recursos, Condenar os trabalhos de pavimentação asfáltica. | D59: FISICO: RUIDO, RADIAÇÃO NÃO IONIZANTE. QUÍMICO: POEIRAS MINERAIS (SILICA LIVRE CRISTALIZADA) ERGONOMICO: POSTURA INADEQUADA ACIDENTE:ATROPELAMENTOS, QUEDA DE MESMO NÍVEL. | E59: DESCRIÇÃO SINTÉTICA: Atuar em atividades relativas à área de organização, coordenação e supervisão de construção civil e pavimentação. DESCRIÇÃO DETALHADA: Organizar, coordenar e supervisionar grupos de trabalhadores que desenvolvem suas atribuições na área da construção civil e pavimentação, infraestrutura e pavimentação; Garantir o desenvolvimento do processo de execução das obras dentro dos Prazos e normas estabelecidas; Providenciar que as pessoas sob o seu comando utilizem equipamentos de Proteção individual (EPI), de acordo com as normas de segurança em vigor; Empenhar-se em buscar seu próprio desenvolvimento profissional; Buscar o desenvolvimento pessoal e profissional das pessoas que atuam sob seu comando; Acompanhar a evolução profissional das pessoas sob seu comando; Manter ou desenvolver visando o desempenho apropriado de suas funções, Atuar na qualidade de instrutor de treinamentos e outros eventos de igual Natureza, mediante participação prévia em processo de qualificação e Autorização superior; Dirigir veículos leves, mediante autorização prévia, quando necessário ao Exercício das demais atividades; Manter organizados, limpos e conservados os materiais, máquinas, Equipamentos e local de trabalho, que estão sob sua responsabilidade | F59: CARGO: ENCARREGADO DE PAVIMENTAÇÃO FUNÇÃO: ENCARREGADO DE PAVIMENTAÇÃO CBO: 715140 | G59: PRODUÇÃO
A60: 214915 | B60: ENG. SEG DO TRABALHO | C60: Controlam perdas de processos, produtos e serviços ao identificar, determinar e analisar causas de perdas, estabelecendo plano de ações preventivas e corretivas. Desenvolvem, testam e supervisionam sistemas, processos e métodos produtivos, gerenciam atividades de segurança no trabalho e do meio ambiente, gerenciam exposições a fatores ocupacionais de risco à saúde do trabalhador, planejam empreendimentos e atividades produtivas e coordenam equipes, treinamentos e atividades de trabalho. Os Engenheiros de Logística também gerenciam as operações de logística em três eixos: transportes, armazenamento e inteligência, inclusive no que se refere à logística reversa. | D60: FISICO: RUIDO, RADIAÇÃO NÃO IONIZANTE. QUÍMICO: POEIRAS POEIRAS MINERAIS (SILICA LIVRE CRISTALIZADA); ERGONOMICO: POSTURA INADEQUADA ACIDENTE:ATROPELAMENTOS, QUEDA DE MESMO NÍVEL. | E60: DESCRIÇÃO SINTÉTICA:  Aplicar os conhecimentos de segurança e medicina do trabalho, de modo a reduzir e eliminar os riscos à saúde do trabalhador. DESCRIÇÃO DETALHADA:  Orientar e coordenar o sistema de segurança do trabalho, investigando riscos E causas de acidentes e analisando esquemas de prevenção, para garantir a Integridade dos colaboradores;  Inspecionar locais, instalações e equipamentos coletivos e individuais, observando as condições de trabalho, para determinar fatores e riscos de acidentes;  Estabelecer normas e dispositivos de segurança, sugerindo eventuais modificações nos equipamentos e instalações e verificando sua observância, para prevenir acidentes;  Inspecionar os postos de combate a incêndios, examinando as mangueiras, Hidrantes, extintores e equipamentos de proteção contra incêndios, para certificar-se de suas perfeitas condições de funcionamento;  Comunicar os resultados de suas inspeções, elaborando relatórios, para propor a reparação ou renovação do equipamento de extinção de incêndios e outras medidas de segurança;  Registrar acidentes ocorridos, examinando as condições da ocorrência, para  Identificar suas causas e propor as providências cabíveis;  Manter contato com os serviços médico e social da empresa ou de outra instituição,utilizando os meios de comunicação oficiais, para facilitar o atendimento necessário aos acidentados;  Registrar irregularidades ocorridas, anotando-as em formulários próprios e elaborando estatísticas de acidentes, para obter subsídios destinados à melhoria das medidas de segurança;  Buscar seu próprio desenvolvimento profissional;  Instruir os funcionários da empresa sobre normas de segurança, combate a incêndios e demais medidas de prevenção de acidentes, ministrando palestras e treinamento,para que possam agir acertadamente em casos de emergência | F60: CARGO: TÉCNICO SEGURANÇA DO TRABALHO FUNÇÃO: GESTÃO SMS E OUTROS. CBO: 351605 | G60: SUPERVISÃO
A61: 2142.05 | B61: ENG. DE PLANEJAMENTO | C61: Desenvolvem projetos de engenharia civil, executam obras, planejam, orçam e contratam empreendimentos, coordenam a operação e a manutenção dos mesmos. Controlam a qualidade dos suprimentos e serviços comprados e executados. Elaboram normas e documentação técnica. Podem prestar consultorias. | D61: FISICO: RUIDO, RADIAÇÃO NÃO IONIZANTE. QUÍMICO: POEIRAS MINERAIS (SILICA LIVRE CRISTALIZADA) ERGONOMICO: POSTURA INADEQUADA ACIDENTE: QUEDA DE MESMO NÍVEL. | E61: DESCRIÇÃO SINTÉTICA:  Elaborar, executar e dirigir projetos de engenharia civil. DESCRIÇÃO DETALHADA:  Elaborar projetos de engenharia relativos a estrutura de edificações, tráfegos, vias urbanas e obras de pavimentação, sistemas de água e esgoto, aproveitamento de  Recursos naturais, serviços de equipamentos urbanos, rurais e regionais, entre outros;  Estudar características, especificações e preparar plantas, orçamentos de custos,técnicas de execução e outros dados, para possibilitar e orientar a construção,manutenção e reparo das obras, dentro dos padrões técnicos exigidos;  Efetuar vistorias, perícias, avaliação de imóveis, arbitramento, emitindo laudos e pareceres técnicos;  Participar de planos gerais e específicos, que visem o posicionamento institucional frente à comunidade, no que tange a sua especialidade e formação;  Realizar treinamento na área de atuação, quando solicitado;  Atuar, na qualidade de instrutor de treinamentos e outros eventos de igual natureza,mediante participação prévia em processo de qualificação e autorização superior;  Operar equipamentos e sistemas de informática e outros, quando autorizado e  Necessário ao exercício das demais atividades;  Dirigir veículos leves, mediante autorização prévia, quando necessário ao exercício das demais atividades; | F61: CARGO: ENGENHEIRO PLANEJAMENTO FUNÇÃO: ENGENHEIRO CIVIL CBO:2142.05 | G61: ADMINISTRATIVO
A62: 312320-E | B62: ENCARREGADO DE TOPOGRAFIA | C62: Executam levantamentos geodésicos e topo hidrográficos, por meio de levantamentos altimétricos e planimétricos, implantam, no campo, pontos de projeto, locando obras de sistemas de transporte, obras civis, industriais, rurais e delimitando glebas, planejam trabalhos em geomática, analisam documentos e informações cartográficas, interpretando fotos terrestres, fotos aéreas, imagens orbitais, cartas, mapas, plantas, identificando acidentes geométricos e pontos de apoio para georreferenciamento e amarração, coletando dados geométricos. Efetuam cálculos e desenhos e elaboram documentos cartográficos, definindo escalas e cálculos cartográficos, efetuando aerotriangulação, restituindo fotografias aéreas. | D62: FISICO: RUIDO, RADIAÇÃO NÃO IONIZANTE. QUÍMICO: POEIRAS MINERAIS (SILICA LIVRE CRISTALIZADAS) ERGONOMICO: POSTURA INADEQUADA ACIDENTE:ATROPELAMENTOS, BATIDAS CONTRA, QUEDA DE MESMO NÍVEL. | E62: ESCRIÇÃO SINTÉTICA: Atuar em atividades relativas à área, auxiliando nos serviços topograficos. DESCRIÇÃO DETALHADA: . Analisar documentos e informações cartográficas, interpretando fotos terrestres, fotos aéreas, imagens orbitais, cartas, mapas, plantas, identificando acidentes geométricos e pontos de apoio para georeferenciamento e amarração, coletando dados geométricos; . Efetuar cálculos e desenhos; Elaborar documentos cartográficos, definindo escalas e cálculos cartográficos, efetuando aerotriangulação, restituindo fotografias aéreas. • Executam levantamentos geodésicos e topohidrográficos, por meio de levantamentos altimétricos e planimétricos; implantam, no campo, pontos de projeto, locando obras de sistemas de transporte, obras civis, industriais, rurais e delimitando glebas; planejam trabalhos em geomática; analisam documentos e informações cartográficas, interpretando fotos terrestres, fotos aéreas, imagens orbitais, cartas, mapas, plantas, identificando acidentes geométricos e pontos de apoio para georreferenciamento e amarração, coletando dados geométricos. efetuam cálculos e desenhos e elaboram documentos cartográfico • Exercer tarefas de topografia, procedendo ao levantamento, anotação e cálculo de dados da área a ser demarcada bom como efetuar o desenho da área. Zelar pela limpeza e conservação da aparelhagem topográfica. Auxiliar nas atividades de ensino, pesquisa e extensão. | F62: CARGO: TOPOGRAFO FUNÇÃO: SERVIÇOS DE TOPOGRAFIA | G62: PRODUÇÃO
A63: 2149-10 | B63: ENGENHEIRO QUALIDADE | C63: Desenvolvem projetos de engenharia civil; executam obras; planejam, orçam e contratam empreendimentos; coordenam a operação e a manutenção dos mesmos. Controlam a qualidade dos suprimentos e serviços comprados e executados. Elaboram normas e documentação técnica. Podem prestar consultorias. | D63: FISICO: RUIDO, RADIAÇÃO NÃO IONIZANTE. ERGONOMICO: POSTURA INADEQUADA ACIDENTE: QUEDA DE MESMO NÍVEL. | E63: DESCRIÇÃO SINTÉTICA:  Planeja de controle de qualidade, Planeja e elaborar, executar e dirigir projetos de engenharia civil. DESCRIÇÃO DETALHADA:  Criar um produto, projetando testes, identificando defeitos e analisando os resultados para afinar o processo de produção, Elaborar projetos de engenharia relativos a estrutura de edificações, tráfegos, vias urbanas e obras de pavimentação, sistemas de água e esgoto, aproveitamento de Recursos naturais, serviços de equipamentos urbanos, rurais e regionais, entre outros;  Trabalha de forma a garantir que os produtos, processos e sistemas estejam em conformidade com os padrões e requisitos de qualidade estabelecidos. Eles desempenham diversas atividades para atingir esse objetivo; Estudar características, especificações e preparar plantas, orçamentos de custos,técnicas de execução e outros dados, para possibilitar e orientar a construção,manutenção e reparo das obras, dentro dos padrões técnicos exigidos;  Efetuar vistorias, perícias, avaliação de imóveis, arbitramento, emitindo laudos e pareceres técnicos;  Participar de planos gerais e específicos, que visem o posicionamento institucional frente à comunidade, no que tange a sua especialidade e formação;  Realizar treinamento na área de atuação, quando solicitado;  Atuar, na qualidade de instrutor de treinamentos e outros eventos de igual natureza,mediante participação prévia em processo de qualificação e autorização superior;  Operar equipamentos e sistemas de informática e outros, quando autorizado e  Necessário ao exercício das demais atividades;  Dirigir veículos leves, mediante autorização prévia, quando necessário ao exercício das demais atividades; | F63: CARGO: ENGENHEIRO QUALIDADE FUNÇÃO: ENGENHEIRO QUALIDADE CBO:214910
A64: 7170-10 | B64: MARTELETEIRO | C64: Demolem edificações de concreto, de alvenaria e outras estruturas; preparam canteirosde obras, limpando a área e compactando solos. efetuam manutenção de primeiro nível,limpando máquinas e ferramentas, verificando condições dos equipamentos e reparandoeventuais defeitos mecânicos nos mesmos. realizam escavações e preparam massa deconcreto e outros materiais. | D64: FISICO: RUIDO, RADIAÇÃO NÃO IONIZANTE, VIBRAÇÃO DE CORPO INTEIRO. QUÍMICO: POEIRAS MINERAIS (SILICA LIVRE CRISTALIZADA). ERGONOMICO: POSTURA INADEQUADA. ACIDENTE: COLISÃO E TOMBAMENTO, BATIDAS CONTRA, QUEDAS DE MESMO NIVEL. | E64: DESCRIÇÃO SINTÉTICA: Atuar em atividades Operar martelete para perfurar e romper concreto, cerâmica, rochas e solos em obras de construção. DESCRIÇÃO DETALHADA: Identifica falhas nas rochas Retira pedras e fragmentos soltos Faz desmonte manual de rochas, utilizando ferramentas manuais Sempre trabalhar de botina/sapato de segurança e outros EPI’S que se fi zerem necessário segundo especifi cação do responsável pela segurança do trabalhador do local de trabalho 3.1. Finalidade que a furadeira, o martelete é mais eficiente na perfuração em concreto, pois o impacto produzido por ele é gerado através de um mecanismo elétrico pneumático, em que o pistão exerce uma compressão de ar que é transmitida indiretamente para a broca.O martelo demolidor, também conhecido como martelete, é uma ferramenta essencial em obras de construção civil, especialmente em projetos residenciais. Sua função principal é quebrar concreto, pedras e outros materiais sólidos, facilitando a demolição de estruturas antigas ou a abertura de novos espaços.O martelete rompedor permite que você rompa ou quebre diversas superfícies onde serviços manuais com marretas, por exemplo, são dificultados. A ferramenta permite romper concreto de maior dureza, demolindo paredes, vigas e abrindo canaletas de passagem de tubulações | F64: CARGO: OPERADOR DE MARTELETE FUNÇÃO: SERVIÇOS OPERAR MARTELETE NA OBRAS CBO: 717010 | G64: PRODUÇÃO
A65: 7824.10 | B65: MOTORISTA COLETIVO | C65: Conduzem e vistoriam ônibus e trólebus de transporte coletivo de passageiros urbanos, metropolitanos e ônibus rodoviários de longas distâncias, verificam itinerário de viagens, controlam o embarque e desembarque de passageiros e os orientam quanto a tarifas, itinerários, pontos de embarque e desembarque e procedimentos no interior do veículo. Executam procedimentos para garantir segurança e o conforto dos passageiros. Habilitam-se periodicamente para conduzir ônibus. | D65: RISCO FISICO: RUIDO, RADIAÇÃO NÃO IONIZANTE, VIBRAÇÕES DE CORPO INTEIRO. RISCO QUÍMICO: POEIRAS MINERAIS (SILICA LIVRE CRISTALIZADA) ; RISCO ERGONÔMICO: POSTURA INADEQUADA RISCO DE ACIDENTE: COLISÃO E TOMBAMENTO, BATIDAS CONTRA, QUEDA DO MESMO NÍVEL | E65: DESCRIÇÃO SINTÉTICA:  Condução de veículos de médio e grande porte. DESCRIÇÃO DETALHADA:  Dirigir veículos de médio e grande porte;  Transportar materiais, equipamentos e documentos;  Verificar, diariamente, as condições de funcionamento do veículo, antes de sua Utilização;  Comunicar a chefia imediata por escrito assinando a comunicação da necessidade de reparos no veículo;  Zelar pela segurança de passageiros no caso de ajudante;  Orientar e auxiliar na carga e descarga de materiais;  Amarrar a carga e conferir;  Atentar – se ao peso da carga e zelar pelo equipamento;  Registrar dados preestabelecidos, sobre a utilização diária do veículo;  Verificar, trocar ou completar, se necessário cotidianamente o óleo, a água e o Combustível;  Efetuar limpeza dos materiais que ficam encostados na caçamba;  Limpar placas, faróis e sinaleiros dos veículos utilizados;  Estar sempre atualizado com as leis e normas de trânsito e respeita- las;  Realizar treinamento na área de atuação, quando solicitado;  Utilizar a carga horária que lhe é pertinente com zelo, dedicação, responsabilidade e a serviço da Empresa;  Manter organizados, limpos e conservados os materiais, máquinas, equipamentos e local de trabalho, que estão sob sua responsabilidade;  Operar de acordo com a capacidade e especificações do fabricante. | F65: CARGO: SERVIÇO DE CONDUÇÃO DE VEÍCULOS DE MÉDIO E GRANDE PORTE. FUNÇÃO: MOTORISTA CBO: 7823-05 | G65: PRODUÇÃO
A66: 715110-M | B66: OP. DE MOTONIVELADORA DE ACABAMENTO | C66: Opera máquina niveladora munida de uma lâmina ou um escarificador e movida por autopropulsão ou por reboque, manipulando os comandos de marcha e direção, para nivelar terrenos na construção de edifícios, estradas, pistas de aeroportos e de outras obras. | D66: FISICO: RUIDO, RADIAÇÃO NÃO IONIZANTES E VIBRAÇÕES DE CORPO INTEIRO. QUÍMICO: POEIRAS MINERAIS(SILICA LIVRE CRISTALIZADA) ERGONOMICO: POSTURA INADEQUADA. ACIDENTE: COLISÃO E TOMBAMENTO, QUEDA DO MESMO NÍVEL, BATIDAS CONTRA. | E66: DESCRIÇÃO SINTÉTICA: Atuar em atividades auxiliares relativas à execução de obras em ger Atuar em atividades relativas à área de operação de máquinas e equipamentos,Operam máquinas e equipamentos, Operador de máquina de terraplenagem, Operador de máquina rodoviária, Operador de tratores diversos, retro escavadeiras, escavadeiras hidráulicas, moto niveladora (Patrol) , ajustando comandos, acionando movimentos das máquinas, Avaliam condições de funcionamento das máquinas e equipamentos, interpretando painel de instrumentos de medição, verificando fonte de alimentação, testando comandos de acionamento, Preparam área para operação dos equipamentos e transportam materiais em máquinas e equipamentos, Trabalham seguindo normas de segurança, higiene, qualidade e proteção ao meio ambiente DESCRIÇÃO DETALHADA: Operar as seguintes máquinas: britador, betoneira, escavadeira hidráulica, pá carregadeira, retro escavadeira, trator, espagidor de asfalto, moto niveladora, rolo compactador, fresadora de asfálto, vibro acabadora entre outras; operar máquinas munidas de uma lâmina ou escarifador, movida por autopropulsão ou por reboque, manipulando os comandos de marcha e direção, para nivelar terrenos na construção de edifícios, estradas, pistas e de outras obras; verificar, trocar ou completar, se necessário cotidianamente o óleo, a água e o combustível;limpar, lubrificar e ajustar as máquinas e seus implementos, de acordo com as instruções de manutenção do fabricante; acompanhar os serviços de manutenção preventiva e corretiva das máquinas e seus implementos e, após executados, efetuar os testes necessários; realizar treinamento na área de atuação, quando solicitado; observar as medidas de segurança ao operar e estacionar as máquinas; anotar, segundo normas estabelecidas, dados e informações sobre trabalhos realizados, consumo de combustível, consertos e outras ocorrências; limpar placas, faróis e sinaleiros das máquinas e equipamentos utilizado; Obedecer a legislação de transito; Vistoriar mangueira,óleo,combustível e agua; Compactar o solo; manter organizados, limpos e conservados os materiais, máquinas, equipamentos e local de trabalho, que estão sob sua responsabilidade; Espalhar material (Asfalto,BGS,BGTC,CBUQ e etc...); Escavar solo; Fresamento da camada asfáltica; Nivelar o solo; Carregar material e cortar buracos; Laminar o solo; Varrer o solo com vassoura mecânica; operar equipamentos e sistemas de informática e outros, quando autorizado e necessário ao exercício das demais atividades; Dirigir veículos leves, mediante autorização prévia, quando necessário ao exercício das demais atividades; Manter organizados, limpos e conservados os materiais, máquinas, equipamentos e local de trabalho, que estão sob sua responsabilidade, incluindo a limpeza da incrustações em laminas, conchas e demais partes do equipamento onde há possibilidade de incrustações de produtos;utilizar a carga horária de lhe é pertinente com dedicação, zelo, responsabilidade e tão somente a serviço da empresa; Responsalidade pelo manuseio do equipamento; Controlar capacidade do equipamento dentro das especificações do fabricante. | F66: CARGO: ESCAVADEIRAS HIDRÁULICAS, FRESADORA DE ASFÁLTO MOTO NIVELADORA, TRATOR DE ESTEIRA, TRATOR D6 E D8, OPERADOR DE FRESADEIRA, RETRO ESCAVAEIRAS E ROLO COMPACTADOR FUNÇÃO: SERVIÇOS OPERACIONAIS DE MÁQUINAS E EQUIPAMENTOS DE OBRAS. CBO: 7151-10 | G66: PRODUÇÃO
A67: 710205 | B67: ENCARREGADO (A) DE OBRA GERAL | C67: Coordena e discutir com os encarregados instruções técnicas do projeto a ser desenvolvido. Interpretarplantas, gráficos e escalas. Orientar e acompanhar a equipe quanto a execução dos trabalhos cumprindo o cronograma. Coordenar a instalação e utilização de equipamentos e estruturas construtivas em canteiros de obra. Participar da instalação do canteiro de obras, demarcando a obra, conforme projeto. | D67: FISICO: RUIDO, RADIAÇÃO NÃO IONIZANTES. ERGONOMICO: POSTURA INADEQUADA. ACIDENTE: ATROPELAMENTO, BATIDAS CONTRA, PROJEÇÃO DE PARTICULAS, QUEDA DE MESMO NÍVEL. | E67: DESCRIÇÃO SINTÉTICA: Atuar em atividades relativas à área de organização, coordenação e supervisão de construção civil e pavimentação. DESCRIÇÃO DETALHADA: Organizar, coordenar e supervisionar grupos de trabalhadores que desenvolvem suas atribuições na área da construção civil, infraestrutura e pavimentação; Garantir o desenvolvimento do processo de execução das obras dentro dos Prazos e normas estabelecidas; Providenciar que as pessoas sob o seu comando utilizem equipamentos de Proteção individual (EPI), de acordo com as normas de segurança em vigor; Empenhar-se em buscar seu próprio desenvolvimento profissional; Buscar o desenvolvimento pessoal e profissional das pessoas que atuam sob seu comando; Acompanhar a evolução profissional das pessoas sob seu comando; Manter ou desenvolver visando o desempenho apropriado de suas funções, Atuar na qualidade de instrutor de treinamentos e outros eventos de igual Natureza, mediante participação prévia em processo de qualificação e Autorização superior; Dirigir veículos leves, mediante autorização prévia, quando necessário ao Exercício das demais atividades; Manter organizados, limpos e conservados os materiais, máquinas, Equipamentos e local de trabalho, que estão sob sua responsabilidade | F67: CARGO: ENCARREGADO GERAL FUNÇÃO: ENCARREGADO GERAL CBO: 123105 | G67: PRODUÇÃO
A68: 410105-O | B68: ENCARREGADO (A) ADMINISTRATIVO DE OBRA | C68: Supervisionam equipes de trabalhadores da construção civil que atuam em usinas de concreto, canteiros de obras civis e ferrovias. Elaboram documentação técnica e controlam recursos produtivos da obra (arranjos físicos, equipamentos, materiais, insumos e equipes de trabalho). Controlam padrões produtivos da obra tais como inspeção da qualidade dos materiais e insumos utilizados, orientação sobre especificação, fluxo e movimentação dos materiais e sobre medidas de segurança dos locais e equipamentos da obra. Administram o cronograma da obra. | D68: FISICO: RUIDO. ERGONOMICO: POSTURA EM PÉ POR LONGOS PERIODOS | E68: DESCRIÇÃO SINTÉTICA: Atuar em atividades relativas à área de organização, coordenação e supervisão de área administrativa. DESCRIÇÃO DETALHADA: Tarefas de departamento pessoal para a gestão dos funcionários • Compra de materiais • Controles financeiros • Crédito e cobrança • Conciliação bancária • Lançamentos contábeis • Elaboração de relatórios gerenciais • Realização de reuniões • Tomada de decisões baseadas em dados e análises • Elaboração de planilhas de controle • Análise de indicadores • Acompanhamento das atividades realizadas pela equipe • Elaboração de O.S. (Ordem de Serviço). • Organização de documentos | F68: CARGO: ENCARREGADO ADMINISTRATIVO-CBO-410105 | G68: ADMINISTRATIVO
A69: 312105-TM | B69: TECNICO EM MEDIÇÃO | C69: Realizam levantamentos topográficos e planialtimétricos. Desenvolvem e legalizam projetos de edificações sob supervisão de um engenheiro civil, planejam a execução, orçam e providenciam suprimentos e supervisionam a execução de obras e serviços. Treinam mão-de-obra e realizam o controle tecnológico de materiais e do solo. | D69: FISICO: RUIDO, RADIAÇÃO NÃO IONIZANTE. ERGONOMICO: POSTURA INADEQUADA ACIDENTE: QUEDA DE MESMO NÍVEL.. | E69: DESCRIÇÃO SINTÉTICA:  Auxiliar na elaborar, medições da obras, assegurar que as medições sejam conduzidas de forma a garantir precisão, rastreabilidade e confiabilidade nos resultados DESCRIÇÃO DETALHADA:  Auxilia na elaborar elaboração de estratégias antes da execução de qualquer medição, garantindo que cada etapa seja conduzida de maneira precisa e confiável. Na metrologia, onde a exatidão dos resultados é crucial, o planejamento da medição desempenha um papel vital  Recursos naturais, serviços de equipamentos urbanos, rurais e regionais, entre outros;  Estudar características, especificações e preparar plantas, orçamentos de custos,técnicas de execução e outros dados, para possibilitar e orientar a construção,manutenção e reparo das obras, dentro dos padrões técnicos exigidos;  Precisão é fundamental para garantir que as medições reflitam com precisão as características do objeto medido. A rastreabilidade, por sua vez, permite a conexão entre as medições realizadas e os padrões de referência. Já a confiabilidade dos resultados é crucial para tomadas de decisão informadas  Realizar treinamento na área de atuação, quando solicitado;  Atuar, na qualidade de instrutor de treinamentos e outros eventos de igual natureza,mediante participação prévia em processo de qualificação e autorização superior;  Operar equipamentos e sistemas de informática e outros, quando autorizado e  Necessário ao exercício das demais atividades;Compreenda as exigências específicas de cada medição. Considere a natureza da grandeza a ser medida e os requisitos de precisão; Determine a precisão necessária para os resultados desejados. Escolha instrumentos que atendam ou excedam essas exigências; Considere a faixa de valores a ser medida. Certifique-se de que os instrumentos selecionados cubram adequadamente essa faixa; Escolha a tecnologia de medição mais apropriada para a aplicação. Considere fatores como resolução, sensibilidade e tempo de resposta. Verifique se os instrumentos estão em conformidade com os padrões de referência. Certifique-se de que são calibrados e mantidos regularmente; steja ciente das limitações orçamentárias e procure um equilíbrio entre custo e qualidade. Priorize a qualidade do instrumento, pois isso impactará diretamente na confiabilidade das medições. Ao seguir esses passos, você estará mais bem preparado para escolher os instrumentos que melhor atendem às necessidades específicas de suas medições, garantindo resultados precisos e confiáveis.  Dirigir veículos leves, mediante autorização prévia, quando necessário ao exercício das demais atividades; | F69: CARGO: TECNICO EM MEDIÇÕES FUNÇÃO: TECNICO EM MEDIÇÕES CBO: | G69: ADMINISTRATIVO
A70: 2524-05 | B70: ANALISTA DE RECRUTAMENTO E SELEÇÃO | C70: Administram pessoal e plano de cargos e salários, promovem ações de treinamento e de desenvolvimento de pessoal. Efetuam processo de recrutamento e de seleção, geram plano de benefícios e promovem ações de qualidade de vida e assistência aos empregados. Administram relações de trabalho e coordenam sistemas de avaliação de desempenho. No desenvolvimento das atividades, mobilizam um conjunto de capacidades comunicativas. | D70: FISICO: RUIDO, RADIAÇÃO NÃO IONIZANTE. ERGONOMICO: POSTURA INADEQUADA ACIDENTE: QUEDA DE MESMO NÍVEL | E70: DESCRIÇÃO SINTÉTICA:  Gerenciam pessoas e planejam cargos e salários, promovendo ações de treinamento e desenvolvimento de pessoas. Realizam um processo de recrutamento e seleção, gerando planos de benefícios e promovendo qualidade de vida e atendimento aos colaboradores DESCRIÇÃO DETALHADA:  Recebimento de documentos e correspondências, assim como sua organização.  Digitação de documentos.  Elaboração e preenchimento de planilhas de controle interno.  Auxílio ao departamento financeiro com lançamento.  Auxiliar operações diárias das funções e obrigações de RH  Compilar e atualizar registros do funcionário (cópias impressas e digitais)  Processar a documentação e preparar relatórios relacionados com as atividades do pessoal (agenciamento, recrutamento, treinamento, reclamações, avaliações de desempenho etc.)  Solicitações de funcionário relacionadas com problemas, regras e regulamentos de recursos humanos  Auxiliar na preparação da folha de pagamento fornecendo dados relevantes (ausências, bônus, licenças etc.)  Elaborar Relatórios e documentação mensais ao cliente  Conduzir a orientação inicial para funcionários recentemente contratados  Auxiliar os nossos recrutadores na seleção de candidatos e atualizar o nosso banco de dados.  Apoiar os processos de admissão, integração e desligamento;  Elaboração e preenchimento de planilhas de controles. Exemplo: controle de férias dos colaboradores;  Fazer a gestão de ponto;  Responder dúvidas e solicitações dos colaboradores acerca dos processos do RH  Auxiliar o no lançamento benefícios e adicionais que incidem na folha de pagamento  Suporte as rotinas do departamento Pessoal;  Atendimento interno à colaboradores. | F70: CARGO: ANALISTA DE RECRUTAMENTO E SELEÇÃO CBO- 2524-05 | G70: ADMINISTRATIVO
A71: 7151.40 | B71: MOTORISTA ESPARGIDOR | C71: Planejam o trabalho, realizam manutenção básica de máquinas pesadas e as operam. Removem solo e material orgânico bota-fora , drenam solos e executam construção de aterros. Realizam acabamento em pavimentos e cravam estacas. | D71: RISCO FISICO: RUIDO, RADIAÇÃO NÃO IONIZANTE, VIBRAÇÕES DE CORPO INTEIRO. RISCO QUÍMICO: POEIRAS MINERAIS (SILICA LIVRE CRISTALIZADA) ; RISCO ERGONÔMICO: POSTURA INADEQUADA RISCO DE ACIDENTE: COLISÃO E TOMBAMENTO, BATIDAS CONTRA, QUEDA DO MESMO NÍVEL | E71: DESCRIÇÃO SINTÉTICA:  Condução de veículos de médio e grande porte. DESCRIÇÃO DETALHADA:  Dirigir veículos de médio e grande porte;  Transportar materiais, equipamentos e documentos;  Verificar, diariamente, as condições de funcionamento do veículo, antes de sua Utilização;  Comunicar a chefia imediata por escrito assinando a comunicação da necessidade de reparos no veículo;  Zelar pela segurança de passageiros no caso de ajudante;  Orientar e auxiliar na carga e descarga de materiais;  Amarrar a carga e conferir;  Atentar – se ao peso da carga e zelar pelo equipamento;  Registrar dados preestabelecidos, sobre a utilização diária do veículo;  Verificar, trocar ou completar, se necessário cotidianamente o óleo, a água e o Combustível;  Efetuar limpeza dos materiais que ficam encostados na caçamba;  Limpar placas, faróis e sinaleiros dos veículos utilizados;  Estar sempre atualizado com as leis e normas de trânsito e respeita- las;  Realizar treinamento na área de atuação, quando solicitado;  Utilizar a carga horária que lhe é pertinente com zelo, dedicação, responsabilidade e a serviço da Empresa;  Manter organizados, limpos e conservados os materiais, máquinas, equipamentos e local de trabalho, que estão sob sua responsabilidade;  Operar de acordo com a capacidade e especificações do fabricante. | F71: CARGO: SERVIÇO DE CONDUÇÃO DE VEÍCULOS DE MÉDIO E GRANDE PORTE. FUNÇÃO: MOTORISTA CBO: 7823-05 | G71: PRODUÇÃO
A72: 2149-35 | B72: AUXILIAR SEGURANÇA DO TRABALHO | C72: Controlam perdas de processos, produtos e serviços ao identificar, determinar e analisar causas de perdas, estabelecendo plano de ações preventivas e corretivas. Desenvolvem, testam e supervisionam sistemas, processos e métodos produtivos, gerenciam atividades de segurança do trabalho e do meio ambiente, planejam empreendimentos e atividades produtivas e coordenam equipes, treinamentos e atividades de trabalho. | D72: FISICO: RUIDO, RADIAÇÃO NÃO IONIZANTE. ERGONOMICO: POSTURA INADEQUADA ACIDENTE:QUEDA DE MESMO NÍVEL. | E72: DESCRIÇÃO SINTÉTICA:  Orienta os funcionários a utilizar os EPI's de forma correta, estabelece normas de segurança, informa sobre meios de prevenção de acidentes, inspeciona áreas de trabalho a fim de verificar as condições do ambiente e checa equipamentos usados para determinar possíveis fatores de risco.Aplicar os conhecimentos de segurança e medicina do trabalho, de modo a reduzir e eliminar os riscos à saúde do trabalhador. DESCRIÇÃO DETALHADA:  Principal responsabilidade é minimizar, controlar e eliminar os riscos à saúde dos trabalhadores.Orientar e coordenar o sistema de segurança do trabalho, investigando riscos E causas de acidentes e analisando esquemas de prevenção, para garantir a Integridade dos colaboradores;  Inspecionar locais, instalações e equipamentos coletivos e individuais, observando as condições de trabalho, para determinar fatores e riscos de acidentes;  Estabelecer normas e dispositivos de segurança, sugerindo eventuais modificações nos equipamentos e instalações e verificando sua observância, para prevenir acidentes;  Inspecionar os postos de combate a incêndios, examinando as mangueiras, Hidrantes, extintores e equipamentos de proteção contra incêndios, para certificar-se de suas perfeitas condições de funcionamento;  Comunicar os resultados de suas inspeções, elaborando relatórios, para propor a reparação ou renovação do equipamento de extinção de incêndios e outras medidas de segurança;  Registrar acidentes ocorridos, examinando as condições da ocorrência, para  Identificar suas causas e propor as providências cabíveis;  Manter contato com os serviços médico e social da empresa ou de outra instituição,utilizando os meios de comunicação oficiais, para facilitar o atendimento necessário aos acidentados;  Registrar irregularidades ocorridas, anotando-as em formulários próprios e elaborando estatísticas de acidentes, para obter subsídios destinados à melhoria das medidas de segurança;  Buscar seu próprio desenvolvimento profissional;  Instruir os funcionários da empresa sobre normas de segurança, combate a incêndios e demais medidas de prevenção de acidentes, ministrando palestras e treinamento,para que possam agir acertadamente em casos de emergência; É o profissional responsável pela prevenção de acidentes por promover a qualidade de vida no ambiente de trabalho e zelar pela segurança física dos empregados. | F72: CARGO: AULIAR SEGURANÇA DO TRABALHO FUNÇÃO: GESTÃO SMS E OUTROS. CBO: 351605 | G72: PRODUÇÃO
A73: 214010 | B73: TECNICO EM MEIO AMBIENTE | C73: Elaboram e implantam projetos ambientais , gerenciam a implementação do sistema de Gestão Ambiental (SGA) nas empresas, implementam ações de controle de emissão de poluentes, administram resíduos e procedimentos de remediação. Podem prestar consultoria, assistência e assessoria. | D73: FISICO: RUIDO, RADIAÇÃO NÃO IONIZANTE. ERGONOMICO: POSTURA INADEQUADA ACIDENTE: QUEDA DE MESMO NÍVEL.. | E73: DESCRIÇÃO SINTÉTICA:  Profissionais que atuar na gestão e preservação dos recursos naturais, com foco em soluções sustentáveis para os desafios ambientais DESCRIÇÃO DETALHADA:  Responsável por monitorar e propor soluções para questões ambientais, como gestão de resíduos, análise da qualidade do ar, solo e água, e elaboração de projetos de preservação. Ele também atua na fiscalização de atividades para garantir que estejam de acordo com a legislação ambiental e realiza campanhas de conscientização e educação. Além disso, pode prestar consultoria e assessoria a empresas, orientando sobre práticas sustentáveis e ajudando na obtenção de licenças ambientais. Em suma, seu trabalho busca promover a sustentabilidade e a recuperação de áreas degradadas.  Recursos naturais, serviços de equipamentos urbanos, rurais e regionais, entre outros;  Avaliar os impactos causados por resíduos sólidos, atmosféricos e águas residuais, identificando as consequências sobre o ambiente, propondo estratégias de gerenciamento, redução, reciclagem, tratamento e disposição final adequada;  Auxiliar de fiscalização ambiental é responsável por auxiliar em vistorias, visitas e análises técnicas, em diferentes ambientes, como obras, indústrias, áreas de preservação ambiental, entre outros;  Realizar treinamento na área de atuação, quando solicitado;  Atuar, na qualidade de instrutor de treinamentos e outros eventos de igual natureza,mediante participação prévia em processo de temas Ambientais;  Operar equipamentos e sistemas de informática e outros, quando autorizado e  Desempenha diversas funções relacionadas à preservação, monitoramento e gestão ambiental em diferentes setores e contextos. Suas responsabilidades podem variar, mas geralmente incluem a realização de levantamentos e análises ambientais, elaboração e implementação de planos de gestão ambiental, acompanhamento de licenciamentos ambientais, fiscalização de atividades que impactam o meio ambiente, elaboração de relatórios técnicos, educação ambiental, entre outras atividades. Eles precisam ter um conhecimento sólido sobre legislação ambiental, técnicas de monitoramento e avaliação ambiental, além de habilidades em comunicação e trabalho em equipe. No dia a dia, um técnico em meio ambiente pode estar envolvido em projetos como a recuperação de áreas degradadas, o controle da poluição, a gestão de resíduos, a implementação de práticas sustentáveis em empresas, entre outros. Seu trabalho é fundamental para garantir o equilíbrio entre o desenvolvimento econômico e a preservação dos recursos naturais, visando a sustentabilidade ambiental e o bem-estar das gerações presentes e futuras.  Dirigir veículos leves, mediante autorização prévia, quando necessário ao exercício das demais atividades; | F73: CARGO: TECNICO EM MEIO AMBIENTE FUNÇÃO: TECNICO EM MEIO AMBIENTE CBO:214010 | G73: PRODUÇÃO
A74: 913120 | B74: MECÂNICO | C74: Consertam máquinas e equipamentos, requisitando peças para reposição, montando máquinas equipamentos e acessórios, conforme especificações do fabricante. Organizam o local de trabalho para manutenção e avaliam as condições de máquinas e equipamentos. Elaboram propostas de serviços e orçamentos, relacionando causas de defeitos e listando peças para substituição. Trabalham seguindo normas de segurança e qualidade. | D74: FISICO: RUIDO, RADIAÇÃO NÃO IONIZANTE. QUIMICO: ÓLEOS LUBRIFICANTES E GRAXAS. ERGONOMICO: POSTURA INADEQUADA ACIDENTE: CORTE PERFURAÇÕES E QUEDA DE MESMO NIVEL. | E74: DESCRIÇÃO SINTÉTICA:  Atuar em atividades relativas à área de montagem, desmontagem, reparo e manutenção de máquinas pesadas. DESCRIÇÃO DETALHADA:  Examinar a máquina ou equipamentos inspecionando-os para determinar os defeitos e anormalidades do funcionamento;  Orientar e executar serviços de manutenção mecânica corretiva e preventiva em veículos pesados, máquinas, motores e equipamentos;  Reparar defeitos, substituindo peças, fazendo ajustes, regulagens e lubrificação,segundo orientações;  Fazer o desmonte, limpeza e a montagem do motor, órgãos de transmissão, diferencial e outras partes;  Providenciar o recondicionamento do equipamento elétrico, o alinhamento da direção e regulagem dos faróis do veículo;  Retirar forros, cintos, revestimentos e carpete e providenciar seu reparo ou manutenção;  Efetuar ajustes, reparos, reformas e manutenções em geral em equipamentos  Diversos, interpretando manuais e normas técnicas;  Realizar diagnósticos técnicos e realizar serviços corretivos e de manutenção, peças,ferramentas e mão-de-obra necessária;  Identificar e prescrever necessidades de serviços de terceiros, mediante relatório escrito e assinado, encaminhado a chefia imediata;  Utilizar a carga horária de lhe é pertinente com dedicação, zelo, responsabilidade e tão somente a serviço da empresa;  Realizar treinamento na área de atuação, quando solicitado;  Zelar pela limpeza, conservação e manutenção dos aparelhos, ferramentas e ambiente de trabalho;Lubrificar máquinas e componentes; Ajustar, trocar, reparar e consertar componentes e partes da máquina; Montar e desmontar máquinas e equipamentos; Realizar inspeções e medições periódicas (manutenção preventiva);Executa processos de manutenção mecânica de máquinas industriais, desmontando, montando, recuperando ou substituindo peças e máquinas, respeitando procedimentos e normas técnicas de qualidade, segurança, meio ambiente e saúde.especializado em agricultura, mineração ou material rodante pesado: escavadeiras, retroescavadeiras, rolo compactador, moto niveladora e tratores, etc. uma das funções do mecânico de máquinas pesadas é planejar, supervisionar e participar dos trabalhos de manutenção corretiva e preventiva. | F74: CARGO: MECÂNICO FUNÇÃO: MECÂNICO CBO: 913120 | G74: OFICINA
A75: 7102.15 | B75: ENCARREGADO (A) DE TERRAPLANAGEM | C75: Desenvolvem projetos de engenharia civil, executam obras, planejam, orçam e contratam empreendimentos, coordenam a operação e a manutenção dos mesmos. Controlam a qualidade dos suprimentos e serviços comprados e executados. Elaboram normas e documentação técnica. Podem prestar consultorias. | D75: FISICO: RUIDO, RADIAÇÃO NÃO IONIZANTES. ERGONOMICO: POSTURA INADEQUADA. ACIDENTE: ATROPELAMENTO, BATIDAS CONTRA, PROJEÇÃO DE PARTICULAS, QUEDA DE MESMO NÍVEL. | E75: DESCRIÇÃO SINTÉTICA: Atuar em atividades relativas à área de organização, coordenação e supervisão de construção civil, pavimentação e terraplanagem. DESCRIÇÃO DETALHADA: Organizar, coordenar e supervisionar grupos de trabalhadores que desenvolvem suas atribuições na área da construção civil, infraestrutura e pavimentação; Garantir o desenvolvimento do processo de execução das obras dentro dos Prazos e normas estabelecidas; Providenciar que as pessoas sob o seu comando utilizem equipamentos de Proteção individual (EPI), de acordo com as normas de segurança em vigor; Empenhar-se em buscar seu próprio desenvolvimento profissional; Buscar o desenvolvimento pessoal e profissional das pessoas que atuam sob seu comando; Acompanhar a evolução profissional das pessoas sob seu comando; Manter ou desenvolver visando o desempenho apropriado de suas funções, Atuar na qualidade de instrutor de treinamentos e outros eventos de igual Natureza, mediante participação prévia em processo de qualificação e Autorização superior; Dirigir veículos leves, mediante autorização prévia, quando necessário ao Exercício das demais atividades; Manter organizados, limpos e conservados os materiais, máquinas, Equipamentos e local de trabalho, que estão sob sua responsabilidade | F75: CARGO: ENCARREGADO DE TERRAPLANAGEM FUNÇÃO: ENCARREGADO DE TERRAPLANAGEM CBO: 7102.15 | G75: PRODUÇÃO
